Workbook

Sheet Summary
A1: Sub Sheet | B1: Playbook | C1: Total | D1: Head Pass | E1: Head Fail | F1: Head Pass % | G1: Head Fail % | H1: Sub Pass | I1: Sub Fail | J1: Sub Pass % | K1: Sub Fail %
A2: AG_change-account | B2: Agent | C2: =D2+E2 -> 60 | D2: =COUNTIF('AG_change-account'!D2:D61,TRUE()) -> 60 | E2: =COUNTIF('AG_change-account'!D2:D61,FALSE()) -> 0 | F2: =IF($C2=0,0,D2/$C2) -> 1 | G2: =IF($C2=0,0,E2/$C2) -> 0 | H2: =COUNTIF('AG_change-account'!G2:G61,TRUE()) -> 60 | I2: =COUNTIF('AG_change-account'!G2:G61,FALSE()) -> 0 | J2: =IF($C2=0,0,H2/$C2) -> 1 | K2: =IF($C2=0,0,I2/$C2) -> 0
A3: AG_change-address | B3: Agent | C3: =D3+E3 -> 60 | D3: =COUNTIF('AG_change-address'!D2:D61,TRUE()) -> 60 | E3: =COUNTIF('AG_change-address'!D2:D61,FALSE()) -> 0 | F3: =IF($C3=0,0,D3/$C3) -> 1 | G3: =IF($C3=0,0,E3/$C3) -> 0 | H3: =COUNTIF('AG_change-address'!G2:G61,TRUE()) -> 60 | I3: =COUNTIF('AG_change-address'!G2:G61,FALSE()) -> 0 | J3: =IF($C3=0,0,H3/$C3) -> 1 | K3: =IF($C3=0,0,I3/$C3) -> 0
A4: AG_change-admin | B4: Agent | C4: =D4+E4 -> 60 | D4: =COUNTIF('AG_change-admin'!D2:D61,TRUE()) -> 60 | E4: =COUNTIF('AG_change-admin'!D2:D61,FALSE()) -> 0 | F4: =IF($C4=0,0,D4/$C4) -> 1 | G4: =IF($C4=0,0,E4/$C4) -> 0 | H4: =COUNTIF('AG_change-admin'!G2:G61,TRUE()) -> 60 | I4: =COUNTIF('AG_change-admin'!G2:G61,FALSE()) -> 0 | J4: =IF($C4=0,0,H4/$C4) -> 1 | K4: =IF($C4=0,0,I4/$C4) -> 0
A5: AG_change-dependent_info | B5: Agent | C5: =D5+E5 -> 60 | D5: =COUNTIF('AG_change-dependent_info'!D2:D61,TRUE()) -> 60 | E5: =COUNTIF('AG_change-dependent_info'!D2:D61,FALSE()) -> 0 | F5: =IF($C5=0,0,D5/$C5) -> 1 | G5: =IF($C5=0,0,E5/$C5) -> 0 | H5: =COUNTIF('AG_change-dependent_info'!G2:G61,TRUE()) -> 60 | I5: =COUNTIF('AG_change-dependent_info'!G2:G61,FALSE()) -> 0 | J5: =IF($C5=0,0,H5/$C5) -> 1 | K5: =IF($C5=0,0,I5/$C5) -> 0
A6: AG_change-group_info | B6: Agent | C6: =D6+E6 -> 60 | D6: =COUNTIF('AG_change-group_info'!D2:D61,TRUE()) -> 59 | E6: =COUNTIF('AG_change-group_info'!D2:D61,FALSE()) -> 1 | F6: =IF($C6=0,0,D6/$C6) -> 0.98333333 | G6: =IF($C6=0,0,E6/$C6) -> 0.016666667 | H6: =COUNTIF('AG_change-group_info'!G2:G61,TRUE()) -> 59 | I6: =COUNTIF('AG_change-group_info'!G2:G61,FALSE()) -> 1 | J6: =IF($C6=0,0,H6/$C6) -> 0.98333333 | K6: =IF($C6=0,0,I6/$C6) -> 0.016666667
A7: AG_change-provider | B7: Agent | C7: =D7+E7 -> 60 | D7: =COUNTIF('AG_change-provider'!D2:D61,TRUE()) -> 60 | E7: =COUNTIF('AG_change-provider'!D2:D61,FALSE()) -> 0 | F7: =IF($C7=0,0,D7/$C7) -> 1 | G7: =IF($C7=0,0,E7/$C7) -> 0 | H7: =COUNTIF('AG_change-provider'!G2:G61,TRUE()) -> 60 | I7: =COUNTIF('AG_change-provider'!G2:G61,FALSE()) -> 0 | J7: =IF($C7=0,0,H7/$C7) -> 1 | K7: =IF($C7=0,0,I7/$C7) -> 0
A8: AG_find-provider | B8: Agent | C8: =D8+E8 -> 60 | D8: =COUNTIF('AG_find-provider'!D2:D61,TRUE()) -> 60 | E8: =COUNTIF('AG_find-provider'!D2:D61,FALSE()) -> 0 | F8: =IF($C8=0,0,D8/$C8) -> 1 | G8: =IF($C8=0,0,E8/$C8) -> 0 | H8: =COUNTIF('AG_find-provider'!G2:G61,TRUE()) -> 60 | I8: =COUNTIF('AG_find-provider'!G2:G61,FALSE()) -> 0 | J8: =IF($C8=0,0,H8/$C8) -> 1 | K8: =IF($C8=0,0,I8/$C8) -> 0
A9: AG_inquire-account_status | B9: Agent | C9: =D9+E9 -> 60 | D9: =COUNTIF('AG_inquire-account_status'!D2:D61,TRUE()) -> 60 | E9: =COUNTIF('AG_inquire-account_status'!D2:D61,FALSE()) -> 0 | F9: =IF($C9=0,0,D9/$C9) -> 1 | G9: =IF($C9=0,0,E9/$C9) -> 0 | H9: =COUNTIF('AG_inquire-account_status'!G2:G61,TRUE()) -> 60 | I9: =COUNTIF('AG_inquire-account_status'!G2:G61,FALSE()) -> 0 | J9: =IF($C9=0,0,H9/$C9) -> 1 | K9: =IF($C9=0,0,I9/$C9) -> 0
A10: AG_report-problem_account | B10: Agent | C10: =D10+E10 -> 60 | D10: =COUNTIF('AG_report-problem_account'!D2:D61,TRUE()) -> 60 | E10: =COUNTIF('AG_report-problem_account'!D2:D61,FALSE()) -> 0 | F10: =IF($C10=0,0,D10/$C10) -> 1 | G10: =IF($C10=0,0,E10/$C10) -> 0 | H10: =COUNTIF('AG_report-problem_account'!G2:G61,TRUE()) -> 60 | I10: =COUNTIF('AG_report-problem_account'!G2:G61,FALSE()) -> 0 | J10: =IF($C10=0,0,H10/$C10) -> 1 | K10: =IF($C10=0,0,I10/$C10) -> 0
A11: AG_request-address | B11: Agent | C11: =D11+E11 -> 60 | D11: =COUNTIF('AG_request-address'!D2:D61,TRUE()) -> 57 | E11: =COUNTIF('AG_request-address'!D2:D61,FALSE()) -> 3 | F11: =IF($C11=0,0,D11/$C11) -> 0.95 | G11: =IF($C11=0,0,E11/$C11) -> 0.05 | H11: =COUNTIF('AG_request-address'!G2:G61,TRUE()) -> 56 | I11: =COUNTIF('AG_request-address'!G2:G61,FALSE()) -> 4 | J11: =IF($C11=0,0,H11/$C11) -> 0.93333333 | K11: =IF($C11=0,0,I11/$C11) -> 0.066666667
A12: AG_request-agent | B12: Agent | C12: =D12+E12 -> 60 | D12: =COUNTIF('AG_request-agent'!D2:D61,TRUE()) -> 59 | E12: =COUNTIF('AG_request-agent'!D2:D61,FALSE()) -> 1 | F12: =IF($C12=0,0,D12/$C12) -> 0.98333333 | G12: =IF($C12=0,0,E12/$C12) -> 0.016666667 | H12: =COUNTIF('AG_request-agent'!G2:G61,TRUE()) -> 59 | I12: =COUNTIF('AG_request-agent'!G2:G61,FALSE()) -> 1 | J12: =IF($C12=0,0,H12/$C12) -> 0.98333333 | K12: =IF($C12=0,0,I12/$C12) -> 0.016666667
A13: AG_request-agent_specific | B13: Agent | C13: =D13+E13 -> 60 | D13: =COUNTIF('AG_request-agent_specific'!D2:D61,TRUE()) -> 59 | E13: =COUNTIF('AG_request-agent_specific'!D2:D61,FALSE()) -> 1 | F13: =IF($C13=0,0,D13/$C13) -> 0.98333333 | G13: =IF($C13=0,0,E13/$C13) -> 0.016666667 | H13: =COUNTIF('AG_request-agent_specific'!G2:G61,TRUE()) -> 59 | I13: =COUNTIF('AG_request-agent_specific'!G2:G61,FALSE()) -> 1 | J13: =IF($C13=0,0,H13/$C13) -> 0.98333333 | K13: =IF($C13=0,0,I13/$C13) -> 0.016666667
A14: AG_request-contact_info | B14: Agent | C14: =D14+E14 -> 60 | D14: =COUNTIF('AG_request-contact_info'!D2:D61,TRUE()) -> 58 | E14: =COUNTIF('AG_request-contact_info'!D2:D61,FALSE()) -> 2 | F14: =IF($C14=0,0,D14/$C14) -> 0.96666667 | G14: =IF($C14=0,0,E14/$C14) -> 0.033333333 | H14: =COUNTIF('AG_request-contact_info'!G2:G61,TRUE()) -> 58 | I14: =COUNTIF('AG_request-contact_info'!G2:G61,FALSE()) -> 2 | J14: =IF($C14=0,0,H14/$C14) -> 0.96666667 | K14: =IF($C14=0,0,I14/$C14) -> 0.033333333
A15: AG_respond-letter | B15: Agent | C15: =D15+E15 -> 60 | D15: =COUNTIF('AG_respond-letter'!D2:D61,TRUE()) -> 60 | E15: =COUNTIF('AG_respond-letter'!D2:D61,FALSE()) -> 0 | F15: =IF($C15=0,0,D15/$C15) -> 1 | G15: =IF($C15=0,0,E15/$C15) -> 0 | H15: =COUNTIF('AG_respond-letter'!G2:G61,TRUE()) -> 60 | I15: =COUNTIF('AG_respond-letter'!G2:G61,FALSE()) -> 0 | J15: =IF($C15=0,0,H15/$C15) -> 1 | K15: =IF($C15=0,0,I15/$C15) -> 0
A16: AG_return-call | B16: Agent | C16: =D16+E16 -> 60 | D16: =COUNTIF('AG_return-call'!D2:D61,TRUE()) -> 60 | E16: =COUNTIF('AG_return-call'!D2:D61,FALSE()) -> 0 | F16: =IF($C16=0,0,D16/$C16) -> 1 | G16: =IF($C16=0,0,E16/$C16) -> 0 | H16: =COUNTIF('AG_return-call'!G2:G61,TRUE()) -> 60 | I16: =COUNTIF('AG_return-call'!G2:G61,FALSE()) -> 0 | J16: =IF($C16=0,0,H16/$C16) -> 1 | K16: =IF($C16=0,0,I16/$C16) -> 0
A17: AG_say-something_else | B17: Agent | C17: =D17+E17 -> 60 | D17: =COUNTIF('AG_say-something_else'!D2:D61,TRUE()) -> 59 | E17: =COUNTIF('AG_say-something_else'!D2:D61,FALSE()) -> 1 | F17: =IF($C17=0,0,D17/$C17) -> 0.98333333 | G17: =IF($C17=0,0,E17/$C17) -> 0.016666667 | H17: =COUNTIF('AG_say-something_else'!G2:G61,TRUE()) -> 59 | I17: =COUNTIF('AG_say-something_else'!G2:G61,FALSE()) -> 1 | J17: =IF($C17=0,0,H17/$C17) -> 0.98333333 | K17: =IF($C17=0,0,I17/$C17) -> 0.016666667
A18: AG_terminate-employee | B18: Agent | C18: =D18+E18 -> 60 | D18: =COUNTIF('AG_terminate-employee'!D2:D61,TRUE()) -> 59 | E18: =COUNTIF('AG_terminate-employee'!D2:D61,FALSE()) -> 1 | F18: =IF($C18=0,0,D18/$C18) -> 0.98333333 | G18: =IF($C18=0,0,E18/$C18) -> 0.016666667 | H18: =COUNTIF('AG_terminate-employee'!G2:G61,TRUE()) -> 59 | I18: =COUNTIF('AG_terminate-employee'!G2:G61,FALSE()) -> 1 | J18: =IF($C18=0,0,H18/$C18) -> 0.98333333 | K18: =IF($C18=0,0,I18/$C18) -> 0.016666667
A19: AG_vague-account | B19: Agent | C19: =D19+E19 -> 60 | D19: =COUNTIF('AG_vague-account'!D2:D61,TRUE()) -> 58 | E19: =COUNTIF('AG_vague-account'!D2:D61,FALSE()) -> 2 | F19: =IF($C19=0,0,D19/$C19) -> 0.96666667 | G19: =IF($C19=0,0,E19/$C19) -> 0.033333333 | H19: =COUNTIF('AG_vague-account'!G2:G61,TRUE()) -> 58 | I19: =COUNTIF('AG_vague-account'!G2:G61,FALSE()) -> 2 | J19: =IF($C19=0,0,H19/$C19) -> 0.96666667 | K19: =IF($C19=0,0,I19/$C19) -> 0.033333333
A20: AG_vague-address | B20: Agent | C20: =D20+E20 -> 60 | D20: =COUNTIF('AG_vague-address'!D2:D61,TRUE()) -> 59 | E20: =COUNTIF('AG_vague-address'!D2:D61,FALSE()) -> 1 | F20: =IF($C20=0,0,D20/$C20) -> 0.98333333 | G20: =IF($C20=0,0,E20/$C20) -> 0.016666667 | H20: =COUNTIF('AG_vague-address'!G2:G61,TRUE()) -> 59 | I20: =COUNTIF('AG_vague-address'!G2:G61,FALSE()) -> 1 | J20: =IF($C20=0,0,H20/$C20) -> 0.98333333 | K20: =IF($C20=0,0,I20/$C20) -> 0.016666667
A21: AG_vague-appointment | B21: Agent | C21: =D21+E21 -> 60 | D21: =COUNTIF('AG_vague-appointment'!D2:D61,TRUE()) -> 60 | E21: =COUNTIF('AG_vague-appointment'!D2:D61,FALSE()) -> 0 | F21: =IF($C21=0,0,D21/$C21) -> 1 | G21: =IF($C21=0,0,E21/$C21) -> 0 | H21: =COUNTIF('AG_vague-appointment'!G2:G61,TRUE()) -> 60 | I21: =COUNTIF('AG_vague-appointment'!G2:G61,FALSE()) -> 0 | J21: =IF($C21=0,0,H21/$C21) -> 1 | K21: =IF($C21=0,0,I21/$C21) -> 0
A22: AG_vague-disability | B22: Agent | C22: =D22+E22 -> 60 | D22: =COUNTIF('AG_vague-disability'!D2:D61,TRUE()) -> 60 | E22: =COUNTIF('AG_vague-disability'!D2:D61,FALSE()) -> 0 | F22: =IF($C22=0,0,D22/$C22) -> 1 | G22: =IF($C22=0,0,E22/$C22) -> 0 | H22: =COUNTIF('AG_vague-disability'!G2:G61,TRUE()) -> 60 | I22: =COUNTIF('AG_vague-disability'!G2:G61,FALSE()) -> 0 | J22: =IF($C22=0,0,H22/$C22) -> 1 | K22: =IF($C22=0,0,I22/$C22) -> 0
A23: AG_vague-employee | B23: Agent | C23: =D23+E23 -> 60 | D23: =COUNTIF('AG_vague-employee'!D2:D61,TRUE()) -> 60 | E23: =COUNTIF('AG_vague-employee'!D2:D61,FALSE()) -> 0 | F23: =IF($C23=0,0,D23/$C23) -> 1 | G23: =IF($C23=0,0,E23/$C23) -> 0 | H23: =COUNTIF('AG_vague-employee'!G2:G61,TRUE()) -> 60 | I23: =COUNTIF('AG_vague-employee'!G2:G61,FALSE()) -> 0 | J23: =IF($C23=0,0,H23/$C23) -> 1 | K23: =IF($C23=0,0,I23/$C23) -> 0
A24: AG_vague-group_info | B24: Agent | C24: =D24+E24 -> 60 | D24: =COUNTIF('AG_vague-group_info'!D2:D61,TRUE()) -> 60 | E24: =COUNTIF('AG_vague-group_info'!D2:D61,FALSE()) -> 0 | F24: =IF($C24=0,0,D24/$C24) -> 1 | G24: =IF($C24=0,0,E24/$C24) -> 0 | H24: =COUNTIF('AG_vague-group_info'!G2:G61,TRUE()) -> 60 | I24: =COUNTIF('AG_vague-group_info'!G2:G61,FALSE()) -> 0 | J24: =IF($C24=0,0,H24/$C24) -> 1 | K24: =IF($C24=0,0,I24/$C24) -> 0
A25: AG_vague-inquire | B25: Agent | C25: =D25+E25 -> 60 | D25: =COUNTIF('AG_vague-inquire'!D2:D61,TRUE()) -> 59 | E25: =COUNTIF('AG_vague-inquire'!D2:D61,FALSE()) -> 1 | F25: =IF($C25=0,0,D25/$C25) -> 0.98333333 | G25: =IF($C25=0,0,E25/$C25) -> 0.016666667 | H25: =COUNTIF('AG_vague-inquire'!G2:G61,TRUE()) -> 59 | I25: =COUNTIF('AG_vague-inquire'!G2:G61,FALSE()) -> 1 | J25: =IF($C25=0,0,H25/$C25) -> 0.98333333 | K25: =IF($C25=0,0,I25/$C25) -> 0.016666667
A26: AG_vague-membership | B26: Agent | C26: =D26+E26 -> 60 | D26: =COUNTIF('AG_vague-membership'!D2:D61,TRUE()) -> 60 | E26: =COUNTIF('AG_vague-membership'!D2:D61,FALSE()) -> 0 | F26: =IF($C26=0,0,D26/$C26) -> 1 | G26: =IF($C26=0,0,E26/$C26) -> 0 | H26: =COUNTIF('AG_vague-membership'!G2:G61,TRUE()) -> 60 | I26: =COUNTIF('AG_vague-membership'!G2:G61,FALSE()) -> 0 | J26: =IF($C26=0,0,H26/$C26) -> 1 | K26: =IF($C26=0,0,I26/$C26) -> 0
A27: AG_vague-problem | B27: Agent | C27: =D27+E27 -> 60 | D27: =COUNTIF('AG_vague-problem'!D2:D61,TRUE()) -> 58 | E27: =COUNTIF('AG_vague-problem'!D2:D61,FALSE()) -> 2 | F27: =IF($C27=0,0,D27/$C27) -> 0.96666667 | G27: =IF($C27=0,0,E27/$C27) -> 0.033333333 | H27: =COUNTIF('AG_vague-problem'!G2:G61,TRUE()) -> 58 | I27: =COUNTIF('AG_vague-problem'!G2:G61,FALSE()) -> 2 | J27: =IF($C27=0,0,H27/$C27) -> 0.96666667 | K27: =IF($C27=0,0,I27/$C27) -> 0.033333333
A28: AG_vague-service | B28: Agent | C28: =D28+E28 -> 60 | D28: =COUNTIF('AG_vague-service'!D2:D61,TRUE()) -> 59 | E28: =COUNTIF('AG_vague-service'!D2:D61,FALSE()) -> 1 | F28: =IF($C28=0,0,D28/$C28) -> 0.98333333 | G28: =IF($C28=0,0,E28/$C28) -> 0.016666667 | H28: =COUNTIF('AG_vague-service'!G2:G61,TRUE()) -> 59 | I28: =COUNTIF('AG_vague-service'!G2:G61,FALSE()) -> 1 | J28: =IF($C28=0,0,H28/$C28) -> 0.98333333 | K28: =IF($C28=0,0,I28/$C28) -> 0.016666667
A29: AG_vague-status | B29: Agent | C29: =D29+E29 -> 60 | D29: =COUNTIF('AG_vague-status'!D2:D61,TRUE()) -> 59 | E29: =COUNTIF('AG_vague-status'!D2:D61,FALSE()) -> 1 | F29: =IF($C29=0,0,D29/$C29) -> 0.98333333 | G29: =IF($C29=0,0,E29/$C29) -> 0.016666667 | H29: =COUNTIF('AG_vague-status'!G2:G61,TRUE()) -> 59 | I29: =COUNTIF('AG_vague-status'!G2:G61,FALSE()) -> 1 | J29: =IF($C29=0,0,H29/$C29) -> 0.98333333 | K29: =IF($C29=0,0,I29/$C29) -> 0.016666667
A30: AG_vague-tax | B30: Agent | C30: =D30+E30 -> 60 | D30: =COUNTIF('AG_vague-tax'!D2:D61,TRUE()) -> 60 | E30: =COUNTIF('AG_vague-tax'!D2:D61,FALSE()) -> 0 | F30: =IF($C30=0,0,D30/$C30) -> 1 | G30: =IF($C30=0,0,E30/$C30) -> 0 | H30: =COUNTIF('AG_vague-tax'!G2:G61,TRUE()) -> 60 | I30: =COUNTIF('AG_vague-tax'!G2:G61,FALSE()) -> 0 | J30: =IF($C30=0,0,H30/$C30) -> 1 | K30: =IF($C30=0,0,I30/$C30) -> 0
A31: AG_vague-vague | B31: Agent | C31: =D31+E31 -> 60 | D31: =COUNTIF('AG_vague-vague'!D2:D61,TRUE()) -> 58 | E31: =COUNTIF('AG_vague-vague'!D2:D61,FALSE()) -> 2 | F31: =IF($C31=0,0,D31/$C31) -> 0.96666667 | G31: =IF($C31=0,0,E31/$C31) -> 0.033333333 | H31: =COUNTIF('AG_vague-vague'!G2:G61,TRUE()) -> 58 | I31: =COUNTIF('AG_vague-vague'!G2:G61,FALSE()) -> 2 | J31: =IF($C31=0,0,H31/$C31) -> 0.96666667 | K31: =IF($C31=0,0,I31/$C31) -> 0.033333333
A32: BL_change-autopay | B32: Billing | C32: =D32+E32 -> 60 | D32: =COUNTIF('BL_change-autopay'!D2:D61,TRUE()) -> 21 | E32: =COUNTIF('BL_change-autopay'!D2:D61,FALSE()) -> 39 | F32: =IF($C32=0,0,D32/$C32) -> 0.35 | G32: =IF($C32=0,0,E32/$C32) -> 0.65 | H32: =COUNTIF('BL_change-autopay'!G2:G61,TRUE()) -> 58 | I32: =COUNTIF('BL_change-autopay'!G2:G61,FALSE()) -> 2 | J32: =IF($C32=0,0,H32/$C32) -> 0.96666667 | K32: =IF($C32=0,0,I32/$C32) -> 0.033333333
A33: BL_change-bank_account | B33: Billing | C33: =D33+E33 -> 60 | D33: =COUNTIF('BL_change-bank_account'!D2:D61,TRUE()) -> 2 | E33: =COUNTIF('BL_change-bank_account'!D2:D61,FALSE()) -> 58 | F33: =IF($C33=0,0,D33/$C33) -> 0.033333333 | G33: =IF($C33=0,0,E33/$C33) -> 0.96666667 | H33: =COUNTIF('BL_change-bank_account'!G2:G61,TRUE()) -> 58 | I33: =COUNTIF('BL_change-bank_account'!G2:G61,FALSE()) -> 2 | J33: =IF($C33=0,0,H33/$C33) -> 0.96666667 | K33: =IF($C33=0,0,I33/$C33) -> 0.033333333
A34: BL_change-billing | B34: Billing | C34: =D34+E34 -> 60 | D34: =COUNTIF('BL_change-billing'!D2:D61,TRUE()) -> 45 | E34: =COUNTIF('BL_change-billing'!D2:D61,FALSE()) -> 15 | F34: =IF($C34=0,0,D34/$C34) -> 0.75 | G34: =IF($C34=0,0,E34/$C34) -> 0.25 | H34: =COUNTIF('BL_change-billing'!G2:G61,TRUE()) -> 56 | I34: =COUNTIF('BL_change-billing'!G2:G61,FALSE()) -> 4 | J34: =IF($C34=0,0,H34/$C34) -> 0.93333333 | K34: =IF($C34=0,0,I34/$C34) -> 0.066666667
A35: BL_inquire-autopay | B35: Billing | C35: =D35+E35 -> 60 | D35: =COUNTIF('BL_inquire-autopay'!D2:D61,TRUE()) -> 10 | E35: =COUNTIF('BL_inquire-autopay'!D2:D61,FALSE()) -> 50 | F35: =IF($C35=0,0,D35/$C35) -> 0.16666667 | G35: =IF($C35=0,0,E35/$C35) -> 0.83333333 | H35: =COUNTIF('BL_inquire-autopay'!G2:G61,TRUE()) -> 57 | I35: =COUNTIF('BL_inquire-autopay'!G2:G61,FALSE()) -> 3 | J35: =IF($C35=0,0,H35/$C35) -> 0.95 | K35: =IF($C35=0,0,I35/$C35) -> 0.05
A36: BL_inquire-balance | B36: Billing | C36: =D36+E36 -> 60 | D36: =COUNTIF('BL_inquire-balance'!D2:D61,TRUE()) -> 23 | E36: =COUNTIF('BL_inquire-balance'!D2:D61,FALSE()) -> 37 | F36: =IF($C36=0,0,D36/$C36) -> 0.38333333 | G36: =IF($C36=0,0,E36/$C36) -> 0.61666667 | H36: =COUNTIF('BL_inquire-balance'!G2:G61,TRUE()) -> 54 | I36: =COUNTIF('BL_inquire-balance'!G2:G61,FALSE()) -> 6 | J36: =IF($C36=0,0,H36/$C36) -> 0.9 | K36: =IF($C36=0,0,I36/$C36) -> 0.1
A37: BL_inquire-billing | B37: Billing | C37: =D37+E37 -> 60 | D37: =COUNTIF('BL_inquire-billing'!D2:D61,TRUE()) -> 33 | E37: =COUNTIF('BL_inquire-billing'!D2:D61,FALSE()) -> 27 | F37: =IF($C37=0,0,D37/$C37) -> 0.55 | G37: =IF($C37=0,0,E37/$C37) -> 0.45 | H37: =COUNTIF('BL_inquire-billing'!G2:G61,TRUE()) -> 57 | I37: =COUNTIF('BL_inquire-billing'!G2:G61,FALSE()) -> 3 | J37: =IF($C37=0,0,H37/$C37) -> 0.95 | K37: =IF($C37=0,0,I37/$C37) -> 0.05
A38: BL_inquire-credit | B38: Billing | C38: =D38+E38 -> 60 | D38: =COUNTIF('BL_inquire-credit'!D2:D61,TRUE()) -> 19 | E38: =COUNTIF('BL_inquire-credit'!D2:D61,FALSE()) -> 41 | F38: =IF($C38=0,0,D38/$C38) -> 0.31666667 | G38: =IF($C38=0,0,E38/$C38) -> 0.68333333 | H38: =COUNTIF('BL_inquire-credit'!G2:G61,TRUE()) -> 55 | I38: =COUNTIF('BL_inquire-credit'!G2:G61,FALSE()) -> 5 | J38: =IF($C38=0,0,H38/$C38) -> 0.91666667 | K38: =IF($C38=0,0,I38/$C38) -> 0.083333333
A39: BL_inquire-mlr | B39: Billing | C39: =D39+E39 -> 60 | D39: =COUNTIF('BL_inquire-mlr'!D2:D61,TRUE()) -> 28 | E39: =COUNTIF('BL_inquire-mlr'!D2:D61,FALSE()) -> 32 | F39: =IF($C39=0,0,D39/$C39) -> 0.46666667 | G39: =IF($C39=0,0,E39/$C39) -> 0.53333333 | H39: =COUNTIF('BL_inquire-mlr'!G2:G61,TRUE()) -> 60 | I39: =COUNTIF('BL_inquire-mlr'!G2:G61,FALSE()) -> 0 | J39: =IF($C39=0,0,H39/$C39) -> 1 | K39: =IF($C39=0,0,I39/$C39) -> 0
A40: BL_inquire-notice_overdue | B40: Billing | C40: =D40+E40 -> 60 | D40: =COUNTIF('BL_inquire-notice_overdue'!D2:D61,TRUE()) -> 6 | E40: =COUNTIF('BL_inquire-notice_overdue'!D2:D61,FALSE()) -> 54 | F40: =IF($C40=0,0,D40/$C40) -> 0.1 | G40: =IF($C40=0,0,E40/$C40) -> 0.9 | H40: =COUNTIF('BL_inquire-notice_overdue'!G2:G61,TRUE()) -> 51 | I40: =COUNTIF('BL_inquire-notice_overdue'!G2:G61,FALSE()) -> 9 | J40: =IF($C40=0,0,H40/$C40) -> 0.85 | K40: =IF($C40=0,0,I40/$C40) -> 0.15
A41: BL_inquire-payment_status | B41: Billing | C41: =D41+E41 -> 60 | D41: =COUNTIF('BL_inquire-payment_status'!D2:D61,TRUE()) -> 11 | E41: =COUNTIF('BL_inquire-payment_status'!D2:D61,FALSE()) -> 49 | F41: =IF($C41=0,0,D41/$C41) -> 0.18333333 | G41: =IF($C41=0,0,E41/$C41) -> 0.81666667 | H41: =COUNTIF('BL_inquire-payment_status'!G2:G61,TRUE()) -> 52 | I41: =COUNTIF('BL_inquire-payment_status'!G2:G61,FALSE()) -> 8 | J41: =IF($C41=0,0,H41/$C41) -> 0.86666667 | K41: =IF($C41=0,0,I41/$C41) -> 0.13333333
A42: BL_inquire-preventive_care | B42: Billing | C42: =D42+E42 -> 60 | D42: =COUNTIF('BL_inquire-preventive_care'!D2:D61,TRUE()) -> 22 | E42: =COUNTIF('BL_inquire-preventive_care'!D2:D61,FALSE()) -> 38 | F42: =IF($C42=0,0,D42/$C42) -> 0.36666667 | G42: =IF($C42=0,0,E42/$C42) -> 0.63333333 | H42: =COUNTIF('BL_inquire-preventive_care'!G2:G61,TRUE()) -> 56 | I42: =COUNTIF('BL_inquire-preventive_care'!G2:G61,FALSE()) -> 4 | J42: =IF($C42=0,0,H42/$C42) -> 0.93333333 | K42: =IF($C42=0,0,I42/$C42) -> 0.066666667
A43: BL_inquire-referral | B43: Billing | C43: =D43+E43 -> 60 | D43: =COUNTIF('BL_inquire-referral'!D2:D61,TRUE()) -> 14 | E43: =COUNTIF('BL_inquire-referral'!D2:D61,FALSE()) -> 46 | F43: =IF($C43=0,0,D43/$C43) -> 0.23333333 | G43: =IF($C43=0,0,E43/$C43) -> 0.76666667 | H43: =COUNTIF('BL_inquire-referral'!G2:G61,TRUE()) -> 60 | I43: =COUNTIF('BL_inquire-referral'!G2:G61,FALSE()) -> 0 | J43: =IF($C43=0,0,H43/$C43) -> 1 | K43: =IF($C43=0,0,I43/$C43) -> 0
A44: BL_inquire-refund | B44: Billing | C44: =D44+E44 -> 60 | D44: =COUNTIF('BL_inquire-refund'!D2:D61,TRUE()) -> 11 | E44: =COUNTIF('BL_inquire-refund'!D2:D61,FALSE()) -> 49 | F44: =IF($C44=0,0,D44/$C44) -> 0.18333333 | G44: =IF($C44=0,0,E44/$C44) -> 0.81666667 | H44: =COUNTIF('BL_inquire-refund'!G2:G61,TRUE()) -> 60 | I44: =COUNTIF('BL_inquire-refund'!G2:G61,FALSE()) -> 0 | J44: =IF($C44=0,0,H44/$C44) -> 1 | K44: =IF($C44=0,0,I44/$C44) -> 0
A45: BL_inquire-transactions | B45: Billing | C45: =D45+E45 -> 60 | D45: =COUNTIF('BL_inquire-transactions'!D2:D61,TRUE()) -> 24 | E45: =COUNTIF('BL_inquire-transactions'!D2:D61,FALSE()) -> 36 | F45: =IF($C45=0,0,D45/$C45) -> 0.4 | G45: =IF($C45=0,0,E45/$C45) -> 0.6 | H45: =COUNTIF('BL_inquire-transactions'!G2:G61,TRUE()) -> 57 | I45: =COUNTIF('BL_inquire-transactions'!G2:G61,FALSE()) -> 3 | J45: =IF($C45=0,0,H45/$C45) -> 0.95 | K45: =IF($C45=0,0,I45/$C45) -> 0.05
A46: BL_make-payment | B46: Billing | C46: =D46+E46 -> 60 | D46: =COUNTIF('BL_make-payment'!D2:D61,TRUE()) -> 37 | E46: =COUNTIF('BL_make-payment'!D2:D61,FALSE()) -> 23 | F46: =IF($C46=0,0,D46/$C46) -> 0.61666667 | G46: =IF($C46=0,0,E46/$C46) -> 0.38333333 | H46: =COUNTIF('BL_make-payment'!G2:G61,TRUE()) -> 49 | I46: =COUNTIF('BL_make-payment'!G2:G61,FALSE()) -> 11 | J46: =IF($C46=0,0,H46/$C46) -> 0.81666667 | K46: =IF($C46=0,0,I46/$C46) -> 0.18333333
A47: BL_make-payment_bill | B47: Billing | C47: =D47+E47 -> 60 | D47: =COUNTIF('BL_make-payment_bill'!D2:D61,TRUE()) -> 36 | E47: =COUNTIF('BL_make-payment_bill'!D2:D61,FALSE()) -> 24 | F47: =IF($C47=0,0,D47/$C47) -> 0.6 | G47: =IF($C47=0,0,E47/$C47) -> 0.4 | H47: =COUNTIF('BL_make-payment_bill'!G2:G61,TRUE()) -> 60 | I47: =COUNTIF('BL_make-payment_bill'!G2:G61,FALSE()) -> 0 | J47: =IF($C47=0,0,H47/$C47) -> 1 | K47: =IF($C47=0,0,I47/$C47) -> 0
A48: BL_make-payment_online | B48: Billing | C48: =D48+E48 -> 60 | D48: =COUNTIF('BL_make-payment_online'!D2:D61,TRUE()) -> 46 | E48: =COUNTIF('BL_make-payment_online'!D2:D61,FALSE()) -> 14 | F48: =IF($C48=0,0,D48/$C48) -> 0.76666667 | G48: =IF($C48=0,0,E48/$C48) -> 0.23333333 | H48: =COUNTIF('BL_make-payment_online'!G2:G61,TRUE()) -> 60 | I48: =COUNTIF('BL_make-payment_online'!G2:G61,FALSE()) -> 0 | J48: =IF($C48=0,0,H48/$C48) -> 1 | K48: =IF($C48=0,0,I48/$C48) -> 0
A49: BL_make-payment_phone | B49: Billing | C49: =D49+E49 -> 60 | D49: =COUNTIF('BL_make-payment_phone'!D2:D61,TRUE()) -> 36 | E49: =COUNTIF('BL_make-payment_phone'!D2:D61,FALSE()) -> 24 | F49: =IF($C49=0,0,D49/$C49) -> 0.6 | G49: =IF($C49=0,0,E49/$C49) -> 0.4 | H49: =COUNTIF('BL_make-payment_phone'!G2:G61,TRUE()) -> 60 | I49: =COUNTIF('BL_make-payment_phone'!G2:G61,FALSE()) -> 0 | J49: =IF($C49=0,0,H49/$C49) -> 1 | K49: =IF($C49=0,0,I49/$C49) -> 0
A50: BL_make-payment_premium | B50: Billing | C50: =D50+E50 -> 60 | D50: =COUNTIF('BL_make-payment_premium'!D2:D61,TRUE()) -> 52 | E50: =COUNTIF('BL_make-payment_premium'!D2:D61,FALSE()) -> 8 | F50: =IF($C50=0,0,D50/$C50) -> 0.86666667 | G50: =IF($C50=0,0,E50/$C50) -> 0.13333333 | H50: =COUNTIF('BL_make-payment_premium'!G2:G61,TRUE()) -> 60 | I50: =COUNTIF('BL_make-payment_premium'!G2:G61,FALSE()) -> 0 | J50: =IF($C50=0,0,H50/$C50) -> 1 | K50: =IF($C50=0,0,I50/$C50) -> 0
A51: BL_report-problem_billing | B51: Billing | C51: =D51+E51 -> 60 | D51: =COUNTIF('BL_report-problem_billing'!D2:D61,TRUE()) -> 40 | E51: =COUNTIF('BL_report-problem_billing'!D2:D61,FALSE()) -> 20 | F51: =IF($C51=0,0,D51/$C51) -> 0.66666667 | G51: =IF($C51=0,0,E51/$C51) -> 0.33333333 | H51: =COUNTIF('BL_report-problem_billing'!G2:G61,TRUE()) -> 60 | I51: =COUNTIF('BL_report-problem_billing'!G2:G61,FALSE()) -> 0 | J51: =IF($C51=0,0,H51/$C51) -> 1 | K51: =IF($C51=0,0,I51/$C51) -> 0
A52: BL_report-problem_payment | B52: Billing | C52: =D52+E52 -> 60 | D52: =COUNTIF('BL_report-problem_payment'!D2:D61,TRUE()) -> 39 | E52: =COUNTIF('BL_report-problem_payment'!D2:D61,FALSE()) -> 21 | F52: =IF($C52=0,0,D52/$C52) -> 0.65 | G52: =IF($C52=0,0,E52/$C52) -> 0.35 | H52: =COUNTIF('BL_report-problem_payment'!G2:G61,TRUE()) -> 60 | I52: =COUNTIF('BL_report-problem_payment'!G2:G61,FALSE()) -> 0 | J52: =IF($C52=0,0,H52/$C52) -> 1 | K52: =IF($C52=0,0,I52/$C52) -> 0
A53: BL_request-address_payment | B53: Billing | C53: =D53+E53 -> 60 | D53: =COUNTIF('BL_request-address_payment'!D2:D61,TRUE()) -> 9 | E53: =COUNTIF('BL_request-address_payment'!D2:D61,FALSE()) -> 51 | F53: =IF($C53=0,0,D53/$C53) -> 0.15 | G53: =IF($C53=0,0,E53/$C53) -> 0.85 | H53: =COUNTIF('BL_request-address_payment'!G2:G61,TRUE()) -> 56 | I53: =COUNTIF('BL_request-address_payment'!G2:G61,FALSE()) -> 4 | J53: =IF($C53=0,0,H53/$C53) -> 0.93333333 | K53: =IF($C53=0,0,I53/$C53) -> 0.066666667
A54: BL_request-agent_billing | B54: Billing | C54: =D54+E54 -> 60 | D54: =COUNTIF('BL_request-agent_billing'!D2:D61,TRUE()) -> 45 | E54: =COUNTIF('BL_request-agent_billing'!D2:D61,FALSE()) -> 15 | F54: =IF($C54=0,0,D54/$C54) -> 0.75 | G54: =IF($C54=0,0,E54/$C54) -> 0.25 | H54: =COUNTIF('BL_request-agent_billing'!G2:G61,TRUE()) -> 59 | I54: =COUNTIF('BL_request-agent_billing'!G2:G61,FALSE()) -> 1 | J54: =IF($C54=0,0,H54/$C54) -> 0.98333333 | K54: =IF($C54=0,0,I54/$C54) -> 0.016666667
A55: BL_request-bill_copy | B55: Billing | C55: =D55+E55 -> 60 | D55: =COUNTIF('BL_request-bill_copy'!D2:D61,TRUE()) -> 24 | E55: =COUNTIF('BL_request-bill_copy'!D2:D61,FALSE()) -> 36 | F55: =IF($C55=0,0,D55/$C55) -> 0.4 | G55: =IF($C55=0,0,E55/$C55) -> 0.6 | H55: =COUNTIF('BL_request-bill_copy'!G2:G61,TRUE()) -> 60 | I55: =COUNTIF('BL_request-bill_copy'!G2:G61,FALSE()) -> 0 | J55: =IF($C55=0,0,H55/$C55) -> 1 | K55: =IF($C55=0,0,I55/$C55) -> 0
A56: BL_setup-autopay | B56: Billing | C56: =D56+E56 -> 60 | D56: =COUNTIF('BL_setup-autopay'!D2:D61,TRUE()) -> 31 | E56: =COUNTIF('BL_setup-autopay'!D2:D61,FALSE()) -> 29 | F56: =IF($C56=0,0,D56/$C56) -> 0.51666667 | G56: =IF($C56=0,0,E56/$C56) -> 0.48333333 | H56: =COUNTIF('BL_setup-autopay'!G2:G61,TRUE()) -> 58 | I56: =COUNTIF('BL_setup-autopay'!G2:G61,FALSE()) -> 2 | J56: =IF($C56=0,0,H56/$C56) -> 0.96666667 | K56: =IF($C56=0,0,I56/$C56) -> 0.033333333
A57: BL_vague-bill_pay | B57: Billing | C57: =D57+E57 -> 60 | D57: =COUNTIF('BL_vague-bill_pay'!D2:D61,TRUE()) -> 38 | E57: =COUNTIF('BL_vague-bill_pay'!D2:D61,FALSE()) -> 22 | F57: =IF($C57=0,0,D57/$C57) -> 0.63333333 | G57: =IF($C57=0,0,E57/$C57) -> 0.36666667 | H57: =COUNTIF('BL_vague-bill_pay'!G2:G61,TRUE()) -> 60 | I57: =COUNTIF('BL_vague-bill_pay'!G2:G61,FALSE()) -> 0 | J57: =IF($C57=0,0,H57/$C57) -> 1 | K57: =IF($C57=0,0,I57/$C57) -> 0
A58: BL_vague-billing | B58: Billing | C58: =D58+E58 -> 60 | D58: =COUNTIF('BL_vague-billing'!D2:D61,TRUE()) -> 57 | E58: =COUNTIF('BL_vague-billing'!D2:D61,FALSE()) -> 3 | F58: =IF($C58=0,0,D58/$C58) -> 0.95 | G58: =IF($C58=0,0,E58/$C58) -> 0.05 | H58: =COUNTIF('BL_vague-billing'!G2:G61,TRUE()) -> 60 | I58: =COUNTIF('BL_vague-billing'!G2:G61,FALSE()) -> 0 | J58: =IF($C58=0,0,H58/$C58) -> 1 | K58: =IF($C58=0,0,I58/$C58) -> 0
A59: BL_vague-billing_access | B59: Billing | C59: =D59+E59 -> 60 | D59: =COUNTIF('BL_vague-billing_access'!D2:D61,TRUE()) -> 49 | E59: =COUNTIF('BL_vague-billing_access'!D2:D61,FALSE()) -> 11 | F59: =IF($C59=0,0,D59/$C59) -> 0.81666667 | G59: =IF($C59=0,0,E59/$C59) -> 0.18333333 | H59: =COUNTIF('BL_vague-billing_access'!G2:G61,TRUE()) -> 60 | I59: =COUNTIF('BL_vague-billing_access'!G2:G61,FALSE()) -> 0 | J59: =IF($C59=0,0,H59/$C59) -> 1 | K59: =IF($C59=0,0,I59/$C59) -> 0
A60: BL_vague-billing_eligibility | B60: Billing | C60: =D60+E60 -> 60 | D60: =COUNTIF('BL_vague-billing_eligibility'!D2:D61,TRUE()) -> 49 | E60: =COUNTIF('BL_vague-billing_eligibility'!D2:D61,FALSE()) -> 11 | F60: =IF($C60=0,0,D60/$C60) -> 0.81666667 | G60: =IF($C60=0,0,E60/$C60) -> 0.18333333 | H60: =COUNTIF('BL_vague-billing_eligibility'!G2:G61,TRUE()) -> 60 | I60: =COUNTIF('BL_vague-billing_eligibility'!G2:G61,FALSE()) -> 0 | J60: =IF($C60=0,0,H60/$C60) -> 1 | K60: =IF($C60=0,0,I60/$C60) -> 0
A61: BL_vague-billing_enrollment | B61: Billing | C61: =D61+E61 -> 60 | D61: =COUNTIF('BL_vague-billing_enrollment'!D2:D61,TRUE()) -> 49 | E61: =COUNTIF('BL_vague-billing_enrollment'!D2:D61,FALSE()) -> 11 | F61: =IF($C61=0,0,D61/$C61) -> 0.81666667 | G61: =IF($C61=0,0,E61/$C61) -> 0.18333333 | H61: =COUNTIF('BL_vague-billing_enrollment'!G2:G61,TRUE()) -> 60 | I61: =COUNTIF('BL_vague-billing_enrollment'!G2:G61,FALSE()) -> 0 | J61: =IF($C61=0,0,H61/$C61) -> 1 | K61: =IF($C61=0,0,I61/$C61) -> 0
A62: BL_vague-check | B62: Billing | C62: =D62+E62 -> 60 | D62: =COUNTIF('BL_vague-check'!D2:D61,TRUE()) -> 34 | E62: =COUNTIF('BL_vague-check'!D2:D61,FALSE()) -> 26 | F62: =IF($C62=0,0,D62/$C62) -> 0.56666667 | G62: =IF($C62=0,0,E62/$C62) -> 0.43333333 | H62: =COUNTIF('BL_vague-check'!G2:G61,TRUE()) -> 59 | I62: =COUNTIF('BL_vague-check'!G2:G61,FALSE()) -> 1 | J62: =IF($C62=0,0,H62/$C62) -> 0.98333333 | K62: =IF($C62=0,0,I62/$C62) -> 0.016666667
A63: BL_vague-payment | B63: Billing | C63: =D63+E63 -> 60 | D63: =COUNTIF('BL_vague-payment'!D2:D61,TRUE()) -> 31 | E63: =COUNTIF('BL_vague-payment'!D2:D61,FALSE()) -> 29 | F63: =IF($C63=0,0,D63/$C63) -> 0.51666667 | G63: =IF($C63=0,0,E63/$C63) -> 0.48333333 | H63: =COUNTIF('BL_vague-payment'!G2:G61,TRUE()) -> 58 | I63: =COUNTIF('BL_vague-payment'!G2:G61,FALSE()) -> 2 | J63: =IF($C63=0,0,H63/$C63) -> 0.96666667 | K63: =IF($C63=0,0,I63/$C63) -> 0.033333333
A64: BL_vague-premium | B64: Billing | C64: =D64+E64 -> 60 | D64: =COUNTIF('BL_vague-premium'!D2:D61,TRUE()) -> 45 | E64: =COUNTIF('BL_vague-premium'!D2:D61,FALSE()) -> 15 | F64: =IF($C64=0,0,D64/$C64) -> 0.75 | G64: =IF($C64=0,0,E64/$C64) -> 0.25 | H64: =COUNTIF('BL_vague-premium'!G2:G61,TRUE()) -> 58 | I64: =COUNTIF('BL_vague-premium'!G2:G61,FALSE()) -> 2 | J64: =IF($C64=0,0,H64/$C64) -> 0.96666667 | K64: =IF($C64=0,0,I64/$C64) -> 0.033333333
A65: BL_vague-reinstate | B65: Billing | C65: =D65+E65 -> 60 | D65: =COUNTIF('BL_vague-reinstate'!D2:D61,TRUE()) -> 43 | E65: =COUNTIF('BL_vague-reinstate'!D2:D61,FALSE()) -> 17 | F65: =IF($C65=0,0,D65/$C65) -> 0.71666667 | G65: =IF($C65=0,0,E65/$C65) -> 0.28333333 | H65: =COUNTIF('BL_vague-reinstate'!G2:G61,TRUE()) -> 59 | I65: =COUNTIF('BL_vague-reinstate'!G2:G61,FALSE()) -> 1 | J65: =IF($C65=0,0,H65/$C65) -> 0.98333333 | K65: =IF($C65=0,0,I65/$C65) -> 0.016666667
A66: BN_benefits_dental | B66: Benefits | C66: =D66+E66 -> 60 | D66: =COUNTIF(BN_benefits_dental!D2:D61,TRUE()) -> 59 | E66: =COUNTIF(BN_benefits_dental!D2:D61,FALSE()) -> 1 | F66: =IF($C66=0,0,D66/$C66) -> 0.98333333 | G66: =IF($C66=0,0,E66/$C66) -> 0.016666667 | H66: =COUNTIF(BN_benefits_dental!G2:G61,TRUE()) -> 60 | I66: =COUNTIF(BN_benefits_dental!G2:G61,FALSE()) -> 0 | J66: =IF($C66=0,0,H66/$C66) -> 1 | K66: =IF($C66=0,0,I66/$C66) -> 0
A67: BN_benefits_life | B67: Benefits | C67: =D67+E67 -> 60 | D67: =COUNTIF(BN_benefits_life!D2:D61,TRUE()) -> 60 | E67: =COUNTIF(BN_benefits_life!D2:D61,FALSE()) -> 0 | F67: =IF($C67=0,0,D67/$C67) -> 1 | G67: =IF($C67=0,0,E67/$C67) -> 0 | H67: =COUNTIF(BN_benefits_life!G2:G61,TRUE()) -> 60 | I67: =COUNTIF(BN_benefits_life!G2:G61,FALSE()) -> 0 | J67: =IF($C67=0,0,H67/$C67) -> 1 | K67: =IF($C67=0,0,I67/$C67) -> 0
A68: BN_benefits_medical | B68: Benefits | C68: =D68+E68 -> 60 | D68: =COUNTIF(BN_benefits_medical!D2:D61,TRUE()) -> 60 | E68: =COUNTIF(BN_benefits_medical!D2:D61,FALSE()) -> 0 | F68: =IF($C68=0,0,D68/$C68) -> 1 | G68: =IF($C68=0,0,E68/$C68) -> 0 | H68: =COUNTIF(BN_benefits_medical!G2:G61,TRUE()) -> 60 | I68: =COUNTIF(BN_benefits_medical!G2:G61,FALSE()) -> 0 | J68: =IF($C68=0,0,H68/$C68) -> 1 | K68: =IF($C68=0,0,I68/$C68) -> 0
A69: BN_benefits_vision | B69: Benefits | C69: =D69+E69 -> 60 | D69: =COUNTIF(BN_benefits_vision!D2:D61,TRUE()) -> 57 | E69: =COUNTIF(BN_benefits_vision!D2:D61,FALSE()) -> 3 | F69: =IF($C69=0,0,D69/$C69) -> 0.95 | G69: =IF($C69=0,0,E69/$C69) -> 0.05 | H69: =COUNTIF(BN_benefits_vision!G2:G61,TRUE()) -> 60 | I69: =COUNTIF(BN_benefits_vision!G2:G61,FALSE()) -> 0 | J69: =IF($C69=0,0,H69/$C69) -> 1 | K69: =IF($C69=0,0,I69/$C69) -> 0
A70: BN_claims_life | B70: Benefits | C70: =D70+E70 -> 60 | D70: =COUNTIF(BN_claims_life!D2:D61,TRUE()) -> 53 | E70: =COUNTIF(BN_claims_life!D2:D61,FALSE()) -> 7 | F70: =IF($C70=0,0,D70/$C70) -> 0.88333333 | G70: =IF($C70=0,0,E70/$C70) -> 0.11666667 | H70: =COUNTIF(BN_claims_life!G2:G61,TRUE()) -> 60 | I70: =COUNTIF(BN_claims_life!G2:G61,FALSE()) -> 0 | J70: =IF($C70=0,0,H70/$C70) -> 1 | K70: =IF($C70=0,0,I70/$C70) -> 0
A71: BN_eligibility_life | B71: Benefits | C71: =D71+E71 -> 60 | D71: =COUNTIF(BN_eligibility_life!D2:D61,TRUE()) -> 52 | E71: =COUNTIF(BN_eligibility_life!D2:D61,FALSE()) -> 8 | F71: =IF($C71=0,0,D71/$C71) -> 0.86666667 | G71: =IF($C71=0,0,E71/$C71) -> 0.13333333 | H71: =COUNTIF(BN_eligibility_life!G2:G61,TRUE()) -> 59 | I71: =COUNTIF(BN_eligibility_life!G2:G61,FALSE()) -> 1 | J71: =IF($C71=0,0,H71/$C71) -> 0.98333333 | K71: =IF($C71=0,0,I71/$C71) -> 0.016666667
A72: BN_inquire-benefits | B72: Benefits | C72: =D72+E72 -> 60 | D72: =COUNTIF('BN_inquire-benefits'!D2:D61,TRUE()) -> 59 | E72: =COUNTIF('BN_inquire-benefits'!D2:D61,FALSE()) -> 1 | F72: =IF($C72=0,0,D72/$C72) -> 0.98333333 | G72: =IF($C72=0,0,E72/$C72) -> 0.016666667 | H72: =COUNTIF('BN_inquire-benefits'!G2:G61,TRUE()) -> 53 | I72: =COUNTIF('BN_inquire-benefits'!G2:G61,FALSE()) -> 7 | J72: =IF($C72=0,0,H72/$C72) -> 0.88333333 | K72: =IF($C72=0,0,I72/$C72) -> 0.11666667
A73: BN_inquire-deductible | B73: Benefits | C73: =D73+E73 -> 60 | D73: =COUNTIF('BN_inquire-deductible'!D2:D61,TRUE()) -> 25 | E73: =COUNTIF('BN_inquire-deductible'!D2:D61,FALSE()) -> 35 | F73: =IF($C73=0,0,D73/$C73) -> 0.41666667 | G73: =IF($C73=0,0,E73/$C73) -> 0.58333333 | H73: =COUNTIF('BN_inquire-deductible'!G2:G61,TRUE()) -> 60 | I73: =COUNTIF('BN_inquire-deductible'!G2:G61,FALSE()) -> 0 | J73: =IF($C73=0,0,H73/$C73) -> 1 | K73: =IF($C73=0,0,I73/$C73) -> 0
A74: BN_inquire-employee_benefits | B74: Benefits | C74: =D74+E74 -> 60 | D74: =COUNTIF('BN_inquire-employee_benefits'!D2:D61,TRUE()) -> 58 | E74: =COUNTIF('BN_inquire-employee_benefits'!D2:D61,FALSE()) -> 2 | F74: =IF($C74=0,0,D74/$C74) -> 0.96666667 | G74: =IF($C74=0,0,E74/$C74) -> 0.033333333 | H74: =COUNTIF('BN_inquire-employee_benefits'!G2:G61,TRUE()) -> 60 | I74: =COUNTIF('BN_inquire-employee_benefits'!G2:G61,FALSE()) -> 0 | J74: =IF($C74=0,0,H74/$C74) -> 1 | K74: =IF($C74=0,0,I74/$C74) -> 0
A75: BN_inquire-summary | B75: Benefits | C75: =D75+E75 -> 60 | D75: =COUNTIF('BN_inquire-summary'!D2:D61,TRUE()) -> 43 | E75: =COUNTIF('BN_inquire-summary'!D2:D61,FALSE()) -> 17 | F75: =IF($C75=0,0,D75/$C75) -> 0.71666667 | G75: =IF($C75=0,0,E75/$C75) -> 0.28333333 | H75: =COUNTIF('BN_inquire-summary'!G2:G61,TRUE()) -> 60 | I75: =COUNTIF('BN_inquire-summary'!G2:G61,FALSE()) -> 0 | J75: =IF($C75=0,0,H75/$C75) -> 1 | K75: =IF($C75=0,0,I75/$C75) -> 0
A76: BN_vague-authorization | B76: Benefits | C76: =D76+E76 -> 60 | D76: =COUNTIF('BN_vague-authorization'!D2:D61,TRUE()) -> 47 | E76: =COUNTIF('BN_vague-authorization'!D2:D61,FALSE()) -> 13 | F76: =IF($C76=0,0,D76/$C76) -> 0.78333333 | G76: =IF($C76=0,0,E76/$C76) -> 0.21666667 | H76: =COUNTIF('BN_vague-authorization'!G2:G61,TRUE()) -> 60 | I76: =COUNTIF('BN_vague-authorization'!G2:G61,FALSE()) -> 0 | J76: =IF($C76=0,0,H76/$C76) -> 1 | K76: =IF($C76=0,0,I76/$C76) -> 0
A77: BN_vague-cob | B77: Benefits | C77: =D77+E77 -> 60 | D77: =COUNTIF('BN_vague-cob'!D2:D61,TRUE()) -> 33 | E77: =COUNTIF('BN_vague-cob'!D2:D61,FALSE()) -> 27 | F77: =IF($C77=0,0,D77/$C77) -> 0.55 | G77: =IF($C77=0,0,E77/$C77) -> 0.45 | H77: =COUNTIF('BN_vague-cob'!G2:G61,TRUE()) -> 59 | I77: =COUNTIF('BN_vague-cob'!G2:G61,FALSE()) -> 1 | J77: =IF($C77=0,0,H77/$C77) -> 0.98333333 | K77: =IF($C77=0,0,I77/$C77) -> 0.016666667
A78: BN_vague-coverage | B78: Benefits | C78: =D78+E78 -> 60 | D78: =COUNTIF('BN_vague-coverage'!D2:D61,TRUE()) -> 42 | E78: =COUNTIF('BN_vague-coverage'!D2:D61,FALSE()) -> 18 | F78: =IF($C78=0,0,D78/$C78) -> 0.7 | G78: =IF($C78=0,0,E78/$C78) -> 0.3 | H78: =COUNTIF('BN_vague-coverage'!G2:G61,TRUE()) -> 60 | I78: =COUNTIF('BN_vague-coverage'!G2:G61,FALSE()) -> 0 | J78: =IF($C78=0,0,H78/$C78) -> 1 | K78: =IF($C78=0,0,I78/$C78) -> 0
A79: BN_vague-provider | B79: Benefits | C79: =D79+E79 -> 60 | D79: =COUNTIF('BN_vague-provider'!D2:D61,TRUE()) -> 35 | E79: =COUNTIF('BN_vague-provider'!D2:D61,FALSE()) -> 25 | F79: =IF($C79=0,0,D79/$C79) -> 0.58333333 | G79: =IF($C79=0,0,E79/$C79) -> 0.41666667 | H79: =COUNTIF('BN_vague-provider'!G2:G61,TRUE()) -> 59 | I79: =COUNTIF('BN_vague-provider'!G2:G61,FALSE()) -> 1 | J79: =IF($C79=0,0,H79/$C79) -> 0.98333333 | K79: =IF($C79=0,0,I79/$C79) -> 0.016666667
A80: BN_verify-benefits | B80: Benefits | C80: =D80+E80 -> 60 | D80: =COUNTIF('BN_verify-benefits'!D2:D61,TRUE()) -> 56 | E80: =COUNTIF('BN_verify-benefits'!D2:D61,FALSE()) -> 4 | F80: =IF($C80=0,0,D80/$C80) -> 0.93333333 | G80: =IF($C80=0,0,E80/$C80) -> 0.066666667 | H80: =COUNTIF('BN_verify-benefits'!G2:G61,TRUE()) -> 57 | I80: =COUNTIF('BN_verify-benefits'!G2:G61,FALSE()) -> 3 | J80: =IF($C80=0,0,H80/$C80) -> 0.95 | K80: =IF($C80=0,0,I80/$C80) -> 0.05
A81: CL_claims_dental | B81: Claims | C81: =D81+E81 -> 60 | D81: =COUNTIF(CL_claims_dental!D2:D61,TRUE()) -> 57 | E81: =COUNTIF(CL_claims_dental!D2:D61,FALSE()) -> 3 | F81: =IF($C81=0,0,D81/$C81) -> 0.95 | G81: =IF($C81=0,0,E81/$C81) -> 0.05 | H81: =COUNTIF(CL_claims_dental!G2:G61,TRUE()) -> 60 | I81: =COUNTIF(CL_claims_dental!G2:G61,FALSE()) -> 0 | J81: =IF($C81=0,0,H81/$C81) -> 1 | K81: =IF($C81=0,0,I81/$C81) -> 0
A82: CL_claims_medical | B82: Claims | C82: =D82+E82 -> 60 | D82: =COUNTIF(CL_claims_medical!D2:D61,TRUE()) -> 60 | E82: =COUNTIF(CL_claims_medical!D2:D61,FALSE()) -> 0 | F82: =IF($C82=0,0,D82/$C82) -> 1 | G82: =IF($C82=0,0,E82/$C82) -> 0 | H82: =COUNTIF(CL_claims_medical!G2:G61,TRUE()) -> 59 | I82: =COUNTIF(CL_claims_medical!G2:G61,FALSE()) -> 1 | J82: =IF($C82=0,0,H82/$C82) -> 0.98333333 | K82: =IF($C82=0,0,I82/$C82) -> 0.016666667
A83: CL_claims_vision | B83: Claims | C83: =D83+E83 -> 60 | D83: =COUNTIF(CL_claims_vision!D2:D61,TRUE()) -> 58 | E83: =COUNTIF(CL_claims_vision!D2:D61,FALSE()) -> 2 | F83: =IF($C83=0,0,D83/$C83) -> 0.96666667 | G83: =IF($C83=0,0,E83/$C83) -> 0.033333333 | H83: =COUNTIF(CL_claims_vision!G2:G61,TRUE()) -> 60 | I83: =COUNTIF(CL_claims_vision!G2:G61,FALSE()) -> 0 | J83: =IF($C83=0,0,H83/$C83) -> 1 | K83: =IF($C83=0,0,I83/$C83) -> 0
A84: CL_inquire-claim_benefits | B84: Claims | C84: =D84+E84 -> 60 | D84: =COUNTIF('CL_inquire-claim_benefits'!D2:D61,TRUE()) -> 51 | E84: =COUNTIF('CL_inquire-claim_benefits'!D2:D61,FALSE()) -> 9 | F84: =IF($C84=0,0,D84/$C84) -> 0.85 | G84: =IF($C84=0,0,E84/$C84) -> 0.15 | H84: =COUNTIF('CL_inquire-claim_benefits'!G2:G61,TRUE()) -> 56 | I84: =COUNTIF('CL_inquire-claim_benefits'!G2:G61,FALSE()) -> 4 | J84: =IF($C84=0,0,H84/$C84) -> 0.93333333 | K84: =IF($C84=0,0,I84/$C84) -> 0.066666667
A85: CL_inquire-claim_status | B85: Claims | C85: =D85+E85 -> 60 | D85: =COUNTIF('CL_inquire-claim_status'!D2:D61,TRUE()) -> 51 | E85: =COUNTIF('CL_inquire-claim_status'!D2:D61,FALSE()) -> 9 | F85: =IF($C85=0,0,D85/$C85) -> 0.85 | G85: =IF($C85=0,0,E85/$C85) -> 0.15 | H85: =COUNTIF('CL_inquire-claim_status'!G2:G61,TRUE()) -> 60 | I85: =COUNTIF('CL_inquire-claim_status'!G2:G61,FALSE()) -> 0 | J85: =IF($C85=0,0,H85/$C85) -> 1 | K85: =IF($C85=0,0,I85/$C85) -> 0
A86: CL_NOSPEECH | B86: Claims | C86: =D86+E86 -> 60 | D86: =COUNTIF(CL_NOSPEECH!D2:D61,TRUE()) -> 0 | E86: =COUNTIF(CL_NOSPEECH!D2:D61,FALSE()) -> 60 | F86: =IF($C86=0,0,D86/$C86) -> 0 | G86: =IF($C86=0,0,E86/$C86) -> 1 | H86: =COUNTIF(CL_NOSPEECH!G2:G61,TRUE()) -> 0 | I86: =COUNTIF(CL_NOSPEECH!G2:G61,FALSE()) -> 60 | J86: =IF($C86=0,0,H86/$C86) -> 0 | K86: =IF($C86=0,0,I86/$C86) -> 1
A87: CL_report-problem_claim | B87: Claims | C87: =D87+E87 -> 60 | D87: =COUNTIF('CL_report-problem_claim'!D2:D61,TRUE()) -> 59 | E87: =COUNTIF('CL_report-problem_claim'!D2:D61,FALSE()) -> 1 | F87: =IF($C87=0,0,D87/$C87) -> 0.98333333 | G87: =IF($C87=0,0,E87/$C87) -> 0.016666667 | H87: =COUNTIF('CL_report-problem_claim'!G2:G61,TRUE()) -> 60 | I87: =COUNTIF('CL_report-problem_claim'!G2:G61,FALSE()) -> 0 | J87: =IF($C87=0,0,H87/$C87) -> 1 | K87: =IF($C87=0,0,I87/$C87) -> 0
A88: CL_vague-claim | B88: Claims | C88: =D88+E88 -> 60 | D88: =COUNTIF('CL_vague-claim'!D2:D61,TRUE()) -> 59 | E88: =COUNTIF('CL_vague-claim'!D2:D61,FALSE()) -> 1 | F88: =IF($C88=0,0,D88/$C88) -> 0.98333333 | G88: =IF($C88=0,0,E88/$C88) -> 0.016666667 | H88: =COUNTIF('CL_vague-claim'!G2:G61,TRUE()) -> 60 | I88: =COUNTIF('CL_vague-claim'!G2:G61,FALSE()) -> 0 | J88: =IF($C88=0,0,H88/$C88) -> 1 | K88: =IF($C88=0,0,I88/$C88) -> 0
A89: CL_vague-claim_appeal | B89: Claims | C89: =D89+E89 -> 60 | D89: =COUNTIF('CL_vague-claim_appeal'!D2:D61,TRUE()) -> 59 | E89: =COUNTIF('CL_vague-claim_appeal'!D2:D61,FALSE()) -> 1 | F89: =IF($C89=0,0,D89/$C89) -> 0.98333333 | G89: =IF($C89=0,0,E89/$C89) -> 0.016666667 | H89: =COUNTIF('CL_vague-claim_appeal'!G2:G61,TRUE()) -> 60 | I89: =COUNTIF('CL_vague-claim_appeal'!G2:G61,FALSE()) -> 0 | J89: =IF($C89=0,0,H89/$C89) -> 1 | K89: =IF($C89=0,0,I89/$C89) -> 0
A90: CL_vague-claim_disability | B90: Claims | C90: =D90+E90 -> 60 | D90: =COUNTIF('CL_vague-claim_disability'!D2:D61,TRUE()) -> 59 | E90: =COUNTIF('CL_vague-claim_disability'!D2:D61,FALSE()) -> 1 | F90: =IF($C90=0,0,D90/$C90) -> 0.98333333 | G90: =IF($C90=0,0,E90/$C90) -> 0.016666667 | H90: =COUNTIF('CL_vague-claim_disability'!G2:G61,TRUE()) -> 60 | I90: =COUNTIF('CL_vague-claim_disability'!G2:G61,FALSE()) -> 0 | J90: =IF($C90=0,0,H90/$C90) -> 1 | K90: =IF($C90=0,0,I90/$C90) -> 0
A91: CL_vague-claim_medical | B91: Claims | C91: =D91+E91 -> 60 | D91: =COUNTIF('CL_vague-claim_medical'!D2:D61,TRUE()) -> 59 | E91: =COUNTIF('CL_vague-claim_medical'!D2:D61,FALSE()) -> 1 | F91: =IF($C91=0,0,D91/$C91) -> 0.98333333 | G91: =IF($C91=0,0,E91/$C91) -> 0.016666667 | H91: =COUNTIF('CL_vague-claim_medical'!G2:G61,TRUE()) -> 60 | I91: =COUNTIF('CL_vague-claim_medical'!G2:G61,FALSE()) -> 0 | J91: =IF($C91=0,0,H91/$C91) -> 1 | K91: =IF($C91=0,0,I91/$C91) -> 0
A92: EL_activate-employee | B92: Eligibility | C92: =D92+E92 -> 60 | D92: =COUNTIF('EL_activate-employee'!D2:D61,TRUE()) -> 60 | E92: =COUNTIF('EL_activate-employee'!D2:D61,FALSE()) -> 0 | F92: =IF($C92=0,0,D92/$C92) -> 1 | G92: =IF($C92=0,0,E92/$C92) -> 0 | H92: =COUNTIF('EL_activate-employee'!G2:G61,TRUE()) -> 60 | I92: =COUNTIF('EL_activate-employee'!G2:G61,FALSE()) -> 0 | J92: =IF($C92=0,0,H92/$C92) -> 1 | K92: =IF($C92=0,0,I92/$C92) -> 0
A93: EL_cancel-account | B93: Eligibility | C93: =D93+E93 -> 60 | D93: =COUNTIF('EL_cancel-account'!D2:D61,TRUE()) -> 60 | E93: =COUNTIF('EL_cancel-account'!D2:D61,FALSE()) -> 0 | F93: =IF($C93=0,0,D93/$C93) -> 1 | G93: =IF($C93=0,0,E93/$C93) -> 0 | H93: =COUNTIF('EL_cancel-account'!G2:G61,TRUE()) -> 60 | I93: =COUNTIF('EL_cancel-account'!G2:G61,FALSE()) -> 0 | J93: =IF($C93=0,0,H93/$C93) -> 1 | K93: =IF($C93=0,0,I93/$C93) -> 0
A94: EL_cancel-coverage | B94: Eligibility | C94: =D94+E94 -> 60 | D94: =COUNTIF('EL_cancel-coverage'!D2:D61,TRUE()) -> 59 | E94: =COUNTIF('EL_cancel-coverage'!D2:D61,FALSE()) -> 1 | F94: =IF($C94=0,0,D94/$C94) -> 0.98333333 | G94: =IF($C94=0,0,E94/$C94) -> 0.016666667 | H94: =COUNTIF('EL_cancel-coverage'!G2:G61,TRUE()) -> 59 | I94: =COUNTIF('EL_cancel-coverage'!G2:G61,FALSE()) -> 1 | J94: =IF($C94=0,0,H94/$C94) -> 0.98333333 | K94: =IF($C94=0,0,I94/$C94) -> 0.016666667
A95: EL_cancel-group | B95: Eligibility | C95: =D95+E95 -> 60 | D95: =COUNTIF('EL_cancel-group'!D2:D61,TRUE()) -> 60 | E95: =COUNTIF('EL_cancel-group'!D2:D61,FALSE()) -> 0 | F95: =IF($C95=0,0,D95/$C95) -> 1 | G95: =IF($C95=0,0,E95/$C95) -> 0 | H95: =COUNTIF('EL_cancel-group'!G2:G61,TRUE()) -> 60 | I95: =COUNTIF('EL_cancel-group'!G2:G61,FALSE()) -> 0 | J95: =IF($C95=0,0,H95/$C95) -> 1 | K95: =IF($C95=0,0,I95/$C95) -> 0
A96: EL_change-birthdate | B96: Eligibility | C96: =D96+E96 -> 60 | D96: =COUNTIF('EL_change-birthdate'!D2:D61,TRUE()) -> 59 | E96: =COUNTIF('EL_change-birthdate'!D2:D61,FALSE()) -> 1 | F96: =IF($C96=0,0,D96/$C96) -> 0.98333333 | G96: =IF($C96=0,0,E96/$C96) -> 0.016666667 | H96: =COUNTIF('EL_change-birthdate'!G2:G61,TRUE()) -> 59 | I96: =COUNTIF('EL_change-birthdate'!G2:G61,FALSE()) -> 1 | J96: =IF($C96=0,0,H96/$C96) -> 0.98333333 | K96: =IF($C96=0,0,I96/$C96) -> 0.016666667
A97: EL_change-coverage | B97: Eligibility | C97: =D97+E97 -> 60 | D97: =COUNTIF('EL_change-coverage'!D2:D61,TRUE()) -> 60 | E97: =COUNTIF('EL_change-coverage'!D2:D61,FALSE()) -> 0 | F97: =IF($C97=0,0,D97/$C97) -> 1 | G97: =IF($C97=0,0,E97/$C97) -> 0 | H97: =COUNTIF('EL_change-coverage'!G2:G61,TRUE()) -> 60 | I97: =COUNTIF('EL_change-coverage'!G2:G61,FALSE()) -> 0 | J97: =IF($C97=0,0,H97/$C97) -> 1 | K97: =IF($C97=0,0,I97/$C97) -> 0
A98: EL_change-eligibility | B98: Eligibility | C98: =D98+E98 -> 60 | D98: =COUNTIF('EL_change-eligibility'!D2:D61,TRUE()) -> 60 | E98: =COUNTIF('EL_change-eligibility'!D2:D61,FALSE()) -> 0 | F98: =IF($C98=0,0,D98/$C98) -> 1 | G98: =IF($C98=0,0,E98/$C98) -> 0 | H98: =COUNTIF('EL_change-eligibility'!G2:G61,TRUE()) -> 60 | I98: =COUNTIF('EL_change-eligibility'!G2:G61,FALSE()) -> 0 | J98: =IF($C98=0,0,H98/$C98) -> 1 | K98: =IF($C98=0,0,I98/$C98) -> 0
A99: EL_change-employee | B99: Eligibility | C99: =D99+E99 -> 60 | D99: =COUNTIF('EL_change-employee'!D2:D61,TRUE()) -> 60 | E99: =COUNTIF('EL_change-employee'!D2:D61,FALSE()) -> 0 | F99: =IF($C99=0,0,D99/$C99) -> 1 | G99: =IF($C99=0,0,E99/$C99) -> 0 | H99: =COUNTIF('EL_change-employee'!G2:G61,TRUE()) -> 55 | I99: =COUNTIF('EL_change-employee'!G2:G61,FALSE()) -> 5 | J99: =IF($C99=0,0,H99/$C99) -> 0.91666667 | K99: =IF($C99=0,0,I99/$C99) -> 0.083333333
A100: EL_change-employee-coverage | B100: Eligibility | C100: =D100+E100 -> 60 | D100: =COUNTIF('EL_change-employee-coverage'!D2:D61,TRUE()) -> 59 | E100: =COUNTIF('EL_change-employee-coverage'!D2:D61,FALSE()) -> 1 | F100: =IF($C100=0,0,D100/$C100) -> 0.98333333 | G100: =IF($C100=0,0,E100/$C100) -> 0.016666667 | H100: =COUNTIF('EL_change-employee-coverage'!G2:G61,TRUE()) -> 59 | I100: =COUNTIF('EL_change-employee-coverage'!G2:G61,FALSE()) -> 1 | J100: =IF($C100=0,0,H100/$C100) -> 0.98333333 | K100: =IF($C100=0,0,I100/$C100) -> 0.016666667
...

Sheet Playbook Summary
A1: Playbook | B1: Total | C1: Head Pass | D1: Head Fail | E1: Head Pass % | F1: Head Fail % | G1: Sub Pass | H1: Sub Fail | I1: Sub Pass % | J1: Sub Fail %
A2: Agent | B2: =SUMIF(Summary!$B$2:$B$186,A2,Summary!$C$2:$C$186) -> 1800 | C2: =SUMIF(Summary!$B$2:$B$186,A2,Summary!$D$2:$D$186) -> 1780 | D2: =SUMIF(Summary!$B$2:$B$186,A2,Summary!$E$2:$E$186) -> 20 | E2: =IF($B2=0,0,C2/$B2) -> 0.98888889 | F2: =IF($B2=0,0,D2/$B2) -> 0.011111111 | G2: =SUMIF(Summary!$B$2:$B$186,A2,Summary!$H$2:$H$186) -> 1779 | H2: =SUMIF(Summary!$B$2:$B$186,A2,Summary!$I$2:$I$186) -> 21 | I2: =IF($B2=0,0,G2/$B2) -> 0.98833333 | J2: =IF($B2=0,0,H2/$B2) -> 0.011666667
A3: Benefits | B3: =SUMIF(Summary!$B$2:$B$186,A3,Summary!$C$2:$C$186) -> 900 | C3: =SUMIF(Summary!$B$2:$B$186,A3,Summary!$D$2:$D$186) -> 739 | D3: =SUMIF(Summary!$B$2:$B$186,A3,Summary!$E$2:$E$186) -> 161 | E3: =IF($B3=0,0,C3/$B3) -> 0.82111111 | F3: =IF($B3=0,0,D3/$B3) -> 0.17888889 | G3: =SUMIF(Summary!$B$2:$B$186,A3,Summary!$H$2:$H$186) -> 887 | H3: =SUMIF(Summary!$B$2:$B$186,A3,Summary!$I$2:$I$186) -> 13 | I3: =IF($B3=0,0,G3/$B3) -> 0.98555556 | J3: =IF($B3=0,0,H3/$B3) -> 0.014444444
A4: Billing | B4: =SUMIF(Summary!$B$2:$B$186,A4,Summary!$C$2:$C$186) -> 2040 | C4: =SUMIF(Summary!$B$2:$B$186,A4,Summary!$D$2:$D$186) -> 1059 | D4: =SUMIF(Summary!$B$2:$B$186,A4,Summary!$E$2:$E$186) -> 981 | E4: =IF($B4=0,0,C4/$B4) -> 0.51911765 | F4: =IF($B4=0,0,D4/$B4) -> 0.48088235 | G4: =SUMIF(Summary!$B$2:$B$186,A4,Summary!$H$2:$H$186) -> 1967 | H4: =SUMIF(Summary!$B$2:$B$186,A4,Summary!$I$2:$I$186) -> 73 | I4: =IF($B4=0,0,G4/$B4) -> 0.96421569 | J4: =IF($B4=0,0,H4/$B4) -> 0.035784314
A5: Claims | B5: =SUMIF(Summary!$B$2:$B$186,A5,Summary!$C$2:$C$186) -> 660 | C5: =SUMIF(Summary!$B$2:$B$186,A5,Summary!$D$2:$D$186) -> 572 | D5: =SUMIF(Summary!$B$2:$B$186,A5,Summary!$E$2:$E$186) -> 88 | E5: =IF($B5=0,0,C5/$B5) -> 0.86666667 | F5: =IF($B5=0,0,D5/$B5) -> 0.13333333 | G5: =SUMIF(Summary!$B$2:$B$186,A5,Summary!$H$2:$H$186) -> 595 | H5: =SUMIF(Summary!$B$2:$B$186,A5,Summary!$I$2:$I$186) -> 65 | I5: =IF($B5=0,0,G5/$B5) -> 0.90151515 | J5: =IF($B5=0,0,H5/$B5) -> 0.098484848
A6: Eligibility | B6: =SUMIF(Summary!$B$2:$B$186,A6,Summary!$C$2:$C$186) -> 3120 | C6: =SUMIF(Summary!$B$2:$B$186,A6,Summary!$D$2:$D$186) -> 3100 | D6: =SUMIF(Summary!$B$2:$B$186,A6,Summary!$E$2:$E$186) -> 20 | E6: =IF($B6=0,0,C6/$B6) -> 0.99358974 | F6: =IF($B6=0,0,D6/$B6) -> 0.0064102564 | G6: =SUMIF(Summary!$B$2:$B$186,A6,Summary!$H$2:$H$186) -> 3094 | H6: =SUMIF(Summary!$B$2:$B$186,A6,Summary!$I$2:$I$186) -> 26 | I6: =IF($B6=0,0,G6/$B6) -> 0.99166667 | J6: =IF($B6=0,0,H6/$B6) -> 0.0083333333
A7: Head Intent Detection | B7: =SUMIF(Summary!$B$2:$B$186,A7,Summary!$C$2:$C$186) -> 780 | C7: =SUMIF(Summary!$B$2:$B$186,A7,Summary!$D$2:$D$186) -> 639 | D7: =SUMIF(Summary!$B$2:$B$186,A7,Summary!$E$2:$E$186) -> 141 | E7: =IF($B7=0,0,C7/$B7) -> 0.81923077 | F7: =IF($B7=0,0,D7/$B7) -> 0.18076923 | G7: NA | H7: NA | I7: NA | J7: NA
A8: Other Intents | B8: =SUMIF(Summary!$B$2:$B$186,A8,Summary!$C$2:$C$186) -> 1800 | C8: =SUMIF(Summary!$B$2:$B$186,A8,Summary!$D$2:$D$186) -> 1706 | D8: =SUMIF(Summary!$B$2:$B$186,A8,Summary!$E$2:$E$186) -> 94 | E8: =IF($B8=0,0,C8/$B8) -> 0.94777778 | F8: =IF($B8=0,0,D8/$B8) -> 0.052222222 | G8: =SUMIF(Summary!$B$2:$B$186,A8,Summary!$H$2:$H$186) -> 1705 | H8: =SUMIF(Summary!$B$2:$B$186,A8,Summary!$I$2:$I$186) -> 95 | I8: =IF($B8=0,0,G8/$B8) -> 0.94722222 | J8: =IF($B8=0,0,H8/$B8) -> 0.052777778
A9: Steering | B9: =SUMIF(Summary!$B$2:$B$186,A9,Summary!$C$2:$C$186) -> 0 | C9: =SUMIF(Summary!$B$2:$B$186,A9,Summary!$D$2:$D$186) -> 0 | D9: =SUMIF(Summary!$B$2:$B$186,A9,Summary!$E$2:$E$186) -> 0 | E9: =IF($B9=0,0,C9/$B9) -> 0 | F9: =IF($B9=0,0,D9/$B9) -> 0 | G9: =SUMIF(Summary!$B$2:$B$186,A9,Summary!$H$2:$H$186) -> 0 | H9: =SUMIF(Summary!$B$2:$B$186,A9,Summary!$I$2:$I$186) -> 0 | I9: =IF($B9=0,0,G9/$B9) -> 0 | J9: =IF($B9=0,0,H9/$B9) -> 0
A10: TOTAL | B10: =SUM(B2:B9) -> 11100 | C10: =SUM(C2:C9) -> 9595 | D10: =SUM(D2:D9) -> 1505 | E10: =IF($B10=0,0,C10/$B10) -> 0.86441441 | F10: =IF($B10=0,0,D10/$B10) -> 0.13558559 | G10: =SUM(G2:G9) -> 10027 | H10: =SUM(H2:H9) -> 293 | I10: =IF((G10+H10)=0,0,G10/(G10+H10)) -> 0.97160853 | J10: =IF((G10+H10)=0,0,H10/(G10+H10)) -> 0.028391473

Sheet AG_change-account
A1: utterance | B1: expected_head_intent | C1: detected_head_intent | D1: head_intent_match | E1: expected_sub_intent | F1: detected_sub_intent | G1: sub_intent_match | H1: error
A2: Remove account contact | B2: agent | C2: agent | D2: =TRUE() -> TRUE | E2: change-account | F2: change-account | G2: =TRUE() -> TRUE
A3: Trying to change an employee's information | B3: agent | C3: agent | D3: =TRUE() -> TRUE | E3: change-account | F3: change-account | G3: =TRUE() -> TRUE
A4: Update company profile | B4: agent | C4: agent | D4: =TRUE() -> TRUE | E4: change-account | F4: change-account | G4: =TRUE() -> TRUE
A5: Update contact | B5: agent | C5: agent | D5: =TRUE() -> TRUE | E5: change-account | F5: change-account | G5: =TRUE() -> TRUE
A6: Update contact information | B6: agent | C6: agent | D6: =TRUE() -> TRUE | E6: change-account | F6: change-account | G6: =TRUE() -> TRUE
A7: Update membership | B7: agent | C7: agent | D7: =TRUE() -> TRUE | E7: change-account | F7: change-account | G7: =TRUE() -> TRUE
A8: Update salary information | B8: agent | C8: agent | D8: =TRUE() -> TRUE | E8: change-account | F8: change-account | G8: =TRUE() -> TRUE
A9: Want to make change to subscriber | B9: agent | C9: agent | D9: =TRUE() -> TRUE | E9: change-account | F9: change-account | G9: =TRUE() -> TRUE
A10: Would like to change the account information on the united healthcare secure email | B10: agent | C10: agent | D10: =TRUE() -> TRUE | E10: change-account | F10: change-account | G10: =TRUE() -> TRUE
A11: Wrong social_security number | B11: agent | C11: agent | D11: =TRUE() -> TRUE | E11: change-account | F11: change-account | G11: =TRUE() -> TRUE
A12: I need help with remove account contact. | B12: agent | C12: agent | D12: =TRUE() -> TRUE | E12: change-account | F12: change-account | G12: =TRUE() -> TRUE
A13: I need help with trying to change an employee's information. | B13: agent | C13: agent | D13: =TRUE() -> TRUE | E13: change-account | F13: change-account | G13: =TRUE() -> TRUE
... A61: Calling regarding wrong social_security number. | B61: agent | C61: agent | D61: =TRUE() -> TRUE | E61: change-account | F61: change-account | G61: =TRUE() -> TRUE
A62: HEAD INTENT ACCURACY | D62: 100.0%
A63: SUB INTENT ACCURACY | G63: 100.0%

Sheet AG_change-address
A1: utterance | B1: expected_head_intent | C1: detected_head_intent | D1: head_intent_match | E1: expected_sub_intent | F1: detected_sub_intent | G1: sub_intent_match | H1: error
A2: Update address | B2: agent | C2: agent | D2: =TRUE() -> TRUE | E2: change-address | F2: change-address | G2: =TRUE() -> TRUE
A3: Change address | B3: agent | C3: agent | D3: =TRUE() -> TRUE | E3: change-address | F3: change-address | G3: =TRUE() -> TRUE
A4: Update employee address | B4: agent | C4: agent | D4: =TRUE() -> TRUE | E4: change-address | F4: change-address | G4: =TRUE() -> TRUE
A5: Update company address | B5: agent | C5: agent | D5: =TRUE() -> TRUE | E5: change-address | F5: change-address | G5: =TRUE() -> TRUE
A6: Update mailing address | B6: agent | C6: agent | D6: =TRUE() -> TRUE | E6: change-address | F6: change-address | G6: =TRUE() -> TRUE
A7: Change subscriber address | B7: agent | C7: agent | D7: =TRUE() -> TRUE | E7: change-address | F7: change-address | G7: =TRUE() -> TRUE
A8: Update employer address | B8: agent | C8: agent | D8: =TRUE() -> TRUE | E8: change-address | F8: change-address | G8: =TRUE() -> TRUE
A9: Correct address | B9: agent | C9: agent | D9: =TRUE() -> TRUE | E9: change-address | F9: change-address | G9: =TRUE() -> TRUE
A10: Request address change | B10: agent | C10: agent | D10: =TRUE() -> TRUE | E10: change-address | F10: change-address | G10: =TRUE() -> TRUE
A11: Need to change address | B11: agent | C11: agent | D11: =TRUE() -> TRUE | E11: change-address | F11: change-address | G11: =TRUE() -> TRUE
A12: Update address on policy | B12: agent | C12: agent | D12: =TRUE() -> TRUE | E12: change-address | F12: change-address | G12: =TRUE() -> TRUE
A13: Report address change | B13: agent | C13: agent | D13: =TRUE() -> TRUE | E13: change-address | F13: change-address | G13: =TRUE() -> TRUE
... A61: Looking for help with report address change. | B61: agent | C61: agent | D61: =TRUE() -> TRUE | E61: change-address | F61: change-address | G61: =TRUE() -> TRUE
A62: HEAD INTENT ACCURACY | D62: 100.0%
A63: SUB INTENT ACCURACY | G63: 100.0%

Sheet AG_change-admin
A1: utterance | B1: expected_head_intent | C1: detected_head_intent | D1: head_intent_match | E1: expected_sub_intent | F1: detected_sub_intent | G1: sub_intent_match | H1: error
A2: Transfer of administrator | B2: agent | C2: agent | D2: =TRUE() -> TRUE | E2: change-admin | F2: change-admin | G2: =TRUE() -> TRUE
A3: Want to change admin | B3: agent | C3: agent | D3: =TRUE() -> TRUE | E3: change-admin | F3: change-admin | G3: =TRUE() -> TRUE
A4: Admin change | B4: agent | C4: agent | D4: =TRUE() -> TRUE | E4: change-admin | F4: change-admin | G4: =TRUE() -> TRUE
A5: I need help with transfer of administrator. | B5: agent | C5: agent | D5: =TRUE() -> TRUE | E5: change-admin | F5: change-admin | G5: =TRUE() -> TRUE
A6: I need help with want to change admin. | B6: agent | C6: agent | D6: =TRUE() -> TRUE | E6: change-admin | F6: change-admin | G6: =TRUE() -> TRUE
A7: I need help with admin change. | B7: agent | C7: agent | D7: =TRUE() -> TRUE | E7: change-admin | F7: change-admin | G7: =TRUE() -> TRUE
A8: Calling about transfer of administrator. | B8: agent | C8: agent | D8: =TRUE() -> TRUE | E8: change-admin | F8: change-admin | G8: =TRUE() -> TRUE
A9: Calling about want to change admin. | B9: agent | C9: agent | D9: =TRUE() -> TRUE | E9: change-admin | F9: change-admin | G9: =TRUE() -> TRUE
A10: Calling about admin change. | B10: agent | C10: agent | D10: =TRUE() -> TRUE | E10: change-admin | F10: change-admin | G10: =TRUE() -> TRUE
A11: I have a question about transfer of administrator. | B11: agent | C11: agent | D11: =TRUE() -> TRUE | E11: change-admin | F11: change-admin | G11: =TRUE() -> TRUE
A12: I have a question about want to change admin. | B12: agent | C12: agent | D12: =TRUE() -> TRUE | E12: change-admin | F12: change-admin | G12: =TRUE() -> TRUE
A13: I have a question about admin change. | B13: agent | C13: agent | D13: =TRUE() -> TRUE | E13: change-admin | F13: change-admin | G13: =TRUE() -> TRUE
... A61: I'm trying to get help with admin change. | B61: agent | C61: agent | D61: =TRUE() -> TRUE | E61: change-admin | F61: change-admin | G61: =TRUE() -> TRUE
A62: HEAD INTENT ACCURACY | D62: 100.0%
A63: SUB INTENT ACCURACY | G63: 100.0%

Sheet AG_change-dependent_info
A1: utterance | B1: expected_head_intent | C1: detected_head_intent | D1: head_intent_match | E1: expected_sub_intent | F1: detected_sub_intent | G1: sub_intent_match | H1: error
A2: I need to update a dependent address | B2: agent | C2: agent | D2: =TRUE() -> TRUE | E2: change-dependent_info | F2: change-dependent_info | G2: =TRUE() -> TRUE
A3: To change an address for a married dependent | B3: agent | C3: agent | D3: =TRUE() -> TRUE | E3: change-dependent_info | F3: change-dependent_info | G3: =TRUE() -> TRUE
A4: Update a social of a dependent | B4: agent | C4: agent | D4: =TRUE() -> TRUE | E4: change-dependent_info | F4: change-dependent_info | G4: =TRUE() -> TRUE
A5: Updating dependent information | B5: agent | C5: agent | D5: =TRUE() -> TRUE | E5: change-dependent_info | F5: change-dependent_info | G5: =TRUE() -> TRUE
A6: I need help with i need to update a dependent address. | B6: agent | C6: agent | D6: =TRUE() -> TRUE | E6: change-dependent_info | F6: change-dependent_info | G6: =TRUE() -> TRUE
A7: I need help with update a social of a dependent. | B7: agent | C7: agent | D7: =TRUE() -> TRUE | E7: change-dependent_info | F7: change-dependent_info | G7: =TRUE() -> TRUE
A8: I need help with updating dependent information. | B8: agent | C8: agent | D8: =TRUE() -> TRUE | E8: change-dependent_info | F8: change-dependent_info | G8: =TRUE() -> TRUE
A9: Calling about i need to update a dependent address. | B9: agent | C9: agent | D9: =TRUE() -> TRUE | E9: change-dependent_info | F9: change-dependent_info | G9: =TRUE() -> TRUE
A10: Calling about update a social of a dependent. | B10: agent | C10: agent | D10: =TRUE() -> TRUE | E10: change-dependent_info | F10: change-dependent_info | G10: =TRUE() -> TRUE
A11: Calling about updating dependent information. | B11: agent | C11: agent | D11: =TRUE() -> TRUE | E11: change-dependent_info | F11: change-dependent_info | G11: =TRUE() -> TRUE
A12: I have a question about i need to update a dependent address. | B12: agent | C12: agent | D12: =TRUE() -> TRUE | E12: change-dependent_info | F12: change-dependent_info | G12: =TRUE() -> TRUE
A13: I have a question about update a social of a dependent. | B13: agent | C13: agent | D13: =TRUE() -> TRUE | E13: change-dependent_info | F13: change-dependent_info | G13: =TRUE() -> TRUE
... A61: I'm trying to get help with update a social of a dependent. | B61: agent | C61: agent | D61: =TRUE() -> TRUE | E61: change-dependent_info | F61: change-dependent_info | G61: =TRUE() -> TRUE
A62: HEAD INTENT ACCURACY | D62: 100.0%
A63: SUB INTENT ACCURACY | G63: 100.0%

Sheet AG_change-group_info
A1: utterance | B1: expected_head_intent | C1: detected_head_intent | D1: head_intent_match | E1: expected_sub_intent | F1: detected_sub_intent | G1: sub_intent_match | H1: error
A2: Manage group | B2: agent | C2: agent | D2: =TRUE() -> TRUE | E2: change-group_info | F2: change-group_info | G2: =TRUE() -> TRUE
A3: Receipt of group information update form | B3: agent | C3: agent | D3: =TRUE() -> TRUE | E3: change-group_info | F3: change-group_info | G3: =TRUE() -> TRUE
A4: Small group changes terminations | B4: agent | C4: agent | D4: =TRUE() -> TRUE | E4: change-group_info | F4: change-group_info | G4: =TRUE() -> TRUE
A5: Update group information | B5: agent | C5: agent | D5: =TRUE() -> TRUE | E5: change-group_info | F5: change-group_info | G5: =TRUE() -> TRUE
A6: Upgrade a group | B6: agent | C6: agent | D6: =TRUE() -> TRUE | E6: change-group_info | F6: change-group_info | G6: =TRUE() -> TRUE
A7: I need help with manage group. | B7: agent | C7: agent | D7: =TRUE() -> TRUE | E7: change-group_info | F7: change-group_info | G7: =TRUE() -> TRUE
A8: I need help with receipt of group information update form. | B8: agent | C8: agent | D8: =TRUE() -> TRUE | E8: change-group_info | F8: change-group_info | G8: =TRUE() -> TRUE
A9: I need help with small group changes terminations. | B9: agent | C9: agent | D9: =TRUE() -> TRUE | E9: change-group_info | F9: change-group_info | G9: =TRUE() -> TRUE
A10: I need help with update group information. | B10: agent | C10: agent | D10: =TRUE() -> TRUE | E10: change-group_info | F10: change-group_info | G10: =TRUE() -> TRUE
A11: I need help with upgrade a group. | B11: agent | C11: agent | D11: =TRUE() -> TRUE | E11: change-group_info | F11: change-group_info | G11: =TRUE() -> TRUE
A12: Calling about manage group. | B12: agent | C12: agent | D12: =TRUE() -> TRUE | E12: change-group_info | F12: change-group_info | G12: =TRUE() -> TRUE
A13: Calling about receipt of group information update form. | B13: agent | C13: agent | D13: =TRUE() -> TRUE | E13: change-group_info | F13: change-group_info | G13: =TRUE() -> TRUE
... A46: Help with upgrade a group. | B46: agent | C46: agent | D46: =TRUE() -> TRUE | E46: change-group_info | F46: change-group_info | G46: =TRUE() -> TRUE
A47: Question about manage group. | B47: agent | D47: =FALSE() -> FALSE | E47: change-group_info | G47: =FALSE() -> FALSE
A48: Question about receipt of group information update form. | B48: agent | C48: agent | D48: =TRUE() -> TRUE | E48: change-group_info | F48: change-group_info | G48: =TRUE() -> TRUE
A49: Question about small group changes terminations. | B49: agent | C49: agent | D49: =TRUE() -> TRUE | E49: change-group_info | F49: change-group_info | G49: =TRUE() -> TRUE
A50: Question about update group information. | B50: agent | C50: agent | D50: =TRUE() -> TRUE | E50: change-group_info | F50: change-group_info | G50: =TRUE() -> TRUE
A51: Question about upgrade a group. | B51: agent | C51: agent | D51: =TRUE() -> TRUE | E51: change-group_info | F51: change-group_info | G51: =TRUE() -> TRUE
A52: I'm calling about manage group. | B52: agent | C52: agent | D52: =TRUE() -> TRUE | E52: change-group_info | F52: change-group_info | G52: =TRUE() -> TRUE
A53: I'm calling about receipt of group information update form. | B53: agent | C53: agent | D53: =TRUE() -> TRUE | E53: change-group_info | F53: change-group_info | G53: =TRUE() -> TRUE
A54: I'm calling about small group changes terminations. | B54: agent | C54: agent | D54: =TRUE() -> TRUE | E54: change-group_info | F54: change-group_info | G54: =TRUE() -> TRUE
A55: I'm calling about update group information. | B55: agent | C55: agent | D55: =TRUE() -> TRUE | E55: change-group_info | F55: change-group_info | G55: =TRUE() -> TRUE
A56: I'm calling about upgrade a group. | B56: agent | C56: agent | D56: =TRUE() -> TRUE | E56: change-group_info | F56: change-group_info | G56: =TRUE() -> TRUE
A57: I'd like information on manage group. | B57: agent | C57: agent | D57: =TRUE() -> TRUE | E57: change-group_info | F57: change-group_info | G57: =TRUE() -> TRUE
A58: I'd like information on receipt of group information update form. | B58: agent | C58: agent | D58: =TRUE() -> TRUE | E58: change-group_info | F58: change-group_info | G58: =TRUE() -> TRUE
A59: I'd like information on small group changes terminations. | B59: agent | C59: agent | D59: =TRUE() -> TRUE | E59: change-group_info | F59: change-group_info | G59: =TRUE() -> TRUE
... A61: I'd like information on upgrade a group. | B61: agent | C61: agent | D61: =TRUE() -> TRUE | E61: change-group_info | F61: change-group_info | G61: =TRUE() -> TRUE
A62: HEAD INTENT ACCURACY | D62: 98.33%
A63: SUB INTENT ACCURACY | G63: 98.33%

Sheet AG_change-provider
A1: utterance | B1: expected_head_intent | C1: detected_head_intent | D1: head_intent_match | E1: expected_sub_intent | F1: detected_sub_intent | G1: sub_intent_match | H1: error
A2: Member member upset because primary care provider was changed | B2: agent | C2: agent | D2: =TRUE() -> TRUE | E2: change-provider | F2: change-provider | G2: =TRUE() -> TRUE
A3: Need to change dependents physician | B3: agent | C3: agent | D3: =TRUE() -> TRUE | E3: change-provider | F3: change-provider | G3: =TRUE() -> TRUE
A4: Need to change primary care physician for dependent | B4: agent | C4: agent | D4: =TRUE() -> TRUE | E4: change-provider | F4: change-provider | G4: =TRUE() -> TRUE
A5: P c p change | B5: agent | C5: agent | D5: =TRUE() -> TRUE | E5: change-provider | F5: change-provider | G5: =TRUE() -> TRUE
A6: P_c_p update | B6: agent | C6: agent | D6: =TRUE() -> TRUE | E6: change-provider | F6: change-provider | G6: =TRUE() -> TRUE
A7: To get the p_c_p updated for two employees of washington street pawn brokers | B7: agent | C7: agent | D7: =TRUE() -> TRUE | E7: change-provider | F7: change-provider | G7: =TRUE() -> TRUE
A8: Update primary care physician | B8: agent | C8: agent | D8: =TRUE() -> TRUE | E8: change-provider | F8: change-provider | G8: =TRUE() -> TRUE
A9: I need help with member member upset because primary care provider was changed. | B9: agent | C9: agent | D9: =TRUE() -> TRUE | E9: change-provider | F9: change-provider | G9: =TRUE() -> TRUE
A10: I need help with need to change dependents physician. | B10: agent | C10: agent | D10: =TRUE() -> TRUE | E10: change-provider | F10: change-provider | G10: =TRUE() -> TRUE
A11: I need help with need to change primary care physician for dependent. | B11: agent | C11: agent | D11: =TRUE() -> TRUE | E11: change-provider | F11: change-provider | G11: =TRUE() -> TRUE
A12: I need help with p c p change. | B12: agent | C12: agent | D12: =TRUE() -> TRUE | E12: change-provider | F12: change-provider | G12: =TRUE() -> TRUE
A13: I need help with p_c_p update. | B13: agent | C13: agent | D13: =TRUE() -> TRUE | E13: change-provider | F13: change-provider | G13: =TRUE() -> TRUE
... A61: Question about p_c_p update. | B61: agent | C61: agent | D61: =TRUE() -> TRUE | E61: change-provider | F61: change-provider | G61: =TRUE() -> TRUE
A62: HEAD INTENT ACCURACY | D62: 100.0%
A63: SUB INTENT ACCURACY | G63: 100.0%

Sheet AG_find-provider
A1: utterance | B1: expected_head_intent | C1: detected_head_intent | D1: head_intent_match | E1: expected_sub_intent | F1: detected_sub_intent | G1: sub_intent_match | H1: error
A2: Find a physician | B2: agent | C2: agent | D2: =TRUE() -> TRUE | E2: find-provider | F2: find-provider | G2: =TRUE() -> TRUE
A3: Need to find a provider | B3: agent | C3: agent | D3: =TRUE() -> TRUE | E3: find-provider | F3: find-provider | G3: =TRUE() -> TRUE
A4: A dentist in p p o network | B4: agent | C4: agent | D4: =TRUE() -> TRUE | E4: find-provider | F4: find-provider | G4: =TRUE() -> TRUE
A5: D m o dentist list | B5: agent | C5: agent | D5: =TRUE() -> TRUE | E5: find-provider | F5: find-provider | G5: =TRUE() -> TRUE
A6: Find an in_network doctor for a client | B6: agent | C6: agent | D6: =TRUE() -> TRUE | E6: find-provider | F6: find-provider | G6: =TRUE() -> TRUE
A7: Finding participating dentist | B7: agent | C7: agent | D7: =TRUE() -> TRUE | E7: find-provider | F7: find-provider | G7: =TRUE() -> TRUE
A8: I need a list of dental dentist | B8: agent | C8: agent | D8: =TRUE() -> TRUE | E8: find-provider | F8: find-provider | G8: =TRUE() -> TRUE
A9: I need a provider directory | B9: agent | C9: agent | D9: =TRUE() -> TRUE | E9: find-provider | F9: find-provider | G9: =TRUE() -> TRUE
A10: I'm looking for a doctor | B10: agent | C10: agent | D10: =TRUE() -> TRUE | E10: find-provider | F10: find-provider | G10: =TRUE() -> TRUE
A11: I'm looking for provider directory online | B11: agent | C11: agent | D11: =TRUE() -> TRUE | E11: find-provider | F11: find-provider | G11: =TRUE() -> TRUE
A12: Looking for lab location | B12: agent | C12: agent | D12: =TRUE() -> TRUE | E12: find-provider | F12: find-provider | G12: =TRUE() -> TRUE
A13: Needed to find urgent care centers through one of my united healthcare groups | B13: agent | C13: agent | D13: =TRUE() -> TRUE | E13: find-provider | F13: find-provider | G13: =TRUE() -> TRUE
... A61: I have a question about provider location. | B61: agent | C61: agent | D61: =TRUE() -> TRUE | E61: find-provider | F61: find-provider | G61: =TRUE() -> TRUE
A62: HEAD INTENT ACCURACY | D62: 100.0%
A63: SUB INTENT ACCURACY | G63: 100.0%

Sheet AG_inquire-account_status
A1: utterance | B1: expected_head_intent | C1: detected_head_intent | D1: head_intent_match | E1: expected_sub_intent | F1: detected_sub_intent | G1: sub_intent_match | H1: error
A2: I want to confirm that we are my account is active | B2: agent | C2: agent | D2: =TRUE() -> TRUE | E2: inquire-account_status | F2: inquire-account_status | G2: =TRUE() -> TRUE
A3: Status of account | B3: agent | C3: agent | D3: =TRUE() -> TRUE | E3: inquire-account_status | F3: inquire-account_status | G3: =TRUE() -> TRUE
A4: I need help with i want to confirm that we are my account is active. | B4: agent | C4: agent | D4: =TRUE() -> TRUE | E4: inquire-account_status | F4: inquire-account_status | G4: =TRUE() -> TRUE
A5: I need help with status of account. | B5: agent | C5: agent | D5: =TRUE() -> TRUE | E5: inquire-account_status | F5: inquire-account_status | G5: =TRUE() -> TRUE
A6: Calling about i want to confirm that we are my account is active. | B6: agent | C6: agent | D6: =TRUE() -> TRUE | E6: inquire-account_status | F6: inquire-account_status | G6: =TRUE() -> TRUE
A7: Calling about status of account. | B7: agent | C7: agent | D7: =TRUE() -> TRUE | E7: inquire-account_status | F7: inquire-account_status | G7: =TRUE() -> TRUE
A8: I have a question about i want to confirm that we are my account is active. | B8: agent | C8: agent | D8: =TRUE() -> TRUE | E8: inquire-account_status | F8: inquire-account_status | G8: =TRUE() -> TRUE
A9: I have a question about status of account. | B9: agent | C9: agent | D9: =TRUE() -> TRUE | E9: inquire-account_status | F9: inquire-account_status | G9: =TRUE() -> TRUE
A10: Looking for help with i want to confirm that we are my account is active. | B10: agent | C10: agent | D10: =TRUE() -> TRUE | E10: inquire-account_status | F10: inquire-account_status | G10: =TRUE() -> TRUE
A11: Looking for help with status of account. | B11: agent | C11: agent | D11: =TRUE() -> TRUE | E11: inquire-account_status | F11: inquire-account_status | G11: =TRUE() -> TRUE
A12: Calling regarding i want to confirm that we are my account is active. | B12: agent | C12: agent | D12: =TRUE() -> TRUE | E12: inquire-account_status | F12: inquire-account_status | G12: =TRUE() -> TRUE
A13: Calling regarding status of account. | B13: agent | C13: agent | D13: =TRUE() -> TRUE | E13: inquire-account_status | F13: inquire-account_status | G13: =TRUE() -> TRUE
... A61: I want to talk to someone about status of account. | B61: agent | C61: agent | D61: =TRUE() -> TRUE | E61: inquire-account_status | F61: inquire-account_status | G61: =TRUE() -> TRUE
A62: HEAD INTENT ACCURACY | D62: 100.0%
A63: SUB INTENT ACCURACY | G63: 100.0%

Sheet AG_report-problem_account
A1: utterance | B1: expected_head_intent | C1: detected_head_intent | D1: head_intent_match | E1: expected_sub_intent | F1: detected_sub_intent | G1: sub_intent_match | H1: error
A2: Report problem account | B2: agent | C2: agent | D2: =TRUE() -> TRUE | E2: report-problem_account | F2: report-problem_account | G2: =TRUE() -> TRUE
A3: I need help with report problem account. | B3: agent | C3: agent | D3: =TRUE() -> TRUE | E3: report-problem_account | F3: report-problem_account | G3: =TRUE() -> TRUE
A4: Calling about report problem account. | B4: agent | C4: agent | D4: =TRUE() -> TRUE | E4: report-problem_account | F4: report-problem_account | G4: =TRUE() -> TRUE
A5: I have a question about report problem account. | B5: agent | C5: agent | D5: =TRUE() -> TRUE | E5: report-problem_account | F5: report-problem_account | G5: =TRUE() -> TRUE
A6: Looking for help with report problem account. | B6: agent | C6: agent | D6: =TRUE() -> TRUE | E6: report-problem_account | F6: report-problem_account | G6: =TRUE() -> TRUE
A7: Calling regarding report problem account. | B7: agent | C7: agent | D7: =TRUE() -> TRUE | E7: report-problem_account | F7: report-problem_account | G7: =TRUE() -> TRUE
A8: Need assistance with report problem account. | B8: agent | C8: agent | D8: =TRUE() -> TRUE | E8: report-problem_account | F8: report-problem_account | G8: =TRUE() -> TRUE
A9: I want information about report problem account. | B9: agent | C9: agent | D9: =TRUE() -> TRUE | E9: report-problem_account | F9: report-problem_account | G9: =TRUE() -> TRUE
A10: Help with report problem account. | B10: agent | C10: agent | D10: =TRUE() -> TRUE | E10: report-problem_account | F10: report-problem_account | G10: =TRUE() -> TRUE
A11: Question about report problem account. | B11: agent | C11: agent | D11: =TRUE() -> TRUE | E11: report-problem_account | F11: report-problem_account | G11: =TRUE() -> TRUE
A12: I'm calling about report problem account. | B12: agent | C12: agent | D12: =TRUE() -> TRUE | E12: report-problem_account | F12: report-problem_account | G12: =TRUE() -> TRUE
A13: I'd like information on report problem account. | B13: agent | C13: agent | D13: =TRUE() -> TRUE | E13: report-problem_account | F13: report-problem_account | G13: =TRUE() -> TRUE
... A61: I'd appreciate help with report problem account. | B61: agent | C61: agent | D61: =TRUE() -> TRUE | E61: report-problem_account | F61: report-problem_account | G61: =TRUE() -> TRUE
A62: HEAD INTENT ACCURACY | D62: 100.0%
A63: SUB INTENT ACCURACY | G63: 100.0%

Sheet AG_request-address
A1: utterance | B1: expected_head_intent | C1: detected_head_intent | D1: head_intent_match | E1: expected_sub_intent | F1: detected_sub_intent | G1: sub_intent_match | H1: error
A2: Request address | B2: agent | C2: agent | D2: =TRUE() -> TRUE | E2: request-address | F2: request-address | G2: =TRUE() -> TRUE
A3: I need help with request address. | B3: agent | C3: agent | D3: =TRUE() -> TRUE | E3: request-address | F3: request-address | G3: =TRUE() -> TRUE
A4: Calling about request address. | B4: agent | C4: agent | D4: =TRUE() -> TRUE | E4: request-address | F4: request-address | G4: =TRUE() -> TRUE
A5: I have a question about request address. | B5: agent | C5: agent | D5: =TRUE() -> TRUE | E5: request-address | F5: request-address | G5: =TRUE() -> TRUE
A6: Looking for help with request address. | B6: agent | C6: agent | D6: =TRUE() -> TRUE | E6: request-address | F6: request-address | G6: =TRUE() -> TRUE
A7: Calling regarding request address. | B7: agent | C7: agent | D7: =TRUE() -> TRUE | E7: request-address | F7: request-address | G7: =TRUE() -> TRUE
A8: Need assistance with request address. | B8: agent | C8: agent | D8: =TRUE() -> TRUE | E8: request-address | F8: request-address | G8: =TRUE() -> TRUE
A9: I want information about request address. | B9: agent | C9: agent | D9: =TRUE() -> TRUE | E9: request-address | F9: request-address | G9: =TRUE() -> TRUE
A10: Help with request address. | B10: agent | C10: agent | D10: =TRUE() -> TRUE | E10: request-address | F10: request-address | G10: =TRUE() -> TRUE
A11: Question about request address. | B11: agent | D11: =FALSE() -> FALSE | E11: request-address | G11: =FALSE() -> FALSE
A12: I'm calling about request address. | B12: agent | C12: agent | D12: =TRUE() -> TRUE | E12: request-address | F12: request-address | G12: =TRUE() -> TRUE
A13: I'd like information on request address. | B13: agent | C13: agent | D13: =TRUE() -> TRUE | E13: request-address | F13: request-address | G13: =TRUE() -> TRUE
A14: I need information on request address. | B14: agent | C14: agent | D14: =TRUE() -> TRUE | E14: request-address | F14: request-address | G14: =TRUE() -> TRUE
A15: Can you help me with request address? | B15: agent | C15: agent | D15: =TRUE() -> TRUE | E15: request-address | F15: request-address | G15: =TRUE() -> TRUE
A16: I wanted to ask about request address. | B16: agent | C16: agent | D16: =TRUE() -> TRUE | E16: request-address | F16: request-address | G16: =TRUE() -> TRUE
A17: This is regarding request address. | B17: agent | D17: =FALSE() -> FALSE | E17: request-address | G17: =FALSE() -> FALSE
A18: I'm calling regarding request address. | B18: agent | C18: agent | D18: =TRUE() -> TRUE | E18: request-address | F18: request-address | G18: =TRUE() -> TRUE
A19: I have a question regarding request address. | B19: agent | C19: agent | D19: =TRUE() -> TRUE | E19: request-address | F19: request-address | G19: =TRUE() -> TRUE
A20: Could you help me with request address? | B20: agent | C20: agent | D20: =TRUE() -> TRUE | E20: request-address | F20: request-address | G20: =TRUE() -> TRUE
A21: I'm trying to get help with request address. | B21: agent | C21: agent | D21: =TRUE() -> TRUE | E21: request-address | F21: request-address | G21: =TRUE() -> TRUE
A22: I just have a question about request address. | B22: agent | C22: agent | D22: =TRUE() -> TRUE | E22: request-address | F22: request-address | G22: =TRUE() -> TRUE
A23: I'm calling to ask about request address. | B23: agent | C23: agent | D23: =TRUE() -> TRUE | E23: request-address | F23: request-address | G23: =TRUE() -> TRUE
A24: Reaching out about request address. | B24: agent | C24: agent | D24: =TRUE() -> TRUE | E24: request-address | F24: request-address | G24: =TRUE() -> TRUE
A25: I'd like to ask about request address. | B25: agent | C25: agent | D25: =TRUE() -> TRUE | E25: request-address | F25: request-address | G25: =TRUE() -> TRUE
A26: Wanted to check on request address. | B26: agent | D26: =FALSE() -> FALSE | E26: request-address | G26: =FALSE() -> FALSE
A27: Hoping to get some help with request address. | B27: agent | C27: agent | D27: =TRUE() -> TRUE | E27: request-address | F27: request-address | G27: =TRUE() -> TRUE
A28: I was hoping you could help me with request address. | B28: agent | C28: agent | D28: =TRUE() -> TRUE | E28: request-address | F28: request-address | G28: =TRUE() -> TRUE
A29: My question is about request address. | B29: agent | C29: agent | D29: =TRUE() -> TRUE | E29: request-address | F29: request-address | G29: =TRUE() -> TRUE
A30: I'm following up about request address. | B30: agent | C30: agent | D30: =TRUE() -> TRUE | E30: request-address | F30: request-address | G30: =TRUE() -> TRUE
A31: I want to talk to someone about request address. | B31: agent | C31: agent | D31: =TRUE() -> TRUE | E31: request-address | F31: request-address | G31: =TRUE() -> TRUE
A32: I have a question about my request address. | B32: agent | C32: agent | D32: =TRUE() -> TRUE | E32: request-address | F32: request-address | G32: =TRUE() -> TRUE
A33: I'm calling about my request address. | B33: agent | C33: agent | D33: =TRUE() -> TRUE | E33: request-address | F33: request-address | G33: =TRUE() -> TRUE
A34: It's about my request address. | B34: agent | C34: agent | D34: =TRUE() -> TRUE | E34: request-address | F34: request-address | G34: =TRUE() -> TRUE
A35: I need help with my request address. | B35: agent | C35: agent | D35: =TRUE() -> TRUE | E35: request-address | F35: request-address | G35: =TRUE() -> TRUE
A36: Can you help me with my request address? | B36: agent | C36: agent | D36: =TRUE() -> TRUE | E36: request-address | F36: request-address | G36: =TRUE() -> TRUE
A37: I have an issue with my request address. | B37: agent | C37: agent | D37: =TRUE() -> TRUE | E37: request-address | F37: request-address | G37: =TRUE() -> TRUE
A38: I have a concern about my request address. | B38: agent | C38: agent | D38: =TRUE() -> TRUE | E38: request-address | F38: request-address | G38: =TRUE() -> TRUE
... A44: I'd like to understand my request address. | B44: agent | C44: agent | D44: =TRUE() -> TRUE | E44: request-address | F44: request-address | G44: =TRUE() -> TRUE
A45: I'm confused about my request address. | B45: agent | C45: agent | D45: =TRUE() -> TRUE | E45: request-address | F45: vague-address | G45: =FALSE() -> FALSE
A46: I have a quick question about my request address. | B46: agent | C46: agent | D46: =TRUE() -> TRUE | E46: request-address | F46: request-address | G46: =TRUE() -> TRUE
A47: Need to take care of my request address. | B47: agent | C47: agent | D47: =TRUE() -> TRUE | E47: request-address | F47: request-address | G47: =TRUE() -> TRUE
A48: Calling about my request address today. | B48: agent | C48: agent | D48: =TRUE() -> TRUE | E48: request-address | F48: request-address | G48: =TRUE() -> TRUE
A49: Yeah, I have a question about request address. | B49: agent | C49: agent | D49: =TRUE() -> TRUE | E49: request-address | F49: request-address | G49: =TRUE() -> TRUE
A50: Hi, I'm calling about request address. | B50: agent | C50: agent | D50: =TRUE() -> TRUE | E50: request-address | F50: request-address | G50: =TRUE() -> TRUE
A51: So I need some help with request address. | B51: agent | C51: agent | D51: =TRUE() -> TRUE | E51: request-address | F51: request-address | G51: =TRUE() -> TRUE
A52: Okay, I have a question about request address. | B52: agent | C52: agent | D52: =TRUE() -> TRUE | E52: request-address | F52: request-address | G52: =TRUE() -> TRUE
A53: Hello, I wanted to ask about request address. | B53: agent | C53: agent | D53: =TRUE() -> TRUE | E53: request-address | F53: request-address | G53: =TRUE() -> TRUE
A54: Who do I talk to about request address? | B54: agent | C54: agent | D54: =TRUE() -> TRUE | E54: request-address | F54: request-address | G54: =TRUE() -> TRUE
A55: I need to speak to someone about request address. | B55: agent | C55: agent | D55: =TRUE() -> TRUE | E55: request-address | F55: request-address | G55: =TRUE() -> TRUE
A56: I'm trying to figure out request address. | B56: agent | C56: agent | D56: =TRUE() -> TRUE | E56: request-address | F56: request-address | G56: =TRUE() -> TRUE
A57: Do you handle request address? | B57: agent | C57: agent | D57: =TRUE() -> TRUE | E57: request-address | F57: request-address | G57: =TRUE() -> TRUE
... A61: I'd appreciate help with request address. | B61: agent | C61: agent | D61: =TRUE() -> TRUE | E61: request-address | F61: request-address | G61: =TRUE() -> TRUE
A62: HEAD INTENT ACCURACY | D62: 95.0%
A63: SUB INTENT ACCURACY | G63: 93.33%

Sheet AG_request-agent
A1: utterance | B1: expected_head_intent | C1: detected_head_intent | D1: head_intent_match | E1: expected_sub_intent | F1: detected_sub_intent | G1: sub_intent_match | H1: error
A2: Request agent | B2: agent | C2: agent | D2: =TRUE() -> TRUE | E2: request-agent | F2: request-agent | G2: =TRUE() -> TRUE
A3: I need help with request agent. | B3: agent | C3: agent | D3: =TRUE() -> TRUE | E3: request-agent | F3: request-agent | G3: =TRUE() -> TRUE
A4: Calling about request agent. | B4: agent | C4: agent | D4: =TRUE() -> TRUE | E4: request-agent | F4: request-agent | G4: =TRUE() -> TRUE
A5: I have a question about request agent. | B5: agent | C5: agent | D5: =TRUE() -> TRUE | E5: request-agent | F5: request-agent | G5: =TRUE() -> TRUE
A6: Looking for help with request agent. | B6: agent | C6: agent | D6: =TRUE() -> TRUE | E6: request-agent | F6: request-agent | G6: =TRUE() -> TRUE
A7: Calling regarding request agent. | B7: agent | C7: agent | D7: =TRUE() -> TRUE | E7: request-agent | F7: request-agent | G7: =TRUE() -> TRUE
A8: Need assistance with request agent. | B8: agent | C8: agent | D8: =TRUE() -> TRUE | E8: request-agent | F8: request-agent | G8: =TRUE() -> TRUE
A9: I want information about request agent. | B9: agent | C9: agent | D9: =TRUE() -> TRUE | E9: request-agent | F9: request-agent | G9: =TRUE() -> TRUE
A10: Help with request agent. | B10: agent | C10: agent | D10: =TRUE() -> TRUE | E10: request-agent | F10: request-agent | G10: =TRUE() -> TRUE
A11: Question about request agent. | B11: agent | C11: agent | D11: =TRUE() -> TRUE | E11: request-agent | F11: request-agent | G11: =TRUE() -> TRUE
A12: I'm calling about request agent. | B12: agent | C12: agent | D12: =TRUE() -> TRUE | E12: request-agent | F12: request-agent | G12: =TRUE() -> TRUE
A13: I'd like information on request agent. | B13: agent | C13: agent | D13: =TRUE() -> TRUE | E13: request-agent | F13: request-agent | G13: =TRUE() -> TRUE
... A40: I need to ask about my request agent. | B40: agent | C40: agent | D40: =TRUE() -> TRUE | E40: request-agent | F40: request-agent | G40: =TRUE() -> TRUE
A41: Wanted to check on my request agent. | B41: agent | D41: =FALSE() -> FALSE | E41: request-agent | G41: =FALSE() -> FALSE
A42: I'm following up on my request agent. | B42: agent | C42: agent | D42: =TRUE() -> TRUE | E42: request-agent | F42: request-agent | G42: =TRUE() -> TRUE
A43: Question about my request agent. | B43: agent | C43: agent | D43: =TRUE() -> TRUE | E43: request-agent | F43: request-agent | G43: =TRUE() -> TRUE
A44: I'd like to understand my request agent. | B44: agent | C44: agent | D44: =TRUE() -> TRUE | E44: request-agent | F44: request-agent | G44: =TRUE() -> TRUE
A45: I'm confused about my request agent. | B45: agent | C45: agent | D45: =TRUE() -> TRUE | E45: request-agent | F45: request-agent | G45: =TRUE() -> TRUE
A46: I have a quick question about my request agent. | B46: agent | C46: agent | D46: =TRUE() -> TRUE | E46: request-agent | F46: request-agent | G46: =TRUE() -> TRUE
A47: Need to take care of my request agent. | B47: agent | C47: agent | D47: =TRUE() -> TRUE | E47: request-agent | F47: request-agent | G47: =TRUE() -> TRUE
A48: Calling about my request agent today. | B48: agent | C48: agent | D48: =TRUE() -> TRUE | E48: request-agent | F48: request-agent | G48: =TRUE() -> TRUE
A49: Yeah, I have a question about request agent. | B49: agent | C49: agent | D49: =TRUE() -> TRUE | E49: request-agent | F49: request-agent | G49: =TRUE() -> TRUE
A50: Hi, I'm calling about request agent. | B50: agent | C50: agent | D50: =TRUE() -> TRUE | E50: request-agent | F50: request-agent | G50: =TRUE() -> TRUE
A51: So I need some help with request agent. | B51: agent | C51: agent | D51: =TRUE() -> TRUE | E51: request-agent | F51: request-agent | G51: =TRUE() -> TRUE
A52: Okay, I have a question about request agent. | B52: agent | C52: agent | D52: =TRUE() -> TRUE | E52: request-agent | F52: request-agent | G52: =TRUE() -> TRUE
A53: Hello, I wanted to ask about request agent. | B53: agent | C53: agent | D53: =TRUE() -> TRUE | E53: request-agent | F53: request-agent | G53: =TRUE() -> TRUE
... A61: I'd appreciate help with request agent. | B61: agent | C61: agent | D61: =TRUE() -> TRUE | E61: request-agent | F61: request-agent | G61: =TRUE() -> TRUE
A62: HEAD INTENT ACCURACY | D62: 98.33%
A63: SUB INTENT ACCURACY | G63: 98.33%

Sheet AG_request-agent_specific
A1: utterance | B1: expected_head_intent | C1: detected_head_intent | D1: head_intent_match | E1: expected_sub_intent | F1: detected_sub_intent | G1: sub_intent_match | H1: error
A2: Request agent specific | B2: agent | C2: agent | D2: =TRUE() -> TRUE | E2: request-agent_specific | F2: request-agent_specific | G2: =TRUE() -> TRUE
A3: I need help with request agent specific. | B3: agent | C3: agent | D3: =TRUE() -> TRUE | E3: request-agent_specific | F3: request-agent_specific | G3: =TRUE() -> TRUE
A4: Calling about request agent specific. | B4: agent | C4: agent | D4: =TRUE() -> TRUE | E4: request-agent_specific | F4: request-agent_specific | G4: =TRUE() -> TRUE
A5: I have a question about request agent specific. | B5: agent | C5: agent | D5: =TRUE() -> TRUE | E5: request-agent_specific | F5: request-agent_specific | G5: =TRUE() -> TRUE
A6: Looking for help with request agent specific. | B6: agent | C6: agent | D6: =TRUE() -> TRUE | E6: request-agent_specific | F6: request-agent_specific | G6: =TRUE() -> TRUE
A7: Calling regarding request agent specific. | B7: agent | C7: agent | D7: =TRUE() -> TRUE | E7: request-agent_specific | F7: request-agent_specific | G7: =TRUE() -> TRUE
A8: Need assistance with request agent specific. | B8: agent | C8: agent | D8: =TRUE() -> TRUE | E8: request-agent_specific | F8: request-agent_specific | G8: =TRUE() -> TRUE
A9: I want information about request agent specific. | B9: agent | C9: agent | D9: =TRUE() -> TRUE | E9: request-agent_specific | F9: request-agent_specific | G9: =TRUE() -> TRUE
A10: Help with request agent specific. | B10: agent | C10: agent | D10: =TRUE() -> TRUE | E10: request-agent_specific | F10: request-agent_specific | G10: =TRUE() -> TRUE
A11: Question about request agent specific. | B11: agent | C11: agent | D11: =TRUE() -> TRUE | E11: request-agent_specific | F11: request-agent_specific | G11: =TRUE() -> TRUE
A12: I'm calling about request agent specific. | B12: agent | C12: agent | D12: =TRUE() -> TRUE | E12: request-agent_specific | F12: request-agent_specific | G12: =TRUE() -> TRUE
A13: I'd like information on request agent specific. | B13: agent | C13: agent | D13: =TRUE() -> TRUE | E13: request-agent_specific | F13: request-agent_specific | G13: =TRUE() -> TRUE
... A33: I'm calling about my request agent specific. | B33: agent | C33: agent | D33: =TRUE() -> TRUE | E33: request-agent_specific | F33: request-agent_specific | G33: =TRUE() -> TRUE
A34: It's about my request agent specific. | B34: agent | D34: =FALSE() -> FALSE | E34: request-agent_specific | G34: =FALSE() -> FALSE
A35: I need help with my request agent specific. | B35: agent | C35: agent | D35: =TRUE() -> TRUE | E35: request-agent_specific | F35: request-agent_specific | G35: =TRUE() -> TRUE
A36: Can you help me with my request agent specific? | B36: agent | C36: agent | D36: =TRUE() -> TRUE | E36: request-agent_specific | F36: request-agent_specific | G36: =TRUE() -> TRUE
A37: I have an issue with my request agent specific. | B37: agent | C37: agent | D37: =TRUE() -> TRUE | E37: request-agent_specific | F37: request-agent_specific | G37: =TRUE() -> TRUE
A38: I have a concern about my request agent specific. | B38: agent | C38: agent | D38: =TRUE() -> TRUE | E38: request-agent_specific | F38: request-agent_specific | G38: =TRUE() -> TRUE
A39: I'm calling regarding my request agent specific. | B39: agent | C39: agent | D39: =TRUE() -> TRUE | E39: request-agent_specific | F39: request-agent_specific | G39: =TRUE() -> TRUE
A40: I need to ask about my request agent specific. | B40: agent | C40: agent | D40: =TRUE() -> TRUE | E40: request-agent_specific | F40: request-agent_specific | G40: =TRUE() -> TRUE
A41: Wanted to check on my request agent specific. | B41: agent | C41: agent | D41: =TRUE() -> TRUE | E41: request-agent_specific | F41: request-agent_specific | G41: =TRUE() -> TRUE
A42: I'm following up on my request agent specific. | B42: agent | C42: agent | D42: =TRUE() -> TRUE | E42: request-agent_specific | F42: request-agent_specific | G42: =TRUE() -> TRUE
A43: Question about my request agent specific. | B43: agent | C43: agent | D43: =TRUE() -> TRUE | E43: request-agent_specific | F43: request-agent_specific | G43: =TRUE() -> TRUE
A44: I'd like to understand my request agent specific. | B44: agent | C44: agent | D44: =TRUE() -> TRUE | E44: request-agent_specific | F44: request-agent_specific | G44: =TRUE() -> TRUE
A45: I'm confused about my request agent specific. | B45: agent | C45: agent | D45: =TRUE() -> TRUE | E45: request-agent_specific | F45: request-agent_specific | G45: =TRUE() -> TRUE
A46: I have a quick question about my request agent specific. | B46: agent | C46: agent | D46: =TRUE() -> TRUE | E46: request-agent_specific | F46: request-agent_specific | G46: =TRUE() -> TRUE
... A61: I'd appreciate help with request agent specific. | B61: agent | C61: agent | D61: =TRUE() -> TRUE | E61: request-agent_specific | F61: request-agent_specific | G61: =TRUE() -> TRUE
A62: HEAD INTENT ACCURACY | D62: 98.33%
A63: SUB INTENT ACCURACY | G63: 98.33%

Sheet AG_request-contact_info
A1: utterance | B1: expected_head_intent | C1: detected_head_intent | D1: head_intent_match | E1: expected_sub_intent | F1: detected_sub_intent | G1: sub_intent_match | H1: error
A2: Request contact info | B2: agent | C2: agent | D2: =TRUE() -> TRUE | E2: request-contact_info | F2: request-contact_info | G2: =TRUE() -> TRUE
A3: I need help with request contact info. | B3: agent | C3: agent | D3: =TRUE() -> TRUE | E3: request-contact_info | F3: request-contact_info | G3: =TRUE() -> TRUE
A4: Calling about request contact info. | B4: agent | C4: agent | D4: =TRUE() -> TRUE | E4: request-contact_info | F4: request-contact_info | G4: =TRUE() -> TRUE
A5: I have a question about request contact info. | B5: agent | C5: agent | D5: =TRUE() -> TRUE | E5: request-contact_info | F5: request-contact_info | G5: =TRUE() -> TRUE
A6: Looking for help with request contact info. | B6: agent | C6: agent | D6: =TRUE() -> TRUE | E6: request-contact_info | F6: request-contact_info | G6: =TRUE() -> TRUE
A7: Calling regarding request contact info. | B7: agent | C7: agent | D7: =TRUE() -> TRUE | E7: request-contact_info | F7: request-contact_info | G7: =TRUE() -> TRUE
A8: Need assistance with request contact info. | B8: agent | C8: agent | D8: =TRUE() -> TRUE | E8: request-contact_info | F8: request-contact_info | G8: =TRUE() -> TRUE
A9: I want information about request contact info. | B9: agent | C9: agent | D9: =TRUE() -> TRUE | E9: request-contact_info | F9: request-contact_info | G9: =TRUE() -> TRUE
A10: Help with request contact info. | B10: agent | C10: agent | D10: =TRUE() -> TRUE | E10: request-contact_info | F10: request-contact_info | G10: =TRUE() -> TRUE
A11: Question about request contact info. | B11: agent | D11: =FALSE() -> FALSE | E11: request-contact_info | G11: =FALSE() -> FALSE
A12: I'm calling about request contact info. | B12: agent | C12: agent | D12: =TRUE() -> TRUE | E12: request-contact_info | F12: request-contact_info | G12: =TRUE() -> TRUE
A13: I'd like information on request contact info. | B13: agent | C13: agent | D13: =TRUE() -> TRUE | E13: request-contact_info | F13: request-contact_info | G13: =TRUE() -> TRUE
A14: I need information on request contact info. | B14: agent | C14: agent | D14: =TRUE() -> TRUE | E14: request-contact_info | F14: request-contact_info | G14: =TRUE() -> TRUE
A15: Can you help me with request contact info? | B15: agent | C15: agent | D15: =TRUE() -> TRUE | E15: request-contact_info | F15: request-contact_info | G15: =TRUE() -> TRUE
A16: I wanted to ask about request contact info. | B16: agent | C16: agent | D16: =TRUE() -> TRUE | E16: request-contact_info | F16: request-contact_info | G16: =TRUE() -> TRUE
A17: This is regarding request contact info. | B17: agent | C17: agent | D17: =TRUE() -> TRUE | E17: request-contact_info | F17: request-contact_info | G17: =TRUE() -> TRUE
A18: I'm calling regarding request contact info. | B18: agent | C18: agent | D18: =TRUE() -> TRUE | E18: request-contact_info | F18: request-contact_info | G18: =TRUE() -> TRUE
A19: I have a question regarding request contact info. | B19: agent | C19: agent | D19: =TRUE() -> TRUE | E19: request-contact_info | F19: request-contact_info | G19: =TRUE() -> TRUE
A20: Could you help me with request contact info? | B20: agent | C20: agent | D20: =TRUE() -> TRUE | E20: request-contact_info | F20: request-contact_info | G20: =TRUE() -> TRUE
A21: I'm trying to get help with request contact info. | B21: agent | C21: agent | D21: =TRUE() -> TRUE | E21: request-contact_info | F21: request-contact_info | G21: =TRUE() -> TRUE
A22: I just have a question about request contact info. | B22: agent | C22: agent | D22: =TRUE() -> TRUE | E22: request-contact_info | F22: request-contact_info | G22: =TRUE() -> TRUE
A23: I'm calling to ask about request contact info. | B23: agent | C23: agent | D23: =TRUE() -> TRUE | E23: request-contact_info | F23: request-contact_info | G23: =TRUE() -> TRUE
... A33: I'm calling about my request contact info. | B33: agent | C33: agent | D33: =TRUE() -> TRUE | E33: request-contact_info | F33: request-contact_info | G33: =TRUE() -> TRUE
A34: It's about my request contact info. | B34: agent | D34: =FALSE() -> FALSE | E34: request-contact_info | G34: =FALSE() -> FALSE
A35: I need help with my request contact info. | B35: agent | C35: agent | D35: =TRUE() -> TRUE | E35: request-contact_info | F35: request-contact_info | G35: =TRUE() -> TRUE
A36: Can you help me with my request contact info? | B36: agent | C36: agent | D36: =TRUE() -> TRUE | E36: request-contact_info | F36: request-contact_info | G36: =TRUE() -> TRUE
A37: I have an issue with my request contact info. | B37: agent | C37: agent | D37: =TRUE() -> TRUE | E37: request-contact_info | F37: request-contact_info | G37: =TRUE() -> TRUE
A38: I have a concern about my request contact info. | B38: agent | C38: agent | D38: =TRUE() -> TRUE | E38: request-contact_info | F38: request-contact_info | G38: =TRUE() -> TRUE
A39: I'm calling regarding my request contact info. | B39: agent | C39: agent | D39: =TRUE() -> TRUE | E39: request-contact_info | F39: request-contact_info | G39: =TRUE() -> TRUE
A40: I need to ask about my request contact info. | B40: agent | C40: agent | D40: =TRUE() -> TRUE | E40: request-contact_info | F40: request-contact_info | G40: =TRUE() -> TRUE
A41: Wanted to check on my request contact info. | B41: agent | C41: agent | D41: =TRUE() -> TRUE | E41: request-contact_info | F41: request-contact_info | G41: =TRUE() -> TRUE
A42: I'm following up on my request contact info. | B42: agent | C42: agent | D42: =TRUE() -> TRUE | E42: request-contact_info | F42: request-contact_info | G42: =TRUE() -> TRUE
A43: Question about my request contact info. | B43: agent | C43: agent | D43: =TRUE() -> TRUE | E43: request-contact_info | F43: request-contact_info | G43: =TRUE() -> TRUE
A44: I'd like to understand my request contact info. | B44: agent | C44: agent | D44: =TRUE() -> TRUE | E44: request-contact_info | F44: request-contact_info | G44: =TRUE() -> TRUE
A45: I'm confused about my request contact info. | B45: agent | C45: agent | D45: =TRUE() -> TRUE | E45: request-contact_info | F45: request-contact_info | G45: =TRUE() -> TRUE
A46: I have a quick question about my request contact info. | B46: agent | C46: agent | D46: =TRUE() -> TRUE | E46: request-contact_info | F46: request-contact_info | G46: =TRUE() -> TRUE
... A61: I'd appreciate help with request contact info. | B61: agent | C61: agent | D61: =TRUE() -> TRUE | E61: request-contact_info | F61: request-contact_info | G61: =TRUE() -> TRUE
A62: HEAD INTENT ACCURACY | D62: 96.67%
A63: SUB INTENT ACCURACY | G63: 96.67%

Sheet AG_respond-letter
A1: utterance | B1: expected_head_intent | C1: detected_head_intent | D1: head_intent_match | E1: expected_sub_intent | F1: detected_sub_intent | G1: sub_intent_match | H1: error
A2: Respond letter | B2: agent | C2: agent | D2: =TRUE() -> TRUE | E2: respond-letter | F2: respond-letter | G2: =TRUE() -> TRUE
A3: I need help with respond letter. | B3: agent | C3: agent | D3: =TRUE() -> TRUE | E3: respond-letter | F3: respond-letter | G3: =TRUE() -> TRUE
A4: Calling about respond letter. | B4: agent | C4: agent | D4: =TRUE() -> TRUE | E4: respond-letter | F4: respond-letter | G4: =TRUE() -> TRUE
A5: I have a question about respond letter. | B5: agent | C5: agent | D5: =TRUE() -> TRUE | E5: respond-letter | F5: respond-letter | G5: =TRUE() -> TRUE
A6: Looking for help with respond letter. | B6: agent | C6: agent | D6: =TRUE() -> TRUE | E6: respond-letter | F6: respond-letter | G6: =TRUE() -> TRUE
A7: Calling regarding respond letter. | B7: agent | C7: agent | D7: =TRUE() -> TRUE | E7: respond-letter | F7: respond-letter | G7: =TRUE() -> TRUE
A8: Need assistance with respond letter. | B8: agent | C8: agent | D8: =TRUE() -> TRUE | E8: respond-letter | F8: respond-letter | G8: =TRUE() -> TRUE
A9: I want information about respond letter. | B9: agent | C9: agent | D9: =TRUE() -> TRUE | E9: respond-letter | F9: respond-letter | G9: =TRUE() -> TRUE
A10: Help with respond letter. | B10: agent | C10: agent | D10: =TRUE() -> TRUE | E10: respond-letter | F10: respond-letter | G10: =TRUE() -> TRUE
A11: Question about respond letter. | B11: agent | C11: agent | D11: =TRUE() -> TRUE | E11: respond-letter | F11: respond-letter | G11: =TRUE() -> TRUE
A12: I'm calling about respond letter. | B12: agent | C12: agent | D12: =TRUE() -> TRUE | E12: respond-letter | F12: respond-letter | G12: =TRUE() -> TRUE
A13: I'd like information on respond letter. | B13: agent | C13: agent | D13: =TRUE() -> TRUE | E13: respond-letter | F13: respond-letter | G13: =TRUE() -> TRUE
... A61: I'd appreciate help with respond letter. | B61: agent | C61: agent | D61: =TRUE() -> TRUE | E61: respond-letter | F61: respond-letter | G61: =TRUE() -> TRUE
A62: HEAD INTENT ACCURACY | D62: 100.0%
A63: SUB INTENT ACCURACY | G63: 100.0%

Sheet AG_return-call
A1: utterance | B1: expected_head_intent | C1: detected_head_intent | D1: head_intent_match | E1: expected_sub_intent | F1: detected_sub_intent | G1: sub_intent_match | H1: error
A2: Return call | B2: agent | C2: agent | D2: =TRUE() -> TRUE | E2: return-call | F2: return-call | G2: =TRUE() -> TRUE
A3: I need help with return call. | B3: agent | C3: agent | D3: =TRUE() -> TRUE | E3: return-call | F3: return-call | G3: =TRUE() -> TRUE
A4: Calling about return call. | B4: agent | C4: agent | D4: =TRUE() -> TRUE | E4: return-call | F4: return-call | G4: =TRUE() -> TRUE
A5: I have a question about return call. | B5: agent | C5: agent | D5: =TRUE() -> TRUE | E5: return-call | F5: return-call | G5: =TRUE() -> TRUE
A6: Looking for help with return call. | B6: agent | C6: agent | D6: =TRUE() -> TRUE | E6: return-call | F6: return-call | G6: =TRUE() -> TRUE
A7: Calling regarding return call. | B7: agent | C7: agent | D7: =TRUE() -> TRUE | E7: return-call | F7: return-call | G7: =TRUE() -> TRUE
A8: Need assistance with return call. | B8: agent | C8: agent | D8: =TRUE() -> TRUE | E8: return-call | F8: return-call | G8: =TRUE() -> TRUE
A9: I want information about return call. | B9: agent | C9: agent | D9: =TRUE() -> TRUE | E9: return-call | F9: return-call | G9: =TRUE() -> TRUE
A10: Help with return call. | B10: agent | C10: agent | D10: =TRUE() -> TRUE | E10: return-call | F10: return-call | G10: =TRUE() -> TRUE
A11: Question about return call. | B11: agent | C11: agent | D11: =TRUE() -> TRUE | E11: return-call | F11: return-call | G11: =TRUE() -> TRUE
A12: I'm calling about return call. | B12: agent | C12: agent | D12: =TRUE() -> TRUE | E12: return-call | F12: return-call | G12: =TRUE() -> TRUE
A13: I'd like information on return call. | B13: agent | C13: agent | D13: =TRUE() -> TRUE | E13: return-call | F13: return-call | G13: =TRUE() -> TRUE
... A61: I'd appreciate help with return call. | B61: agent | C61: agent | D61: =TRUE() -> TRUE | E61: return-call | F61: return-call | G61: =TRUE() -> TRUE
A62: HEAD INTENT ACCURACY | D62: 100.0%
A63: SUB INTENT ACCURACY | G63: 100.0%

Sheet AG_say-something_else
A1: utterance | B1: expected_head_intent | C1: detected_head_intent | D1: head_intent_match | E1: expected_sub_intent | F1: detected_sub_intent | G1: sub_intent_match | H1: error
A2: Say something else | B2: agent | C2: agent | D2: =TRUE() -> TRUE | E2: say-something_else | F2: say-something_else | G2: =TRUE() -> TRUE
A3: I need help with say something else. | B3: agent | C3: agent | D3: =TRUE() -> TRUE | E3: say-something_else | F3: say-something_else | G3: =TRUE() -> TRUE
A4: Calling about say something else. | B4: agent | C4: agent | D4: =TRUE() -> TRUE | E4: say-something_else | F4: say-something_else | G4: =TRUE() -> TRUE
A5: I have a question about say something else. | B5: agent | C5: agent | D5: =TRUE() -> TRUE | E5: say-something_else | F5: say-something_else | G5: =TRUE() -> TRUE
A6: Looking for help with say something else. | B6: agent | C6: agent | D6: =TRUE() -> TRUE | E6: say-something_else | F6: say-something_else | G6: =TRUE() -> TRUE
A7: Calling regarding say something else. | B7: agent | C7: agent | D7: =TRUE() -> TRUE | E7: say-something_else | F7: say-something_else | G7: =TRUE() -> TRUE
A8: Need assistance with say something else. | B8: agent | C8: agent | D8: =TRUE() -> TRUE | E8: say-something_else | F8: say-something_else | G8: =TRUE() -> TRUE
A9: I want information about say something else. | B9: agent | C9: agent | D9: =TRUE() -> TRUE | E9: say-something_else | F9: say-something_else | G9: =TRUE() -> TRUE
A10: Help with say something else. | B10: agent | C10: agent | D10: =TRUE() -> TRUE | E10: say-something_else | F10: say-something_else | G10: =TRUE() -> TRUE
A11: Question about say something else. | B11: agent | C11: agent | D11: =TRUE() -> TRUE | E11: say-something_else | F11: say-something_else | G11: =TRUE() -> TRUE
A12: I'm calling about say something else. | B12: agent | C12: agent | D12: =TRUE() -> TRUE | E12: say-something_else | F12: say-something_else | G12: =TRUE() -> TRUE
A13: I'd like information on say something else. | B13: agent | C13: agent | D13: =TRUE() -> TRUE | E13: say-something_else | F13: say-something_else | G13: =TRUE() -> TRUE
... A42: I'm following up on my say something else. | B42: agent | C42: agent | D42: =TRUE() -> TRUE | E42: say-something_else | F42: say-something_else | G42: =TRUE() -> TRUE
A43: Question about my say something else. | B43: agent | D43: =FALSE() -> FALSE | E43: say-something_else | G43: =FALSE() -> FALSE
A44: I'd like to understand my say something else. | B44: agent | C44: agent | D44: =TRUE() -> TRUE | E44: say-something_else | F44: say-something_else | G44: =TRUE() -> TRUE
A45: I'm confused about my say something else. | B45: agent | C45: agent | D45: =TRUE() -> TRUE | E45: say-something_else | F45: say-something_else | G45: =TRUE() -> TRUE
A46: I have a quick question about my say something else. | B46: agent | C46: agent | D46: =TRUE() -> TRUE | E46: say-something_else | F46: say-something_else | G46: =TRUE() -> TRUE
A47: Need to take care of my say something else. | B47: agent | C47: agent | D47: =TRUE() -> TRUE | E47: say-something_else | F47: say-something_else | G47: =TRUE() -> TRUE
A48: Calling about my say something else today. | B48: agent | C48: agent | D48: =TRUE() -> TRUE | E48: say-something_else | F48: say-something_else | G48: =TRUE() -> TRUE
A49: Yeah, I have a question about say something else. | B49: agent | C49: agent | D49: =TRUE() -> TRUE | E49: say-something_else | F49: say-something_else | G49: =TRUE() -> TRUE
A50: Hi, I'm calling about say something else. | B50: agent | C50: agent | D50: =TRUE() -> TRUE | E50: say-something_else | F50: say-something_else | G50: =TRUE() -> TRUE
A51: So I need some help with say something else. | B51: agent | C51: agent | D51: =TRUE() -> TRUE | E51: say-something_else | F51: say-something_else | G51: =TRUE() -> TRUE
A52: Okay, I have a question about say something else. | B52: agent | C52: agent | D52: =TRUE() -> TRUE | E52: say-something_else | F52: say-something_else | G52: =TRUE() -> TRUE
A53: Hello, I wanted to ask about say something else. | B53: agent | C53: agent | D53: =TRUE() -> TRUE | E53: say-something_else | F53: say-something_else | G53: =TRUE() -> TRUE
A54: Who do I talk to about say something else? | B54: agent | C54: agent | D54: =TRUE() -> TRUE | E54: say-something_else | F54: say-something_else | G54: =TRUE() -> TRUE
A55: I need to speak to someone about say something else. | B55: agent | C55: agent | D55: =TRUE() -> TRUE | E55: say-something_else | F55: say-something_else | G55: =TRUE() -> TRUE
... A61: I'd appreciate help with say something else. | B61: agent | C61: agent | D61: =TRUE() -> TRUE | E61: say-something_else | F61: say-something_else | G61: =TRUE() -> TRUE
A62: HEAD INTENT ACCURACY | D62: 98.33%
A63: SUB INTENT ACCURACY | G63: 98.33%

Sheet AG_terminate-employee
A1: utterance | B1: expected_head_intent | C1: detected_head_intent | D1: head_intent_match | E1: expected_sub_intent | F1: detected_sub_intent | G1: sub_intent_match | H1: error
A2: Terminate employee | B2: agent | C2: agent | D2: =TRUE() -> TRUE | E2: terminate-employee | F2: terminate-employee | G2: =TRUE() -> TRUE
A3: I need help with terminate employee. | B3: agent | C3: agent | D3: =TRUE() -> TRUE | E3: terminate-employee | F3: terminate-employee | G3: =TRUE() -> TRUE
A4: Calling about terminate employee. | B4: agent | C4: agent | D4: =TRUE() -> TRUE | E4: terminate-employee | F4: terminate-employee | G4: =TRUE() -> TRUE
A5: I have a question about terminate employee. | B5: agent | C5: agent | D5: =TRUE() -> TRUE | E5: terminate-employee | F5: terminate-employee | G5: =TRUE() -> TRUE
A6: Looking for help with terminate employee. | B6: agent | C6: agent | D6: =TRUE() -> TRUE | E6: terminate-employee | F6: terminate-employee | G6: =TRUE() -> TRUE
A7: Calling regarding terminate employee. | B7: agent | C7: agent | D7: =TRUE() -> TRUE | E7: terminate-employee | F7: terminate-employee | G7: =TRUE() -> TRUE
A8: Need assistance with terminate employee. | B8: agent | C8: agent | D8: =TRUE() -> TRUE | E8: terminate-employee | F8: terminate-employee | G8: =TRUE() -> TRUE
A9: I want information about terminate employee. | B9: agent | C9: agent | D9: =TRUE() -> TRUE | E9: terminate-employee | F9: terminate-employee | G9: =TRUE() -> TRUE
A10: Help with terminate employee. | B10: agent | C10: agent | D10: =TRUE() -> TRUE | E10: terminate-employee | F10: terminate-employee | G10: =TRUE() -> TRUE
A11: Question about terminate employee. | B11: agent | C11: agent | D11: =TRUE() -> TRUE | E11: terminate-employee | F11: terminate-employee | G11: =TRUE() -> TRUE
A12: I'm calling about terminate employee. | B12: agent | C12: agent | D12: =TRUE() -> TRUE | E12: terminate-employee | F12: terminate-employee | G12: =TRUE() -> TRUE
A13: I'd like information on terminate employee. | B13: agent | C13: agent | D13: =TRUE() -> TRUE | E13: terminate-employee | F13: terminate-employee | G13: =TRUE() -> TRUE
... A35: I need help with my terminate employee. | B35: agent | C35: agent | D35: =TRUE() -> TRUE | E35: terminate-employee | F35: terminate-employee | G35: =TRUE() -> TRUE
A36: Can you help me with my terminate employee? | B36: agent | D36: =FALSE() -> FALSE | E36: terminate-employee | G36: =FALSE() -> FALSE | H36: 500 Internal error encountered.
A37: I have an issue with my terminate employee. | B37: agent | C37: agent | D37: =TRUE() -> TRUE | E37: terminate-employee | F37: terminate-employee | G37: =TRUE() -> TRUE
A38: I have a concern about my terminate employee. | B38: agent | C38: agent | D38: =TRUE() -> TRUE | E38: terminate-employee | F38: terminate-employee | G38: =TRUE() -> TRUE
A39: I'm calling regarding my terminate employee. | B39: agent | C39: agent | D39: =TRUE() -> TRUE | E39: terminate-employee | F39: terminate-employee | G39: =TRUE() -> TRUE
A40: I need to ask about my terminate employee. | B40: agent | C40: agent | D40: =TRUE() -> TRUE | E40: terminate-employee | F40: terminate-employee | G40: =TRUE() -> TRUE
A41: Wanted to check on my terminate employee. | B41: agent | C41: agent | D41: =TRUE() -> TRUE | E41: terminate-employee | F41: terminate-employee | G41: =TRUE() -> TRUE
A42: I'm following up on my terminate employee. | B42: agent | C42: agent | D42: =TRUE() -> TRUE | E42: terminate-employee | F42: terminate-employee | G42: =TRUE() -> TRUE
A43: Question about my terminate employee. | B43: agent | C43: agent | D43: =TRUE() -> TRUE | E43: terminate-employee | F43: terminate-employee | G43: =TRUE() -> TRUE
A44: I'd like to understand my terminate employee. | B44: agent | C44: agent | D44: =TRUE() -> TRUE | E44: terminate-employee | F44: terminate-employee | G44: =TRUE() -> TRUE
A45: I'm confused about my terminate employee. | B45: agent | C45: agent | D45: =TRUE() -> TRUE | E45: terminate-employee | F45: terminate-employee | G45: =TRUE() -> TRUE
A46: I have a quick question about my terminate employee. | B46: agent | C46: agent | D46: =TRUE() -> TRUE | E46: terminate-employee | F46: terminate-employee | G46: =TRUE() -> TRUE
A47: Need to take care of my terminate employee. | B47: agent | C47: agent | D47: =TRUE() -> TRUE | E47: terminate-employee | F47: terminate-employee | G47: =TRUE() -> TRUE
A48: Calling about my terminate employee today. | B48: agent | C48: agent | D48: =TRUE() -> TRUE | E48: terminate-employee | F48: terminate-employee | G48: =TRUE() -> TRUE
... A61: I'd appreciate help with terminate employee. | B61: agent | C61: agent | D61: =TRUE() -> TRUE | E61: terminate-employee | F61: terminate-employee | G61: =TRUE() -> TRUE
A62: HEAD INTENT ACCURACY | D62: 98.33%
A63: SUB INTENT ACCURACY | G63: 98.33%

Sheet AG_vague-account
A1: utterance | B1: expected_head_intent | C1: detected_head_intent | D1: head_intent_match | E1: expected_sub_intent | F1: detected_sub_intent | G1: sub_intent_match | H1: error
A2: Vague account | B2: agent | C2: agent | D2: =TRUE() -> TRUE | E2: vague-account | F2: vague-account | G2: =TRUE() -> TRUE
A3: I need help with vague account. | B3: agent | C3: agent | D3: =TRUE() -> TRUE | E3: vague-account | F3: vague-account | G3: =TRUE() -> TRUE
A4: Calling about vague account. | B4: agent | C4: agent | D4: =TRUE() -> TRUE | E4: vague-account | F4: vague-account | G4: =TRUE() -> TRUE
A5: I have a question about vague account. | B5: agent | C5: agent | D5: =TRUE() -> TRUE | E5: vague-account | F5: vague-account | G5: =TRUE() -> TRUE
A6: Looking for help with vague account. | B6: agent | C6: agent | D6: =TRUE() -> TRUE | E6: vague-account | F6: vague-account | G6: =TRUE() -> TRUE
A7: Calling regarding vague account. | B7: agent | C7: agent | D7: =TRUE() -> TRUE | E7: vague-account | F7: vague-account | G7: =TRUE() -> TRUE
A8: Need assistance with vague account. | B8: agent | C8: agent | D8: =TRUE() -> TRUE | E8: vague-account | F8: vague-account | G8: =TRUE() -> TRUE
A9: I want information about vague account. | B9: agent | C9: agent | D9: =TRUE() -> TRUE | E9: vague-account | F9: vague-account | G9: =TRUE() -> TRUE
A10: Help with vague account. | B10: agent | C10: agent | D10: =TRUE() -> TRUE | E10: vague-account | F10: vague-account | G10: =TRUE() -> TRUE
A11: Question about vague account. | B11: agent | D11: =FALSE() -> FALSE | E11: vague-account | G11: =FALSE() -> FALSE
A12: I'm calling about vague account. | B12: agent | C12: agent | D12: =TRUE() -> TRUE | E12: vague-account | F12: vague-account | G12: =TRUE() -> TRUE
A13: I'd like information on vague account. | B13: agent | C13: agent | D13: =TRUE() -> TRUE | E13: vague-account | F13: vague-account | G13: =TRUE() -> TRUE
A14: I need information on vague account. | B14: agent | C14: agent | D14: =TRUE() -> TRUE | E14: vague-account | F14: vague-account | G14: =TRUE() -> TRUE
A15: Can you help me with vague account? | B15: agent | C15: agent | D15: =TRUE() -> TRUE | E15: vague-account | F15: vague-account | G15: =TRUE() -> TRUE
A16: I wanted to ask about vague account. | B16: agent | C16: agent | D16: =TRUE() -> TRUE | E16: vague-account | F16: vague-account | G16: =TRUE() -> TRUE
A17: This is regarding vague account. | B17: agent | C17: agent | D17: =TRUE() -> TRUE | E17: vague-account | F17: vague-account | G17: =TRUE() -> TRUE
A18: I'm calling regarding vague account. | B18: agent | C18: agent | D18: =TRUE() -> TRUE | E18: vague-account | F18: vague-account | G18: =TRUE() -> TRUE
A19: I have a question regarding vague account. | B19: agent | C19: agent | D19: =TRUE() -> TRUE | E19: vague-account | F19: vague-account | G19: =TRUE() -> TRUE
A20: Could you help me with vague account? | B20: agent | C20: agent | D20: =TRUE() -> TRUE | E20: vague-account | F20: vague-account | G20: =TRUE() -> TRUE
A21: I'm trying to get help with vague account. | B21: agent | C21: agent | D21: =TRUE() -> TRUE | E21: vague-account | F21: vague-account | G21: =TRUE() -> TRUE
A22: I just have a question about vague account. | B22: agent | C22: agent | D22: =TRUE() -> TRUE | E22: vague-account | F22: vague-account | G22: =TRUE() -> TRUE
A23: I'm calling to ask about vague account. | B23: agent | C23: agent | D23: =TRUE() -> TRUE | E23: vague-account | F23: vague-account | G23: =TRUE() -> TRUE
... A59: Quick question about vague account. | B59: agent | C59: agent | D59: =TRUE() -> TRUE | E59: vague-account | F59: vague-account | G59: =TRUE() -> TRUE
A60: I'm not sure where to start with vague account. | B60: agent | D60: =FALSE() -> FALSE | E60: vague-account | G60: =FALSE() -> FALSE
A61: I'd appreciate help with vague account. | B61: agent | C61: agent | D61: =TRUE() -> TRUE | E61: vague-account | F61: vague-account | G61: =TRUE() -> TRUE
A62: HEAD INTENT ACCURACY | D62: 96.67%
A63: SUB INTENT ACCURACY | G63: 96.67%

Sheet AG_vague-address
A1: utterance | B1: expected_head_intent | C1: detected_head_intent | D1: head_intent_match | E1: expected_sub_intent | F1: detected_sub_intent | G1: sub_intent_match | H1: error
A2: Vague address | B2: agent | C2: agent | D2: =TRUE() -> TRUE | E2: vague-address | F2: vague-address | G2: =TRUE() -> TRUE
A3: I need help with vague address. | B3: agent | C3: agent | D3: =TRUE() -> TRUE | E3: vague-address | F3: vague-address | G3: =TRUE() -> TRUE
A4: Calling about vague address. | B4: agent | C4: agent | D4: =TRUE() -> TRUE | E4: vague-address | F4: vague-address | G4: =TRUE() -> TRUE
A5: I have a question about vague address. | B5: agent | C5: agent | D5: =TRUE() -> TRUE | E5: vague-address | F5: vague-address | G5: =TRUE() -> TRUE
A6: Looking for help with vague address. | B6: agent | C6: agent | D6: =TRUE() -> TRUE | E6: vague-address | F6: vague-address | G6: =TRUE() -> TRUE
A7: Calling regarding vague address. | B7: agent | C7: agent | D7: =TRUE() -> TRUE | E7: vague-address | F7: vague-address | G7: =TRUE() -> TRUE
A8: Need assistance with vague address. | B8: agent | C8: agent | D8: =TRUE() -> TRUE | E8: vague-address | F8: vague-address | G8: =TRUE() -> TRUE
A9: I want information about vague address. | B9: agent | C9: agent | D9: =TRUE() -> TRUE | E9: vague-address | F9: vague-address | G9: =TRUE() -> TRUE
A10: Help with vague address. | B10: agent | C10: agent | D10: =TRUE() -> TRUE | E10: vague-address | F10: vague-address | G10: =TRUE() -> TRUE
A11: Question about vague address. | B11: agent | C11: agent | D11: =TRUE() -> TRUE | E11: vague-address | F11: vague-address | G11: =TRUE() -> TRUE
A12: I'm calling about vague address. | B12: agent | C12: agent | D12: =TRUE() -> TRUE | E12: vague-address | F12: vague-address | G12: =TRUE() -> TRUE
A13: I'd like information on vague address. | B13: agent | C13: agent | D13: =TRUE() -> TRUE | E13: vague-address | F13: vague-address | G13: =TRUE() -> TRUE
... A59: Quick question about vague address. | B59: agent | C59: agent | D59: =TRUE() -> TRUE | E59: vague-address | F59: vague-address | G59: =TRUE() -> TRUE
A60: I'm not sure where to start with vague address. | B60: agent | D60: =FALSE() -> FALSE | E60: vague-address | G60: =FALSE() -> FALSE
A61: I'd appreciate help with vague address. | B61: agent | C61: agent | D61: =TRUE() -> TRUE | E61: vague-address | F61: vague-address | G61: =TRUE() -> TRUE
A62: HEAD INTENT ACCURACY | D62: 98.33%
A63: SUB INTENT ACCURACY | G63: 98.33%

Sheet AG_vague-appointment
A1: utterance | B1: expected_head_intent | C1: detected_head_intent | D1: head_intent_match | E1: expected_sub_intent | F1: detected_sub_intent | G1: sub_intent_match | H1: error
A2: Vague appointment | B2: agent | C2: agent | D2: =TRUE() -> TRUE | E2: vague-appointment | F2: vague-appointment | G2: =TRUE() -> TRUE
A3: I need help with vague appointment. | B3: agent | C3: agent | D3: =TRUE() -> TRUE | E3: vague-appointment | F3: vague-appointment | G3: =TRUE() -> TRUE
A4: Calling about vague appointment. | B4: agent | C4: agent | D4: =TRUE() -> TRUE | E4: vague-appointment | F4: vague-appointment | G4: =TRUE() -> TRUE
A5: I have a question about vague appointment. | B5: agent | C5: agent | D5: =TRUE() -> TRUE | E5: vague-appointment | F5: vague-appointment | G5: =TRUE() -> TRUE
A6: Looking for help with vague appointment. | B6: agent | C6: agent | D6: =TRUE() -> TRUE | E6: vague-appointment | F6: vague-appointment | G6: =TRUE() -> TRUE
A7: Calling regarding vague appointment. | B7: agent | C7: agent | D7: =TRUE() -> TRUE | E7: vague-appointment | F7: vague-appointment | G7: =TRUE() -> TRUE
A8: Need assistance with vague appointment. | B8: agent | C8: agent | D8: =TRUE() -> TRUE | E8: vague-appointment | F8: vague-appointment | G8: =TRUE() -> TRUE
A9: I want information about vague appointment. | B9: agent | C9: agent | D9: =TRUE() -> TRUE | E9: vague-appointment | F9: vague-appointment | G9: =TRUE() -> TRUE
A10: Help with vague appointment. | B10: agent | C10: agent | D10: =TRUE() -> TRUE | E10: vague-appointment | F10: vague-appointment | G10: =TRUE() -> TRUE
A11: Question about vague appointment. | B11: agent | C11: agent | D11: =TRUE() -> TRUE | E11: vague-appointment | F11: vague-appointment | G11: =TRUE() -> TRUE
A12: I'm calling about vague appointment. | B12: agent | C12: agent | D12: =TRUE() -> TRUE | E12: vague-appointment | F12: vague-appointment | G12: =TRUE() -> TRUE
A13: I'd like information on vague appointment. | B13: agent | C13: agent | D13: =TRUE() -> TRUE | E13: vague-appointment | F13: vague-appointment | G13: =TRUE() -> TRUE
... A61: I'd appreciate help with vague appointment. | B61: agent | C61: agent | D61: =TRUE() -> TRUE | E61: vague-appointment | F61: vague-appointment | G61: =TRUE() -> TRUE
A62: HEAD INTENT ACCURACY | D62: 100.0%
A63: SUB INTENT ACCURACY | G63: 100.0%

Sheet AG_vague-employee
A1: utterance | B1: expected_head_intent | C1: detected_head_intent | D1: head_intent_match | E1: expected_sub_intent | F1: detected_sub_intent | G1: sub_intent_match | H1: error
A2: Vague employee | B2: agent | C2: agent | D2: =TRUE() -> TRUE | E2: vague-employee | F2: vague-employee | G2: =TRUE() -> TRUE
A3: I need help with vague employee. | B3: agent | C3: agent | D3: =TRUE() -> TRUE | E3: vague-employee | F3: vague-employee | G3: =TRUE() -> TRUE
A4: Calling about vague employee. | B4: agent | C4: agent | D4: =TRUE() -> TRUE | E4: vague-employee | F4: vague-employee | G4: =TRUE() -> TRUE
A5: I have a question about vague employee. | B5: agent | C5: agent | D5: =TRUE() -> TRUE | E5: vague-employee | F5: vague-employee | G5: =TRUE() -> TRUE
A6: Looking for help with vague employee. | B6: agent | C6: agent | D6: =TRUE() -> TRUE | E6: vague-employee | F6: vague-employee | G6: =TRUE() -> TRUE
A7: Calling regarding vague employee. | B7: agent | C7: agent | D7: =TRUE() -> TRUE | E7: vague-employee | F7: vague-employee | G7: =TRUE() -> TRUE
A8: Need assistance with vague employee. | B8: agent | C8: agent | D8: =TRUE() -> TRUE | E8: vague-employee | F8: vague-employee | G8: =TRUE() -> TRUE
A9: I want information about vague employee. | B9: agent | C9: agent | D9: =TRUE() -> TRUE | E9: vague-employee | F9: vague-employee | G9: =TRUE() -> TRUE
A10: Help with vague employee. | B10: agent | C10: agent | D10: =TRUE() -> TRUE | E10: vague-employee | F10: vague-employee | G10: =TRUE() -> TRUE
A11: Question about vague employee. | B11: agent | C11: agent | D11: =TRUE() -> TRUE | E11: vague-employee | F11: vague-employee | G11: =TRUE() -> TRUE
A12: I'm calling about vague employee. | B12: agent | C12: agent | D12: =TRUE() -> TRUE | E12: vague-employee | F12: vague-employee | G12: =TRUE() -> TRUE
A13: I'd like information on vague employee. | B13: agent | C13: agent | D13: =TRUE() -> TRUE | E13: vague-employee | F13: vague-employee | G13: =TRUE() -> TRUE
... A61: I'd appreciate help with vague employee. | B61: agent | C61: agent | D61: =TRUE() -> TRUE | E61: vague-employee | F61: vague-employee | G61: =TRUE() -> TRUE
A62: HEAD INTENT ACCURACY | D62: 100.0%
A63: SUB INTENT ACCURACY | G63: 100.0%

Sheet AG_vague-group_info
A1: utterance | B1: expected_head_intent | C1: detected_head_intent | D1: head_intent_match | E1: expected_sub_intent | F1: detected_sub_intent | G1: sub_intent_match | H1: error
A2: Vague group info | B2: agent | C2: agent | D2: =TRUE() -> TRUE | E2: vague-group_info | F2: vague-group_info | G2: =TRUE() -> TRUE
A3: I need help with vague group info. | B3: agent | C3: agent | D3: =TRUE() -> TRUE | E3: vague-group_info | F3: vague-group_info | G3: =TRUE() -> TRUE
A4: Calling about vague group info. | B4: agent | C4: agent | D4: =TRUE() -> TRUE | E4: vague-group_info | F4: vague-group_info | G4: =TRUE() -> TRUE
A5: I have a question about vague group info. | B5: agent | C5: agent | D5: =TRUE() -> TRUE | E5: vague-group_info | F5: vague-group_info | G5: =TRUE() -> TRUE
A6: Looking for help with vague group info. | B6: agent | C6: agent | D6: =TRUE() -> TRUE | E6: vague-group_info | F6: vague-group_info | G6: =TRUE() -> TRUE
A7: Calling regarding vague group info. | B7: agent | C7: agent | D7: =TRUE() -> TRUE | E7: vague-group_info | F7: vague-group_info | G7: =TRUE() -> TRUE
A8: Need assistance with vague group info. | B8: agent | C8: agent | D8: =TRUE() -> TRUE | E8: vague-group_info | F8: vague-group_info | G8: =TRUE() -> TRUE
A9: I want information about vague group info. | B9: agent | C9: agent | D9: =TRUE() -> TRUE | E9: vague-group_info | F9: vague-group_info | G9: =TRUE() -> TRUE
A10: Help with vague group info. | B10: agent | C10: agent | D10: =TRUE() -> TRUE | E10: vague-group_info | F10: vague-group_info | G10: =TRUE() -> TRUE
A11: Question about vague group info. | B11: agent | C11: agent | D11: =TRUE() -> TRUE | E11: vague-group_info | F11: vague-group_info | G11: =TRUE() -> TRUE
A12: I'm calling about vague group info. | B12: agent | C12: agent | D12: =TRUE() -> TRUE | E12: vague-group_info | F12: vague-group_info | G12: =TRUE() -> TRUE
A13: I'd like information on vague group info. | B13: agent | C13: agent | D13: =TRUE() -> TRUE | E13: vague-group_info | F13: vague-group_info | G13: =TRUE() -> TRUE
... A61: I'd appreciate help with vague group info. | B61: agent | C61: agent | D61: =TRUE() -> TRUE | E61: vague-group_info | F61: vague-group_info | G61: =TRUE() -> TRUE
A62: HEAD INTENT ACCURACY | D62: 100.0%
A63: SUB INTENT ACCURACY | G63: 100.0%

Sheet AG_vague-inquire
A1: utterance | B1: expected_head_intent | C1: detected_head_intent | D1: head_intent_match | E1: expected_sub_intent | F1: detected_sub_intent | G1: sub_intent_match | H1: error
A2: Vague inquire | B2: agent | C2: agent | D2: =TRUE() -> TRUE | E2: vague-inquire | F2: vague-inquire | G2: =TRUE() -> TRUE
A3: I need help with vague inquire. | B3: agent | C3: agent | D3: =TRUE() -> TRUE | E3: vague-inquire | F3: vague-inquire | G3: =TRUE() -> TRUE
A4: Calling about vague inquire. | B4: agent | C4: agent | D4: =TRUE() -> TRUE | E4: vague-inquire | F4: vague-inquire | G4: =TRUE() -> TRUE
A5: I have a question about vague inquire. | B5: agent | C5: agent | D5: =TRUE() -> TRUE | E5: vague-inquire | F5: vague-inquire | G5: =TRUE() -> TRUE
A6: Looking for help with vague inquire. | B6: agent | C6: agent | D6: =TRUE() -> TRUE | E6: vague-inquire | F6: vague-inquire | G6: =TRUE() -> TRUE
A7: Calling regarding vague inquire. | B7: agent | C7: agent | D7: =TRUE() -> TRUE | E7: vague-inquire | F7: vague-inquire | G7: =TRUE() -> TRUE
A8: Need assistance with vague inquire. | B8: agent | C8: agent | D8: =TRUE() -> TRUE | E8: vague-inquire | F8: vague-inquire | G8: =TRUE() -> TRUE
A9: I want information about vague inquire. | B9: agent | C9: agent | D9: =TRUE() -> TRUE | E9: vague-inquire | F9: vague-inquire | G9: =TRUE() -> TRUE
A10: Help with vague inquire. | B10: agent | C10: agent | D10: =TRUE() -> TRUE | E10: vague-inquire | F10: vague-inquire | G10: =TRUE() -> TRUE
A11: Question about vague inquire. | B11: agent | D11: =FALSE() -> FALSE | E11: vague-inquire | G11: =FALSE() -> FALSE
A12: I'm calling about vague inquire. | B12: agent | C12: agent | D12: =TRUE() -> TRUE | E12: vague-inquire | F12: vague-inquire | G12: =TRUE() -> TRUE
A13: I'd like information on vague inquire. | B13: agent | C13: agent | D13: =TRUE() -> TRUE | E13: vague-inquire | F13: vague-inquire | G13: =TRUE() -> TRUE
A14: I need information on vague inquire. | B14: agent | C14: agent | D14: =TRUE() -> TRUE | E14: vague-inquire | F14: vague-inquire | G14: =TRUE() -> TRUE
A15: Can you help me with vague inquire? | B15: agent | C15: agent | D15: =TRUE() -> TRUE | E15: vague-inquire | F15: vague-inquire | G15: =TRUE() -> TRUE
A16: I wanted to ask about vague inquire. | B16: agent | C16: agent | D16: =TRUE() -> TRUE | E16: vague-inquire | F16: vague-inquire | G16: =TRUE() -> TRUE
A17: This is regarding vague inquire. | B17: agent | C17: agent | D17: =TRUE() -> TRUE | E17: vague-inquire | F17: vague-inquire | G17: =TRUE() -> TRUE
A18: I'm calling regarding vague inquire. | B18: agent | C18: agent | D18: =TRUE() -> TRUE | E18: vague-inquire | F18: vague-inquire | G18: =TRUE() -> TRUE
A19: I have a question regarding vague inquire. | B19: agent | C19: agent | D19: =TRUE() -> TRUE | E19: vague-inquire | F19: vague-inquire | G19: =TRUE() -> TRUE
A20: Could you help me with vague inquire? | B20: agent | C20: agent | D20: =TRUE() -> TRUE | E20: vague-inquire | F20: vague-inquire | G20: =TRUE() -> TRUE
A21: I'm trying to get help with vague inquire. | B21: agent | C21: agent | D21: =TRUE() -> TRUE | E21: vague-inquire | F21: vague-inquire | G21: =TRUE() -> TRUE
A22: I just have a question about vague inquire. | B22: agent | C22: agent | D22: =TRUE() -> TRUE | E22: vague-inquire | F22: vague-inquire | G22: =TRUE() -> TRUE
A23: I'm calling to ask about vague inquire. | B23: agent | C23: agent | D23: =TRUE() -> TRUE | E23: vague-inquire | F23: vague-inquire | G23: =TRUE() -> TRUE
... A61: I'd appreciate help with vague inquire. | B61: agent | C61: agent | D61: =TRUE() -> TRUE | E61: vague-inquire | F61: vague-inquire | G61: =TRUE() -> TRUE
A62: HEAD INTENT ACCURACY | D62: 98.33%
A63: SUB INTENT ACCURACY | G63: 98.33%

Sheet AG_vague-membership
A1: utterance | B1: expected_head_intent | C1: detected_head_intent | D1: head_intent_match | E1: expected_sub_intent | F1: detected_sub_intent | G1: sub_intent_match | H1: error
A2: Vague membership | B2: agent | C2: agent | D2: =TRUE() -> TRUE | E2: vague-membership | F2: vague-membership | G2: =TRUE() -> TRUE
A3: I need help with vague membership. | B3: agent | C3: agent | D3: =TRUE() -> TRUE | E3: vague-membership | F3: vague-membership | G3: =TRUE() -> TRUE
A4: Calling about vague membership. | B4: agent | C4: agent | D4: =TRUE() -> TRUE | E4: vague-membership | F4: vague-membership | G4: =TRUE() -> TRUE
A5: I have a question about vague membership. | B5: agent | C5: agent | D5: =TRUE() -> TRUE | E5: vague-membership | F5: vague-membership | G5: =TRUE() -> TRUE
A6: Looking for help with vague membership. | B6: agent | C6: agent | D6: =TRUE() -> TRUE | E6: vague-membership | F6: vague-membership | G6: =TRUE() -> TRUE
A7: Calling regarding vague membership. | B7: agent | C7: agent | D7: =TRUE() -> TRUE | E7: vague-membership | F7: vague-membership | G7: =TRUE() -> TRUE
A8: Need assistance with vague membership. | B8: agent | C8: agent | D8: =TRUE() -> TRUE | E8: vague-membership | F8: vague-membership | G8: =TRUE() -> TRUE
A9: I want information about vague membership. | B9: agent | C9: agent | D9: =TRUE() -> TRUE | E9: vague-membership | F9: vague-membership | G9: =TRUE() -> TRUE
A10: Help with vague membership. | B10: agent | C10: agent | D10: =TRUE() -> TRUE | E10: vague-membership | F10: vague-membership | G10: =TRUE() -> TRUE
A11: Question about vague membership. | B11: agent | C11: agent | D11: =TRUE() -> TRUE | E11: vague-membership | F11: vague-membership | G11: =TRUE() -> TRUE
A12: I'm calling about vague membership. | B12: agent | C12: agent | D12: =TRUE() -> TRUE | E12: vague-membership | F12: vague-membership | G12: =TRUE() -> TRUE
A13: I'd like information on vague membership. | B13: agent | C13: agent | D13: =TRUE() -> TRUE | E13: vague-membership | F13: vague-membership | G13: =TRUE() -> TRUE
... A61: I'd appreciate help with vague membership. | B61: agent | C61: agent | D61: =TRUE() -> TRUE | E61: vague-membership | F61: vague-membership | G61: =TRUE() -> TRUE
A62: HEAD INTENT ACCURACY | D62: 100.0%
A63: SUB INTENT ACCURACY | G63: 100.0%

Sheet AG_vague-problem
A1: utterance | B1: expected_head_intent | C1: detected_head_intent | D1: head_intent_match | E1: expected_sub_intent | F1: detected_sub_intent | G1: sub_intent_match | H1: error
A2: Vague problem | B2: agent | C2: agent | D2: =TRUE() -> TRUE | E2: vague-problem | F2: vague-problem | G2: =TRUE() -> TRUE
A3: I need help with vague problem. | B3: agent | C3: agent | D3: =TRUE() -> TRUE | E3: vague-problem | F3: vague-problem | G3: =TRUE() -> TRUE
A4: Calling about vague problem. | B4: agent | C4: agent | D4: =TRUE() -> TRUE | E4: vague-problem | F4: vague-problem | G4: =TRUE() -> TRUE
A5: I have a question about vague problem. | B5: agent | C5: agent | D5: =TRUE() -> TRUE | E5: vague-problem | F5: vague-problem | G5: =TRUE() -> TRUE
A6: Looking for help with vague problem. | B6: agent | C6: agent | D6: =TRUE() -> TRUE | E6: vague-problem | F6: vague-problem | G6: =TRUE() -> TRUE
A7: Calling regarding vague problem. | B7: agent | C7: agent | D7: =TRUE() -> TRUE | E7: vague-problem | F7: vague-problem | G7: =TRUE() -> TRUE
A8: Need assistance with vague problem. | B8: agent | C8: agent | D8: =TRUE() -> TRUE | E8: vague-problem | F8: vague-problem | G8: =TRUE() -> TRUE
A9: I want information about vague problem. | B9: agent | C9: agent | D9: =TRUE() -> TRUE | E9: vague-problem | F9: vague-problem | G9: =TRUE() -> TRUE
A10: Help with vague problem. | B10: agent | C10: agent | D10: =TRUE() -> TRUE | E10: vague-problem | F10: vague-problem | G10: =TRUE() -> TRUE
A11: Question about vague problem. | B11: agent | D11: =FALSE() -> FALSE | E11: vague-problem | G11: =FALSE() -> FALSE
A12: I'm calling about vague problem. | B12: agent | C12: agent | D12: =TRUE() -> TRUE | E12: vague-problem | F12: vague-problem | G12: =TRUE() -> TRUE
A13: I'd like information on vague problem. | B13: agent | C13: agent | D13: =TRUE() -> TRUE | E13: vague-problem | F13: vague-problem | G13: =TRUE() -> TRUE
A14: I need information on vague problem. | B14: agent | C14: agent | D14: =TRUE() -> TRUE | E14: vague-problem | F14: vague-problem | G14: =TRUE() -> TRUE
A15: Can you help me with vague problem? | B15: agent | C15: agent | D15: =TRUE() -> TRUE | E15: vague-problem | F15: vague-problem | G15: =TRUE() -> TRUE
A16: I wanted to ask about vague problem. | B16: agent | C16: agent | D16: =TRUE() -> TRUE | E16: vague-problem | F16: vague-problem | G16: =TRUE() -> TRUE
A17: This is regarding vague problem. | B17: agent | C17: agent | D17: =TRUE() -> TRUE | E17: vague-problem | F17: vague-problem | G17: =TRUE() -> TRUE
A18: I'm calling regarding vague problem. | B18: agent | C18: agent | D18: =TRUE() -> TRUE | E18: vague-problem | F18: vague-problem | G18: =TRUE() -> TRUE
A19: I have a question regarding vague problem. | B19: agent | C19: agent | D19: =TRUE() -> TRUE | E19: vague-problem | F19: vague-problem | G19: =TRUE() -> TRUE
A20: Could you help me with vague problem? | B20: agent | C20: agent | D20: =TRUE() -> TRUE | E20: vague-problem | F20: vague-problem | G20: =TRUE() -> TRUE
A21: I'm trying to get help with vague problem. | B21: agent | C21: agent | D21: =TRUE() -> TRUE | E21: vague-problem | F21: vague-problem | G21: =TRUE() -> TRUE
A22: I just have a question about vague problem. | B22: agent | C22: agent | D22: =TRUE() -> TRUE | E22: vague-problem | F22: vague-problem | G22: =TRUE() -> TRUE
A23: I'm calling to ask about vague problem. | B23: agent | C23: agent | D23: =TRUE() -> TRUE | E23: vague-problem | F23: vague-problem | G23: =TRUE() -> TRUE
... A59: Quick question about vague problem. | B59: agent | C59: agent | D59: =TRUE() -> TRUE | E59: vague-problem | F59: vague-problem | G59: =TRUE() -> TRUE
A60: I'm not sure where to start with vague problem. | B60: agent | D60: =FALSE() -> FALSE | E60: vague-problem | G60: =FALSE() -> FALSE
A61: I'd appreciate help with vague problem. | B61: agent | C61: agent | D61: =TRUE() -> TRUE | E61: vague-problem | F61: vague-problem | G61: =TRUE() -> TRUE
A62: HEAD INTENT ACCURACY | D62: 96.67%
A63: SUB INTENT ACCURACY | G63: 96.67%

Sheet AG_vague-service
A1: utterance | B1: expected_head_intent | C1: detected_head_intent | D1: head_intent_match | E1: expected_sub_intent | F1: detected_sub_intent | G1: sub_intent_match | H1: error
A2: Vague service | B2: agent | C2: agent | D2: =TRUE() -> TRUE | E2: vague-service | F2: vague-service | G2: =TRUE() -> TRUE
A3: I need help with vague service. | B3: agent | C3: agent | D3: =TRUE() -> TRUE | E3: vague-service | F3: vague-service | G3: =TRUE() -> TRUE
A4: Calling about vague service. | B4: agent | C4: agent | D4: =TRUE() -> TRUE | E4: vague-service | F4: vague-service | G4: =TRUE() -> TRUE
A5: I have a question about vague service. | B5: agent | C5: agent | D5: =TRUE() -> TRUE | E5: vague-service | F5: vague-service | G5: =TRUE() -> TRUE
A6: Looking for help with vague service. | B6: agent | C6: agent | D6: =TRUE() -> TRUE | E6: vague-service | F6: vague-service | G6: =TRUE() -> TRUE
A7: Calling regarding vague service. | B7: agent | C7: agent | D7: =TRUE() -> TRUE | E7: vague-service | F7: vague-service | G7: =TRUE() -> TRUE
A8: Need assistance with vague service. | B8: agent | C8: agent | D8: =TRUE() -> TRUE | E8: vague-service | F8: vague-service | G8: =TRUE() -> TRUE
A9: I want information about vague service. | B9: agent | C9: agent | D9: =TRUE() -> TRUE | E9: vague-service | F9: vague-service | G9: =TRUE() -> TRUE
A10: Help with vague service. | B10: agent | C10: agent | D10: =TRUE() -> TRUE | E10: vague-service | F10: vague-service | G10: =TRUE() -> TRUE
A11: Question about vague service. | B11: agent | C11: agent | D11: =TRUE() -> TRUE | E11: vague-service | F11: vague-service | G11: =TRUE() -> TRUE
A12: I'm calling about vague service. | B12: agent | C12: agent | D12: =TRUE() -> TRUE | E12: vague-service | F12: vague-service | G12: =TRUE() -> TRUE
A13: I'd like information on vague service. | B13: agent | C13: agent | D13: =TRUE() -> TRUE | E13: vague-service | F13: vague-service | G13: =TRUE() -> TRUE
... A59: Quick question about vague service. | B59: agent | C59: agent | D59: =TRUE() -> TRUE | E59: vague-service | F59: vague-service | G59: =TRUE() -> TRUE
A60: I'm not sure where to start with vague service. | B60: agent | D60: =FALSE() -> FALSE | E60: vague-service | G60: =FALSE() -> FALSE
A61: I'd appreciate help with vague service. | B61: agent | C61: agent | D61: =TRUE() -> TRUE | E61: vague-service | F61: vague-service | G61: =TRUE() -> TRUE
A62: HEAD INTENT ACCURACY | D62: 98.33%
A63: SUB INTENT ACCURACY | G63: 98.33%

Sheet AG_vague-status
A1: utterance | B1: expected_head_intent | C1: detected_head_intent | D1: head_intent_match | E1: expected_sub_intent | F1: detected_sub_intent | G1: sub_intent_match | H1: error
A2: Vague status | B2: agent | C2: agent | D2: =TRUE() -> TRUE | E2: vague-status | F2: vague-status | G2: =TRUE() -> TRUE
A3: I need help with vague status. | B3: agent | C3: agent | D3: =TRUE() -> TRUE | E3: vague-status | F3: vague-status | G3: =TRUE() -> TRUE
A4: Calling about vague status. | B4: agent | C4: agent | D4: =TRUE() -> TRUE | E4: vague-status | F4: vague-status | G4: =TRUE() -> TRUE
A5: I have a question about vague status. | B5: agent | C5: agent | D5: =TRUE() -> TRUE | E5: vague-status | F5: vague-status | G5: =TRUE() -> TRUE
A6: Looking for help with vague status. | B6: agent | C6: agent | D6: =TRUE() -> TRUE | E6: vague-status | F6: vague-status | G6: =TRUE() -> TRUE
A7: Calling regarding vague status. | B7: agent | C7: agent | D7: =TRUE() -> TRUE | E7: vague-status | F7: vague-status | G7: =TRUE() -> TRUE
A8: Need assistance with vague status. | B8: agent | C8: agent | D8: =TRUE() -> TRUE | E8: vague-status | F8: vague-status | G8: =TRUE() -> TRUE
A9: I want information about vague status. | B9: agent | C9: agent | D9: =TRUE() -> TRUE | E9: vague-status | F9: vague-status | G9: =TRUE() -> TRUE
A10: Help with vague status. | B10: agent | C10: agent | D10: =TRUE() -> TRUE | E10: vague-status | F10: vague-status | G10: =TRUE() -> TRUE
A11: Question about vague status. | B11: agent | D11: =FALSE() -> FALSE | E11: vague-status | G11: =FALSE() -> FALSE
A12: I'm calling about vague status. | B12: agent | C12: agent | D12: =TRUE() -> TRUE | E12: vague-status | F12: vague-status | G12: =TRUE() -> TRUE
A13: I'd like information on vague status. | B13: agent | C13: agent | D13: =TRUE() -> TRUE | E13: vague-status | F13: vague-status | G13: =TRUE() -> TRUE
A14: I need information on vague status. | B14: agent | C14: agent | D14: =TRUE() -> TRUE | E14: vague-status | F14: vague-status | G14: =TRUE() -> TRUE
A15: Can you help me with vague status? | B15: agent | C15: agent | D15: =TRUE() -> TRUE | E15: vague-status | F15: vague-status | G15: =TRUE() -> TRUE
A16: I wanted to ask about vague status. | B16: agent | C16: agent | D16: =TRUE() -> TRUE | E16: vague-status | F16: vague-status | G16: =TRUE() -> TRUE
A17: This is regarding vague status. | B17: agent | C17: agent | D17: =TRUE() -> TRUE | E17: vague-status | F17: vague-status | G17: =TRUE() -> TRUE
A18: I'm calling regarding vague status. | B18: agent | C18: agent | D18: =TRUE() -> TRUE | E18: vague-status | F18: vague-status | G18: =TRUE() -> TRUE
A19: I have a question regarding vague status. | B19: agent | C19: agent | D19: =TRUE() -> TRUE | E19: vague-status | F19: vague-status | G19: =TRUE() -> TRUE
A20: Could you help me with vague status? | B20: agent | C20: agent | D20: =TRUE() -> TRUE | E20: vague-status | F20: vague-status | G20: =TRUE() -> TRUE
A21: I'm trying to get help with vague status. | B21: agent | C21: agent | D21: =TRUE() -> TRUE | E21: vague-status | F21: vague-status | G21: =TRUE() -> TRUE
A22: I just have a question about vague status. | B22: agent | C22: agent | D22: =TRUE() -> TRUE | E22: vague-status | F22: vague-status | G22: =TRUE() -> TRUE
A23: I'm calling to ask about vague status. | B23: agent | C23: agent | D23: =TRUE() -> TRUE | E23: vague-status | F23: vague-status | G23: =TRUE() -> TRUE
... A61: I'd appreciate help with vague status. | B61: agent | C61: agent | D61: =TRUE() -> TRUE | E61: vague-status | F61: vague-status | G61: =TRUE() -> TRUE
A62: HEAD INTENT ACCURACY | D62: 98.33%
A63: SUB INTENT ACCURACY | G63: 98.33%

Sheet AG_vague-tax
A1: utterance | B1: expected_head_intent | C1: detected_head_intent | D1: head_intent_match | E1: expected_sub_intent | F1: detected_sub_intent | G1: sub_intent_match | H1: error
A2: Vague tax | B2: agent | C2: agent | D2: =TRUE() -> TRUE | E2: vague-tax | F2: vague-tax | G2: =TRUE() -> TRUE
A3: I need help with vague tax. | B3: agent | C3: agent | D3: =TRUE() -> TRUE | E3: vague-tax | F3: vague-tax | G3: =TRUE() -> TRUE
A4: Calling about vague tax. | B4: agent | C4: agent | D4: =TRUE() -> TRUE | E4: vague-tax | F4: vague-tax | G4: =TRUE() -> TRUE
A5: I have a question about vague tax. | B5: agent | C5: agent | D5: =TRUE() -> TRUE | E5: vague-tax | F5: vague-tax | G5: =TRUE() -> TRUE
A6: Looking for help with vague tax. | B6: agent | C6: agent | D6: =TRUE() -> TRUE | E6: vague-tax | F6: vague-tax | G6: =TRUE() -> TRUE
A7: Calling regarding vague tax. | B7: agent | C7: agent | D7: =TRUE() -> TRUE | E7: vague-tax | F7: vague-tax | G7: =TRUE() -> TRUE
A8: Need assistance with vague tax. | B8: agent | C8: agent | D8: =TRUE() -> TRUE | E8: vague-tax | F8: vague-tax | G8: =TRUE() -> TRUE
A9: I want information about vague tax. | B9: agent | C9: agent | D9: =TRUE() -> TRUE | E9: vague-tax | F9: vague-tax | G9: =TRUE() -> TRUE
A10: Help with vague tax. | B10: agent | C10: agent | D10: =TRUE() -> TRUE | E10: vague-tax | F10: vague-tax | G10: =TRUE() -> TRUE
A11: Question about vague tax. | B11: agent | C11: agent | D11: =TRUE() -> TRUE | E11: vague-tax | F11: vague-tax | G11: =TRUE() -> TRUE
A12: I'm calling about vague tax. | B12: agent | C12: agent | D12: =TRUE() -> TRUE | E12: vague-tax | F12: vague-tax | G12: =TRUE() -> TRUE
A13: I'd like information on vague tax. | B13: agent | C13: agent | D13: =TRUE() -> TRUE | E13: vague-tax | F13: vague-tax | G13: =TRUE() -> TRUE
... A61: I'd appreciate help with vague tax. | B61: agent | C61: agent | D61: =TRUE() -> TRUE | E61: vague-tax | F61: vague-tax | G61: =TRUE() -> TRUE
A62: HEAD INTENT ACCURACY | D62: 100.0%
A63: SUB INTENT ACCURACY | G63: 100.0%

Sheet AG_vague-vague
A1: utterance | B1: expected_head_intent | C1: detected_head_intent | D1: head_intent_match | E1: expected_sub_intent | F1: detected_sub_intent | G1: sub_intent_match | H1: error
A2: Vague vague | B2: agent | C2: agent | D2: =TRUE() -> TRUE | E2: vague-vague | F2: vague-vague | G2: =TRUE() -> TRUE
A3: I need help with vague vague. | B3: agent | C3: agent | D3: =TRUE() -> TRUE | E3: vague-vague | F3: vague-vague | G3: =TRUE() -> TRUE
A4: Calling about vague vague. | B4: agent | C4: agent | D4: =TRUE() -> TRUE | E4: vague-vague | F4: vague-vague | G4: =TRUE() -> TRUE
A5: I have a question about vague vague. | B5: agent | C5: agent | D5: =TRUE() -> TRUE | E5: vague-vague | F5: vague-vague | G5: =TRUE() -> TRUE
A6: Looking for help with vague vague. | B6: agent | C6: agent | D6: =TRUE() -> TRUE | E6: vague-vague | F6: vague-vague | G6: =TRUE() -> TRUE
A7: Calling regarding vague vague. | B7: agent | C7: agent | D7: =TRUE() -> TRUE | E7: vague-vague | F7: vague-vague | G7: =TRUE() -> TRUE
A8: Need assistance with vague vague. | B8: agent | C8: agent | D8: =TRUE() -> TRUE | E8: vague-vague | F8: vague-vague | G8: =TRUE() -> TRUE
A9: I want information about vague vague. | B9: agent | C9: agent | D9: =TRUE() -> TRUE | E9: vague-vague | F9: vague-vague | G9: =TRUE() -> TRUE
A10: Help with vague vague. | B10: agent | C10: agent | D10: =TRUE() -> TRUE | E10: vague-vague | F10: vague-vague | G10: =TRUE() -> TRUE
A11: Question about vague vague. | B11: agent | C11: agent | D11: =TRUE() -> TRUE | E11: vague-vague | F11: vague-vague | G11: =TRUE() -> TRUE
A12: I'm calling about vague vague. | B12: agent | C12: agent | D12: =TRUE() -> TRUE | E12: vague-vague | F12: vague-vague | G12: =TRUE() -> TRUE
A13: I'd like information on vague vague. | B13: agent | C13: agent | D13: =TRUE() -> TRUE | E13: vague-vague | F13: vague-vague | G13: =TRUE() -> TRUE
... A58: Sorry, I have a question about vague vague. | B58: agent | C58: agent | D58: =TRUE() -> TRUE | E58: vague-vague | F58: vague-vague | G58: =TRUE() -> TRUE
A59: Quick question about vague vague. | B59: agent | D59: =FALSE() -> FALSE | E59: vague-vague | G59: =FALSE() -> FALSE
A60: I'm not sure where to start with vague vague. | B60: agent | D60: =FALSE() -> FALSE | E60: vague-vague | G60: =FALSE() -> FALSE
A61: I'd appreciate help with vague vague. | B61: agent | C61: agent | D61: =TRUE() -> TRUE | E61: vague-vague | F61: vague-vague | G61: =TRUE() -> TRUE
A62: HEAD INTENT ACCURACY | D62: 96.67%
A63: SUB INTENT ACCURACY | G63: 96.67%

Sheet BN_benefits_dental
A1: utterance | B1: expected_head_intent | C1: detected_head_intent | D1: head_intent_match | E1: expected_sub_intent | F1: detected_sub_intent | G1: sub_intent_match | H1: error
A2: Benefits dental | B2: benefits | C2: benefits | D2: =TRUE() -> TRUE | E2: benefits_dental | F2: benefits_dental | G2: =TRUE() -> TRUE
A3: Dental benefits | B3: benefits | C3: benefits | D3: =TRUE() -> TRUE | E3: benefits_dental | F3: benefits_dental | G3: =TRUE() -> TRUE
A4: I need help with benefits dental. | B4: benefits | C4: benefits | D4: =TRUE() -> TRUE | E4: benefits_dental | F4: benefits_dental | G4: =TRUE() -> TRUE
A5: I need help with dental benefits. | B5: benefits | C5: benefits | D5: =TRUE() -> TRUE | E5: benefits_dental | F5: benefits_dental | G5: =TRUE() -> TRUE
A6: Calling about benefits dental. | B6: benefits | C6: benefits | D6: =TRUE() -> TRUE | E6: benefits_dental | F6: benefits_dental | G6: =TRUE() -> TRUE
A7: Calling about dental benefits. | B7: benefits | C7: benefits | D7: =TRUE() -> TRUE | E7: benefits_dental | F7: benefits_dental | G7: =TRUE() -> TRUE
A8: I have a question about benefits dental. | B8: benefits | C8: benefits | D8: =TRUE() -> TRUE | E8: benefits_dental | F8: benefits_dental | G8: =TRUE() -> TRUE
A9: I have a question about dental benefits. | B9: benefits | C9: benefits | D9: =TRUE() -> TRUE | E9: benefits_dental | F9: benefits_dental | G9: =TRUE() -> TRUE
A10: Looking for help with benefits dental. | B10: benefits | D10: =FALSE() -> FALSE | E10: benefits_dental | F10: benefits_dental | G10: =TRUE() -> TRUE
A11: Looking for help with dental benefits. | B11: benefits | C11: benefits | D11: =TRUE() -> TRUE | E11: benefits_dental | F11: benefits_dental | G11: =TRUE() -> TRUE
A12: Calling regarding benefits dental. | B12: benefits | C12: benefits | D12: =TRUE() -> TRUE | E12: benefits_dental | F12: benefits_dental | G12: =TRUE() -> TRUE
A13: Calling regarding dental benefits. | B13: benefits | C13: benefits | D13: =TRUE() -> TRUE | E13: benefits_dental | F13: benefits_dental | G13: =TRUE() -> TRUE
A14: Need assistance with benefits dental. | B14: benefits | C14: benefits | D14: =TRUE() -> TRUE | E14: benefits_dental | F14: benefits_dental | G14: =TRUE() -> TRUE
A15: Need assistance with dental benefits. | B15: benefits | C15: benefits | D15: =TRUE() -> TRUE | E15: benefits_dental | F15: benefits_dental | G15: =TRUE() -> TRUE
A16: I want information about benefits dental. | B16: benefits | C16: benefits | D16: =TRUE() -> TRUE | E16: benefits_dental | F16: benefits_dental | G16: =TRUE() -> TRUE
A17: I want information about dental benefits. | B17: benefits | C17: benefits | D17: =TRUE() -> TRUE | E17: benefits_dental | F17: benefits_dental | G17: =TRUE() -> TRUE
A18: Help with benefits dental. | B18: benefits | C18: benefits | D18: =TRUE() -> TRUE | E18: benefits_dental | F18: benefits_dental | G18: =TRUE() -> TRUE
A19: Help with dental benefits. | B19: benefits | C19: benefits | D19: =TRUE() -> TRUE | E19: benefits_dental | F19: benefits_dental | G19: =TRUE() -> TRUE
A20: Question about benefits dental. | B20: benefits | C20: benefits | D20: =TRUE() -> TRUE | E20: benefits_dental | F20: benefits_dental | G20: =TRUE() -> TRUE
A21: Question about dental benefits. | B21: benefits | C21: benefits | D21: =TRUE() -> TRUE | E21: benefits_dental | F21: benefits_dental | G21: =TRUE() -> TRUE
A22: I'm calling about benefits dental. | B22: benefits | C22: benefits | D22: =TRUE() -> TRUE | E22: benefits_dental | F22: benefits_dental | G22: =TRUE() -> TRUE
... A61: I want to talk to someone about dental benefits. | B61: benefits | C61: benefits | D61: =TRUE() -> TRUE | E61: benefits_dental | F61: benefits_dental | G61: =TRUE() -> TRUE
A62: HEAD INTENT ACCURACY | D62: 98.33%
A63: SUB INTENT ACCURACY | G63: 100.0%

Sheet BN_benefits_medical
A1: utterance | B1: expected_head_intent | C1: detected_head_intent | D1: head_intent_match | E1: expected_sub_intent | F1: detected_sub_intent | G1: sub_intent_match | H1: error
A2: Medical benefits | B2: benefits | C2: benefits | D2: =TRUE() -> TRUE | E2: benefits_medical | F2: benefits_medical | G2: =TRUE() -> TRUE
A3: Benefits medical | B3: benefits | C3: benefits | D3: =TRUE() -> TRUE | E3: benefits_medical | F3: benefits_medical | G3: =TRUE() -> TRUE
A4: I need help with medical benefits. | B4: benefits | C4: benefits | D4: =TRUE() -> TRUE | E4: benefits_medical | F4: benefits_medical | G4: =TRUE() -> TRUE
A5: I need help with benefits medical. | B5: benefits | C5: benefits | D5: =TRUE() -> TRUE | E5: benefits_medical | F5: benefits_medical | G5: =TRUE() -> TRUE
A6: Calling about medical benefits. | B6: benefits | C6: benefits | D6: =TRUE() -> TRUE | E6: benefits_medical | F6: benefits_medical | G6: =TRUE() -> TRUE
A7: Calling about benefits medical. | B7: benefits | C7: benefits | D7: =TRUE() -> TRUE | E7: benefits_medical | F7: benefits_medical | G7: =TRUE() -> TRUE
A8: I have a question about medical benefits. | B8: benefits | C8: benefits | D8: =TRUE() -> TRUE | E8: benefits_medical | F8: benefits_medical | G8: =TRUE() -> TRUE
A9: I have a question about benefits medical. | B9: benefits | C9: benefits | D9: =TRUE() -> TRUE | E9: benefits_medical | F9: benefits_medical | G9: =TRUE() -> TRUE
A10: Looking for help with medical benefits. | B10: benefits | C10: benefits | D10: =TRUE() -> TRUE | E10: benefits_medical | F10: benefits_medical | G10: =TRUE() -> TRUE
A11: Looking for help with benefits medical. | B11: benefits | C11: benefits | D11: =TRUE() -> TRUE | E11: benefits_medical | F11: benefits_medical | G11: =TRUE() -> TRUE
A12: Calling regarding medical benefits. | B12: benefits | C12: benefits | D12: =TRUE() -> TRUE | E12: benefits_medical | F12: benefits_medical | G12: =TRUE() -> TRUE
A13: Calling regarding benefits medical. | B13: benefits | C13: benefits | D13: =TRUE() -> TRUE | E13: benefits_medical | F13: benefits_medical | G13: =TRUE() -> TRUE
... A61: I want to talk to someone about benefits medical. | B61: benefits | C61: benefits | D61: =TRUE() -> TRUE | E61: benefits_medical | F61: benefits_medical | G61: =TRUE() -> TRUE
A62: HEAD INTENT ACCURACY | D62: 100.0%
A63: SUB INTENT ACCURACY | G63: 100.0%

Sheet BN_benefits_vision
A1: utterance | B1: expected_head_intent | C1: detected_head_intent | D1: head_intent_match | E1: expected_sub_intent | F1: detected_sub_intent | G1: sub_intent_match | H1: error
A2: Benefits vision | B2: benefits | C2: benefits | D2: =TRUE() -> TRUE | E2: benefits_vision | F2: benefits_vision | G2: =TRUE() -> TRUE
A3: Vision benefits | B3: benefits | D3: =FALSE() -> FALSE | E3: benefits_vision | F3: benefits_vision | G3: =TRUE() -> TRUE
A4: I need help with benefits vision. | B4: benefits | C4: benefits | D4: =TRUE() -> TRUE | E4: benefits_vision | F4: benefits_vision | G4: =TRUE() -> TRUE
A5: I need help with vision benefits. | B5: benefits | C5: benefits | D5: =TRUE() -> TRUE | E5: benefits_vision | F5: benefits_vision | G5: =TRUE() -> TRUE
A6: Calling about benefits vision. | B6: benefits | C6: benefits | D6: =TRUE() -> TRUE | E6: benefits_vision | F6: benefits_vision | G6: =TRUE() -> TRUE
A7: Calling about vision benefits. | B7: benefits | C7: benefits | D7: =TRUE() -> TRUE | E7: benefits_vision | F7: benefits_vision | G7: =TRUE() -> TRUE
A8: I have a question about benefits vision. | B8: benefits | C8: benefits | D8: =TRUE() -> TRUE | E8: benefits_vision | F8: benefits_vision | G8: =TRUE() -> TRUE
A9: I have a question about vision benefits. | B9: benefits | C9: benefits | D9: =TRUE() -> TRUE | E9: benefits_vision | F9: benefits_vision | G9: =TRUE() -> TRUE
A10: Looking for help with benefits vision. | B10: benefits | C10: benefits | D10: =TRUE() -> TRUE | E10: benefits_vision | F10: benefits_vision | G10: =TRUE() -> TRUE
A11: Looking for help with vision benefits. | B11: benefits | C11: benefits | D11: =TRUE() -> TRUE | E11: benefits_vision | F11: benefits_vision | G11: =TRUE() -> TRUE
A12: Calling regarding benefits vision. | B12: benefits | C12: benefits | D12: =TRUE() -> TRUE | E12: benefits_vision | F12: benefits_vision | G12: =TRUE() -> TRUE
A13: Calling regarding vision benefits. | B13: benefits | C13: benefits | D13: =TRUE() -> TRUE | E13: benefits_vision | F13: benefits_vision | G13: =TRUE() -> TRUE
A14: Need assistance with benefits vision. | B14: benefits | D14: =FALSE() -> FALSE | E14: benefits_vision | F14: benefits_vision | G14: =TRUE() -> TRUE
A15: Need assistance with vision benefits. | B15: benefits | D15: =FALSE() -> FALSE | E15: benefits_vision | F15: benefits_vision | G15: =TRUE() -> TRUE
A16: I want information about benefits vision. | B16: benefits | C16: benefits | D16: =TRUE() -> TRUE | E16: benefits_vision | F16: benefits_vision | G16: =TRUE() -> TRUE
A17: I want information about vision benefits. | B17: benefits | C17: benefits | D17: =TRUE() -> TRUE | E17: benefits_vision | F17: benefits_vision | G17: =TRUE() -> TRUE
A18: Help with benefits vision. | B18: benefits | C18: benefits | D18: =TRUE() -> TRUE | E18: benefits_vision | F18: benefits_vision | G18: =TRUE() -> TRUE
A19: Help with vision benefits. | B19: benefits | C19: benefits | D19: =TRUE() -> TRUE | E19: benefits_vision | F19: benefits_vision | G19: =TRUE() -> TRUE
A20: Question about benefits vision. | B20: benefits | C20: benefits | D20: =TRUE() -> TRUE | E20: benefits_vision | F20: benefits_vision | G20: =TRUE() -> TRUE
A21: Question about vision benefits. | B21: benefits | C21: benefits | D21: =TRUE() -> TRUE | E21: benefits_vision | F21: benefits_vision | G21: =TRUE() -> TRUE
A22: I'm calling about benefits vision. | B22: benefits | C22: benefits | D22: =TRUE() -> TRUE | E22: benefits_vision | F22: benefits_vision | G22: =TRUE() -> TRUE
A23: I'm calling about vision benefits. | B23: benefits | C23: benefits | D23: =TRUE() -> TRUE | E23: benefits_vision | F23: benefits_vision | G23: =TRUE() -> TRUE
A24: I'd like information on benefits vision. | B24: benefits | C24: benefits | D24: =TRUE() -> TRUE | E24: benefits_vision | F24: benefits_vision | G24: =TRUE() -> TRUE
A25: I'd like information on vision benefits. | B25: benefits | C25: benefits | D25: =TRUE() -> TRUE | E25: benefits_vision | F25: benefits_vision | G25: =TRUE() -> TRUE
A26: I need information on benefits vision. | B26: benefits | C26: benefits | D26: =TRUE() -> TRUE | E26: benefits_vision | F26: benefits_vision | G26: =TRUE() -> TRUE
A27: I need information on vision benefits. | B27: benefits | C27: benefits | D27: =TRUE() -> TRUE | E27: benefits_vision | F27: benefits_vision | G27: =TRUE() -> TRUE
... A61: I want to talk to someone about vision benefits. | B61: benefits | C61: benefits | D61: =TRUE() -> TRUE | E61: benefits_vision | F61: benefits_vision | G61: =TRUE() -> TRUE
A62: HEAD INTENT ACCURACY | D62: 95.0%
A63: SUB INTENT ACCURACY | G63: 100.0%

Sheet BN_claims_life
A1: utterance | B1: expected_head_intent | C1: detected_head_intent | D1: head_intent_match | E1: expected_sub_intent | F1: detected_sub_intent | G1: sub_intent_match | H1: error
A2: Claims life | B2: benefits | D2: =FALSE() -> FALSE | E2: claims_life | F2: claims_life | G2: =TRUE() -> TRUE
A3: Life claims | B3: benefits | C3: benefits | D3: =TRUE() -> TRUE | E3: claims_life | F3: claims_life | G3: =TRUE() -> TRUE
A4: I need help with claims life. | B4: benefits | C4: benefits | D4: =TRUE() -> TRUE | E4: claims_life | F4: claims_life | G4: =TRUE() -> TRUE
A5: I need help with life claims. | B5: benefits | C5: benefits | D5: =TRUE() -> TRUE | E5: claims_life | F5: claims_life | G5: =TRUE() -> TRUE
A6: Calling about claims life. | B6: benefits | D6: =FALSE() -> FALSE | E6: claims_life | F6: claims_life | G6: =TRUE() -> TRUE
A7: Calling about life claims. | B7: benefits | C7: benefits | D7: =TRUE() -> TRUE | E7: claims_life | F7: claims_life | G7: =TRUE() -> TRUE
A8: I have a question about claims life. | B8: benefits | C8: benefits | D8: =TRUE() -> TRUE | E8: claims_life | F8: claims_life | G8: =TRUE() -> TRUE
A9: I have a question about life claims. | B9: benefits | C9: benefits | D9: =TRUE() -> TRUE | E9: claims_life | F9: claims_life | G9: =TRUE() -> TRUE
A10: Looking for help with claims life. | B10: benefits | C10: benefits | D10: =TRUE() -> TRUE | E10: claims_life | F10: claims_life | G10: =TRUE() -> TRUE
A11: Looking for help with life claims. | B11: benefits | C11: benefits | D11: =TRUE() -> TRUE | E11: claims_life | F11: claims_life | G11: =TRUE() -> TRUE
A12: Calling regarding claims life. | B12: benefits | D12: =FALSE() -> FALSE | E12: claims_life | F12: claims_life | G12: =TRUE() -> TRUE
A13: Calling regarding life claims. | B13: benefits | C13: benefits | D13: =TRUE() -> TRUE | E13: claims_life | F13: claims_life | G13: =TRUE() -> TRUE
A14: Need assistance with claims life. | B14: benefits | D14: =FALSE() -> FALSE | E14: claims_life | F14: claims_life | G14: =TRUE() -> TRUE
A15: Need assistance with life claims. | B15: benefits | D15: =FALSE() -> FALSE | E15: claims_life | F15: claims_life | G15: =TRUE() -> TRUE
A16: I want information about claims life. | B16: benefits | C16: benefits | D16: =TRUE() -> TRUE | E16: claims_life | F16: claims_life | G16: =TRUE() -> TRUE
A17: I want information about life claims. | B17: benefits | C17: benefits | D17: =TRUE() -> TRUE | E17: claims_life | F17: claims_life | G17: =TRUE() -> TRUE
A18: Help with claims life. | B18: benefits | C18: benefits | D18: =TRUE() -> TRUE | E18: claims_life | F18: claims_life | G18: =TRUE() -> TRUE
A19: Help with life claims. | B19: benefits | C19: benefits | D19: =TRUE() -> TRUE | E19: claims_life | F19: claims_life | G19: =TRUE() -> TRUE
A20: Question about claims life. | B20: benefits | C20: benefits | D20: =TRUE() -> TRUE | E20: claims_life | F20: claims_life | G20: =TRUE() -> TRUE
A21: Question about life claims. | B21: benefits | C21: benefits | D21: =TRUE() -> TRUE | E21: claims_life | F21: claims_life | G21: =TRUE() -> TRUE
A22: I'm calling about claims life. | B22: benefits | C22: benefits | D22: =TRUE() -> TRUE | E22: claims_life | F22: claims_life | G22: =TRUE() -> TRUE
A23: I'm calling about life claims. | B23: benefits | C23: benefits | D23: =TRUE() -> TRUE | E23: claims_life | F23: claims_life | G23: =TRUE() -> TRUE
A24: I'd like information on claims life. | B24: benefits | C24: benefits | D24: =TRUE() -> TRUE | E24: claims_life | F24: claims_life | G24: =TRUE() -> TRUE
A25: I'd like information on life claims. | B25: benefits | D25: =FALSE() -> FALSE | E25: claims_life | F25: claims_life | G25: =TRUE() -> TRUE
A26: I need information on claims life. | B26: benefits | C26: benefits | D26: =TRUE() -> TRUE | E26: claims_life | F26: claims_life | G26: =TRUE() -> TRUE
A27: I need information on life claims. | B27: benefits | C27: benefits | D27: =TRUE() -> TRUE | E27: claims_life | F27: claims_life | G27: =TRUE() -> TRUE
A28: Can you help me with claims life? | B28: benefits | D28: =FALSE() -> FALSE | E28: claims_life | F28: claims_life | G28: =TRUE() -> TRUE
A29: Can you help me with life claims? | B29: benefits | C29: benefits | D29: =TRUE() -> TRUE | E29: claims_life | F29: claims_life | G29: =TRUE() -> TRUE
A30: I wanted to ask about claims life. | B30: benefits | C30: benefits | D30: =TRUE() -> TRUE | E30: claims_life | F30: claims_life | G30: =TRUE() -> TRUE
A31: I wanted to ask about life claims. | B31: benefits | C31: benefits | D31: =TRUE() -> TRUE | E31: claims_life | F31: claims_life | G31: =TRUE() -> TRUE
A32: This is regarding claims life. | B32: benefits | C32: benefits | D32: =TRUE() -> TRUE | E32: claims_life | F32: claims_life | G32: =TRUE() -> TRUE
A33: This is regarding life claims. | B33: benefits | C33: benefits | D33: =TRUE() -> TRUE | E33: claims_life | F33: claims_life | G33: =TRUE() -> TRUE
A34: I'm calling regarding claims life. | B34: benefits | C34: benefits | D34: =TRUE() -> TRUE | E34: claims_life | F34: claims_life | G34: =TRUE() -> TRUE
A35: I'm calling regarding life claims. | B35: benefits | C35: benefits | D35: =TRUE() -> TRUE | E35: claims_life | F35: claims_life | G35: =TRUE() -> TRUE
A36: I have a question regarding claims life. | B36: benefits | C36: benefits | D36: =TRUE() -> TRUE | E36: claims_life | F36: claims_life | G36: =TRUE() -> TRUE
A37: I have a question regarding life claims. | B37: benefits | C37: benefits | D37: =TRUE() -> TRUE | E37: claims_life | F37: claims_life | G37: =TRUE() -> TRUE
A38: Could you help me with claims life? | B38: benefits | C38: benefits | D38: =TRUE() -> TRUE | E38: claims_life | F38: claims_life | G38: =TRUE() -> TRUE
A39: Could you help me with life claims? | B39: benefits | C39: benefits | D39: =TRUE() -> TRUE | E39: claims_life | F39: claims_life | G39: =TRUE() -> TRUE
A40: I'm trying to get help with claims life. | B40: benefits | C40: benefits | D40: =TRUE() -> TRUE | E40: claims_life | F40: claims_life | G40: =TRUE() -> TRUE
... A61: I want to talk to someone about life claims. | B61: benefits | C61: benefits | D61: =TRUE() -> TRUE | E61: claims_life | F61: claims_life | G61: =TRUE() -> TRUE
A62: HEAD INTENT ACCURACY | D62: 88.33%
A63: SUB INTENT ACCURACY | G63: 100.0%

Sheet BN_eligibility_life
A1: utterance | B1: expected_head_intent | C1: detected_head_intent | D1: head_intent_match | E1: expected_sub_intent | F1: detected_sub_intent | G1: sub_intent_match | H1: error
A2: Eligibility_life life | B2: benefits | D2: =FALSE() -> FALSE | E2: eligibility_life | F2: eligibility_life | G2: =TRUE() -> TRUE
A3: Life eligibility_life | B3: benefits | D3: =FALSE() -> FALSE | E3: eligibility_life | F3: eligibility_life | G3: =TRUE() -> TRUE
A4: I need help with eligibility_life life. | B4: benefits | D4: =FALSE() -> FALSE | E4: eligibility_life | F4: eligibility_life | G4: =TRUE() -> TRUE
A5: I need help with life eligibility_life. | B5: benefits | C5: benefits | D5: =TRUE() -> TRUE | E5: eligibility_life | F5: eligibility_life | G5: =TRUE() -> TRUE
A6: Calling about eligibility_life life. | B6: benefits | C6: benefits | D6: =TRUE() -> TRUE | E6: eligibility_life | F6: eligibility_life | G6: =TRUE() -> TRUE
A7: Calling about life eligibility_life. | B7: benefits | C7: benefits | D7: =TRUE() -> TRUE | E7: eligibility_life | F7: eligibility_life | G7: =TRUE() -> TRUE
A8: I have a question about eligibility_life life. | B8: benefits | C8: benefits | D8: =TRUE() -> TRUE | E8: eligibility_life | F8: eligibility_life | G8: =TRUE() -> TRUE
A9: I have a question about life eligibility_life. | B9: benefits | C9: benefits | D9: =TRUE() -> TRUE | E9: eligibility_life | F9: eligibility_life | G9: =TRUE() -> TRUE
A10: Looking for help with eligibility_life life. | B10: benefits | D10: =FALSE() -> FALSE | E10: eligibility_life | F10: eligibility_life | G10: =TRUE() -> TRUE
A11: Looking for help with life eligibility_life. | B11: benefits | C11: benefits | D11: =TRUE() -> TRUE | E11: eligibility_life | F11: eligibility_life | G11: =TRUE() -> TRUE
A12: Calling regarding eligibility_life life. | B12: benefits | C12: benefits | D12: =TRUE() -> TRUE | E12: eligibility_life | F12: eligibility_life | G12: =TRUE() -> TRUE
A13: Calling regarding life eligibility_life. | B13: benefits | C13: benefits | D13: =TRUE() -> TRUE | E13: eligibility_life | F13: eligibility_life | G13: =TRUE() -> TRUE
A14: Need assistance with eligibility_life life. | B14: benefits | D14: =FALSE() -> FALSE | E14: eligibility_life | F14: eligibility_life | G14: =TRUE() -> TRUE
A15: Need assistance with life eligibility_life. | B15: benefits | D15: =FALSE() -> FALSE | E15: eligibility_life | F15: eligibility_life | G15: =TRUE() -> TRUE
A16: I want information about eligibility_life life. | B16: benefits | C16: benefits | D16: =TRUE() -> TRUE | E16: eligibility_life | F16: eligibility_life | G16: =TRUE() -> TRUE
A17: I want information about life eligibility_life. | B17: benefits | C17: benefits | D17: =TRUE() -> TRUE | E17: eligibility_life | F17: eligibility_life | G17: =TRUE() -> TRUE
A18: Help with eligibility_life life. | B18: benefits | C18: benefits | D18: =TRUE() -> TRUE | E18: eligibility_life | F18: eligibility_life | G18: =TRUE() -> TRUE
A19: Help with life eligibility_life. | B19: benefits | C19: benefits | D19: =TRUE() -> TRUE | E19: eligibility_life | F19: eligibility_life | G19: =TRUE() -> TRUE
A20: Question about eligibility_life life. | B20: benefits | C20: benefits | D20: =TRUE() -> TRUE | E20: eligibility_life | F20: eligibility_life | G20: =TRUE() -> TRUE
A21: Question about life eligibility_life. | B21: benefits | C21: benefits | D21: =TRUE() -> TRUE | E21: eligibility_life | F21: eligibility_life | G21: =TRUE() -> TRUE
A22: I'm calling about eligibility_life life. | B22: benefits | C22: benefits | D22: =TRUE() -> TRUE | E22: eligibility_life | F22: eligibility_life | G22: =TRUE() -> TRUE
A23: I'm calling about life eligibility_life. | B23: benefits | C23: benefits | D23: =TRUE() -> TRUE | E23: eligibility_life | F23: eligibility_life | G23: =TRUE() -> TRUE
A24: I'd like information on eligibility_life life. | B24: benefits | C24: benefits | D24: =TRUE() -> TRUE | E24: eligibility_life | F24: eligibility_life | G24: =TRUE() -> TRUE
A25: I'd like information on life eligibility_life. | B25: benefits | D25: =FALSE() -> FALSE | E25: eligibility_life | F25: eligibility_life | G25: =TRUE() -> TRUE
A26: I need information on eligibility_life life. | B26: benefits | C26: benefits | D26: =TRUE() -> TRUE | E26: eligibility_life | F26: eligibility_life | G26: =TRUE() -> TRUE
A27: I need information on life eligibility_life. | B27: benefits | C27: benefits | D27: =TRUE() -> TRUE | E27: eligibility_life | F27: eligibility_life | G27: =TRUE() -> TRUE
A28: Can you help me with eligibility_life life? | B28: benefits | C28: benefits | D28: =TRUE() -> TRUE | E28: eligibility_life | F28: eligibility_life | G28: =TRUE() -> TRUE
A29: Can you help me with life eligibility_life? | B29: benefits | C29: benefits | D29: =TRUE() -> TRUE | E29: eligibility_life | F29: eligibility_life | G29: =TRUE() -> TRUE
A30: I wanted to ask about eligibility_life life. | B30: benefits | C30: benefits | D30: =TRUE() -> TRUE | E30: eligibility_life | F30: eligibility_life | G30: =TRUE() -> TRUE
A31: I wanted to ask about life eligibility_life. | B31: benefits | C31: benefits | D31: =TRUE() -> TRUE | E31: eligibility_life | F31: eligibility_life | G31: =TRUE() -> TRUE
A32: This is regarding eligibility_life life. | B32: benefits | C32: benefits | D32: =TRUE() -> TRUE | E32: eligibility_life | F32: eligibility_life | G32: =TRUE() -> TRUE
A33: This is regarding life eligibility_life. | B33: benefits | C33: benefits | D33: =TRUE() -> TRUE | E33: eligibility_life | F33: eligibility_life | G33: =TRUE() -> TRUE
A34: I'm calling regarding eligibility_life life. | B34: benefits | C34: benefits | D34: =TRUE() -> TRUE | E34: eligibility_life | F34: eligibility_life | G34: =TRUE() -> TRUE
A35: I'm calling regarding life eligibility_life. | B35: benefits | C35: benefits | D35: =TRUE() -> TRUE | E35: eligibility_life | F35: eligibility_life | G35: =TRUE() -> TRUE
A36: I have a question regarding eligibility_life life. | B36: benefits | C36: benefits | D36: =TRUE() -> TRUE | E36: eligibility_life | F36: eligibility_life | G36: =TRUE() -> TRUE
A37: I have a question regarding life eligibility_life. | B37: benefits | C37: benefits | D37: =TRUE() -> TRUE | E37: eligibility_life | F37: eligibility_life | G37: =TRUE() -> TRUE
... A46: Reaching out about eligibility_life life. | B46: benefits | C46: benefits | D46: =TRUE() -> TRUE | E46: eligibility_life | F46: eligibility_life | G46: =TRUE() -> TRUE
A47: Reaching out about life eligibility_life. | B47: benefits | D47: =FALSE() -> FALSE | E47: eligibility_life | G47: =FALSE() -> FALSE | H47: 500 Internal error encountered.
A48: I'd like to ask about eligibility_life life. | B48: benefits | C48: benefits | D48: =TRUE() -> TRUE | E48: eligibility_life | F48: eligibility_life | G48: =TRUE() -> TRUE
A49: I'd like to ask about life eligibility_life. | B49: benefits | C49: benefits | D49: =TRUE() -> TRUE | E49: eligibility_life | F49: eligibility_life | G49: =TRUE() -> TRUE
A50: Wanted to check on eligibility_life life. | B50: benefits | C50: benefits | D50: =TRUE() -> TRUE | E50: eligibility_life | F50: eligibility_life | G50: =TRUE() -> TRUE
A51: Wanted to check on life eligibility_life. | B51: benefits | C51: benefits | D51: =TRUE() -> TRUE | E51: eligibility_life | F51: eligibility_life | G51: =TRUE() -> TRUE
A52: Hoping to get some help with eligibility_life life. | B52: benefits | C52: benefits | D52: =TRUE() -> TRUE | E52: eligibility_life | F52: eligibility_life | G52: =TRUE() -> TRUE
A53: Hoping to get some help with life eligibility_life. | B53: benefits | C53: benefits | D53: =TRUE() -> TRUE | E53: eligibility_life | F53: eligibility_life | G53: =TRUE() -> TRUE
A54: I was hoping you could help me with eligibility_life life. | B54: benefits | C54: benefits | D54: =TRUE() -> TRUE | E54: eligibility_life | F54: eligibility_life | G54: =TRUE() -> TRUE
A55: I was hoping you could help me with life eligibility_life. | B55: benefits | C55: benefits | D55: =TRUE() -> TRUE | E55: eligibility_life | F55: eligibility_life | G55: =TRUE() -> TRUE
A56: My question is about eligibility_life life. | B56: benefits | C56: benefits | D56: =TRUE() -> TRUE | E56: eligibility_life | F56: eligibility_life | G56: =TRUE() -> TRUE
A57: My question is about life eligibility_life. | B57: benefits | C57: benefits | D57: =TRUE() -> TRUE | E57: eligibility_life | F57: eligibility_life | G57: =TRUE() -> TRUE
A58: I'm following up about eligibility_life life. | B58: benefits | C58: benefits | D58: =TRUE() -> TRUE | E58: eligibility_life | F58: eligibility_life | G58: =TRUE() -> TRUE
A59: I'm following up about life eligibility_life. | B59: benefits | C59: benefits | D59: =TRUE() -> TRUE | E59: eligibility_life | F59: eligibility_life | G59: =TRUE() -> TRUE
... A61: I want to talk to someone about life eligibility_life. | B61: benefits | C61: benefits | D61: =TRUE() -> TRUE | E61: eligibility_life | F61: eligibility_life | G61: =TRUE() -> TRUE
A62: HEAD INTENT ACCURACY | D62: 86.67%
A63: SUB INTENT ACCURACY | G63: 98.33%

Sheet BN_inquire-benefits
A1: utterance | B1: expected_head_intent | C1: detected_head_intent | D1: head_intent_match | E1: expected_sub_intent | F1: detected_sub_intent | G1: sub_intent_match | H1: error
A2: Benefit information | B2: benefits | C2: benefits | D2: =TRUE() -> TRUE | E2: inquire-benefits | F2: inquire-benefits | G2: =TRUE() -> TRUE
A3: Benefit question | B3: benefits | C3: benefits | D3: =TRUE() -> TRUE | E3: inquire-benefits | F3: inquire-benefits | G3: =TRUE() -> TRUE
A4: Check benefits | B4: benefits | C4: benefits | D4: =TRUE() -> TRUE | E4: inquire-benefits | F4: inquire-benefits | G4: =TRUE() -> TRUE
A5: Review benefits | B5: benefits | C5: benefits | D5: =TRUE() -> TRUE | E5: inquire-benefits | F5: inquire-benefits | G5: =TRUE() -> TRUE
A6: Medical benefits | B6: benefits | C6: benefits | D6: =TRUE() -> TRUE | E6: inquire-benefits | F6: benefits_medical | G6: =FALSE() -> FALSE
A7: Benefits inquiry | B7: benefits | C7: benefits | D7: =TRUE() -> TRUE | E7: inquire-benefits | F7: inquire-benefits | G7: =TRUE() -> TRUE
A8: Coverage question | B8: benefits | C8: benefits | D8: =TRUE() -> TRUE | E8: inquire-benefits | F8: inquire-benefits | G8: =TRUE() -> TRUE
A9: Verify coverage | B9: benefits | C9: benefits | D9: =TRUE() -> TRUE | E9: inquire-benefits | F9: inquire-benefits | G9: =TRUE() -> TRUE
A10: Preventive care coverage | B10: benefits | C10: benefits | D10: =TRUE() -> TRUE | E10: inquire-benefits | F10: inquire-benefits | G10: =TRUE() -> TRUE
A11: Flu shot coverage | B11: benefits | C11: benefits | D11: =TRUE() -> TRUE | E11: inquire-benefits | F11: inquire-benefits | G11: =TRUE() -> TRUE
A12: Healthcare service coverage | B12: benefits | C12: benefits | D12: =TRUE() -> TRUE | E12: inquire-benefits | F12: inquire-benefits | G12: =TRUE() -> TRUE
A13: I need help with benefit information. | B13: benefits | C13: benefits | D13: =TRUE() -> TRUE | E13: inquire-benefits | F13: inquire-benefits | G13: =TRUE() -> TRUE
A14: I need help with benefit question. | B14: benefits | C14: benefits | D14: =TRUE() -> TRUE | E14: inquire-benefits | F14: inquire-benefits | G14: =TRUE() -> TRUE
A15: I need help with check benefits. | B15: benefits | C15: benefits | D15: =TRUE() -> TRUE | E15: inquire-benefits | F15: inquire-benefits | G15: =TRUE() -> TRUE
A16: I need help with review benefits. | B16: benefits | C16: benefits | D16: =TRUE() -> TRUE | E16: inquire-benefits | F16: inquire-benefits | G16: =TRUE() -> TRUE
A17: I need help with medical benefits. | B17: benefits | C17: benefits | D17: =TRUE() -> TRUE | E17: inquire-benefits | F17: benefits_medical | G17: =FALSE() -> FALSE
A18: I need help with benefits inquiry. | B18: benefits | C18: benefits | D18: =TRUE() -> TRUE | E18: inquire-benefits | F18: inquire-benefits | G18: =TRUE() -> TRUE
A19: I need help with coverage question. | B19: benefits | C19: benefits | D19: =TRUE() -> TRUE | E19: inquire-benefits | F19: inquire-benefits | G19: =TRUE() -> TRUE
A20: I need help with verify coverage. | B20: benefits | C20: benefits | D20: =TRUE() -> TRUE | E20: inquire-benefits | F20: inquire-benefits | G20: =TRUE() -> TRUE
A21: I need help with preventive care coverage. | B21: benefits | C21: benefits | D21: =TRUE() -> TRUE | E21: inquire-benefits | F21: inquire-benefits | G21: =TRUE() -> TRUE
A22: I need help with flu shot coverage. | B22: benefits | C22: benefits | D22: =TRUE() -> TRUE | E22: inquire-benefits | F22: inquire-benefits | G22: =TRUE() -> TRUE
A23: I need help with healthcare service coverage. | B23: benefits | C23: benefits | D23: =TRUE() -> TRUE | E23: inquire-benefits | F23: inquire-benefits | G23: =TRUE() -> TRUE
A24: Calling about benefit information. | B24: benefits | C24: benefits | D24: =TRUE() -> TRUE | E24: inquire-benefits | F24: inquire-benefits | G24: =TRUE() -> TRUE
A25: Calling about benefit question. | B25: benefits | C25: benefits | D25: =TRUE() -> TRUE | E25: inquire-benefits | F25: inquire-benefits | G25: =TRUE() -> TRUE
A26: Calling about check benefits. | B26: benefits | C26: benefits | D26: =TRUE() -> TRUE | E26: inquire-benefits | F26: inquire-benefits | G26: =TRUE() -> TRUE
A27: Calling about review benefits. | B27: benefits | C27: benefits | D27: =TRUE() -> TRUE | E27: inquire-benefits | F27: inquire-benefits | G27: =TRUE() -> TRUE
A28: Calling about medical benefits. | B28: benefits | C28: benefits | D28: =TRUE() -> TRUE | E28: inquire-benefits | F28: benefits_medical | G28: =FALSE() -> FALSE
A29: Calling about benefits inquiry. | B29: benefits | C29: benefits | D29: =TRUE() -> TRUE | E29: inquire-benefits | F29: inquire-benefits | G29: =TRUE() -> TRUE
A30: Calling about coverage question. | B30: benefits | C30: benefits | D30: =TRUE() -> TRUE | E30: inquire-benefits | F30: inquire-benefits | G30: =TRUE() -> TRUE
A31: Calling about verify coverage. | B31: benefits | D31: =FALSE() -> FALSE | E31: inquire-benefits | G31: =FALSE() -> FALSE
A32: Calling about preventive care coverage. | B32: benefits | C32: benefits | D32: =TRUE() -> TRUE | E32: inquire-benefits | F32: inquire-benefits | G32: =TRUE() -> TRUE
A33: Calling about flu shot coverage. | B33: benefits | C33: benefits | D33: =TRUE() -> TRUE | E33: inquire-benefits | F33: inquire-benefits | G33: =TRUE() -> TRUE
A34: Calling about healthcare service coverage. | B34: benefits | C34: benefits | D34: =TRUE() -> TRUE | E34: inquire-benefits | F34: inquire-benefits | G34: =TRUE() -> TRUE
A35: I have a question about benefit information. | B35: benefits | C35: benefits | D35: =TRUE() -> TRUE | E35: inquire-benefits | F35: inquire-benefits | G35: =TRUE() -> TRUE
A36: I have a question about benefit question. | B36: benefits | C36: benefits | D36: =TRUE() -> TRUE | E36: inquire-benefits | F36: inquire-benefits | G36: =TRUE() -> TRUE
A37: I have a question about check benefits. | B37: benefits | C37: benefits | D37: =TRUE() -> TRUE | E37: inquire-benefits | F37: inquire-benefits | G37: =TRUE() -> TRUE
A38: I have a question about review benefits. | B38: benefits | C38: benefits | D38: =TRUE() -> TRUE | E38: inquire-benefits | F38: inquire-benefits | G38: =TRUE() -> TRUE
A39: I have a question about medical benefits. | B39: benefits | C39: benefits | D39: =TRUE() -> TRUE | E39: inquire-benefits | F39: benefits_medical | G39: =FALSE() -> FALSE
A40: I have a question about benefits inquiry. | B40: benefits | C40: benefits | D40: =TRUE() -> TRUE | E40: inquire-benefits | F40: inquire-benefits | G40: =TRUE() -> TRUE
A41: I have a question about coverage question. | B41: benefits | C41: benefits | D41: =TRUE() -> TRUE | E41: inquire-benefits | F41: inquire-benefits | G41: =TRUE() -> TRUE
A42: I have a question about verify coverage. | B42: benefits | C42: benefits | D42: =TRUE() -> TRUE | E42: inquire-benefits | F42: inquire-benefits | G42: =TRUE() -> TRUE
A43: I have a question about preventive care coverage. | B43: benefits | C43: benefits | D43: =TRUE() -> TRUE | E43: inquire-benefits | F43: inquire-benefits | G43: =TRUE() -> TRUE
A44: I have a question about flu shot coverage. | B44: benefits | C44: benefits | D44: =TRUE() -> TRUE | E44: inquire-benefits | F44: inquire-benefits | G44: =TRUE() -> TRUE
A45: I have a question about healthcare service coverage. | B45: benefits | C45: benefits | D45: =TRUE() -> TRUE | E45: inquire-benefits | F45: inquire-benefits | G45: =TRUE() -> TRUE
A46: Looking for help with benefit information. | B46: benefits | C46: benefits | D46: =TRUE() -> TRUE | E46: inquire-benefits | F46: inquire-benefits | G46: =TRUE() -> TRUE
A47: Looking for help with benefit question. | B47: benefits | C47: benefits | D47: =TRUE() -> TRUE | E47: inquire-benefits | F47: inquire-benefits | G47: =TRUE() -> TRUE
A48: Looking for help with check benefits. | B48: benefits | C48: benefits | D48: =TRUE() -> TRUE | E48: inquire-benefits | F48: inquire-benefits | G48: =TRUE() -> TRUE
A49: Looking for help with review benefits. | B49: benefits | C49: benefits | D49: =TRUE() -> TRUE | E49: inquire-benefits | F49: inquire-benefits | G49: =TRUE() -> TRUE
A50: Looking for help with medical benefits. | B50: benefits | C50: benefits | D50: =TRUE() -> TRUE | E50: inquire-benefits | F50: benefits_medical | G50: =FALSE() -> FALSE
A51: Looking for help with benefits inquiry. | B51: benefits | C51: benefits | D51: =TRUE() -> TRUE | E51: inquire-benefits | F51: inquire-benefits | G51: =TRUE() -> TRUE
A52: Looking for help with coverage question. | B52: benefits | C52: benefits | D52: =TRUE() -> TRUE | E52: inquire-benefits | F52: inquire-benefits | G52: =TRUE() -> TRUE
A53: Looking for help with verify coverage. | B53: benefits | C53: benefits | D53: =TRUE() -> TRUE | E53: inquire-benefits | F53: inquire-benefits | G53: =TRUE() -> TRUE
A54: Looking for help with preventive care coverage. | B54: benefits | C54: benefits | D54: =TRUE() -> TRUE | E54: inquire-benefits | F54: inquire-benefits | G54: =TRUE() -> TRUE
A55: Looking for help with flu shot coverage. | B55: benefits | C55: benefits | D55: =TRUE() -> TRUE | E55: inquire-benefits | F55: inquire-benefits | G55: =TRUE() -> TRUE
A56: Looking for help with healthcare service coverage. | B56: benefits | C56: benefits | D56: =TRUE() -> TRUE | E56: inquire-benefits | F56: inquire-benefits | G56: =TRUE() -> TRUE
A57: Calling regarding benefit information. | B57: benefits | C57: benefits | D57: =TRUE() -> TRUE | E57: inquire-benefits | F57: inquire-benefits | G57: =TRUE() -> TRUE
A58: Calling regarding benefit question. | B58: benefits | C58: benefits | D58: =TRUE() -> TRUE | E58: inquire-benefits | F58: inquire-benefits | G58: =TRUE() -> TRUE
A59: Calling regarding check benefits. | B59: benefits | C59: benefits | D59: =TRUE() -> TRUE | E59: inquire-benefits | F59: inquire-benefits | G59: =TRUE() -> TRUE
A60: Calling regarding review benefits. | B60: benefits | C60: benefits | D60: =TRUE() -> TRUE | E60: inquire-benefits | F60: inquire-benefits | G60: =TRUE() -> TRUE
A61: Calling regarding medical benefits. | B61: benefits | C61: benefits | D61: =TRUE() -> TRUE | E61: inquire-benefits | F61: benefits_medical | G61: =FALSE() -> FALSE
A62: HEAD INTENT ACCURACY | D62: 98.33%
A63: SUB INTENT ACCURACY | G63: 88.33%

Sheet BN_inquire-deductible
A1: utterance | B1: expected_head_intent | C1: detected_head_intent | D1: head_intent_match | E1: expected_sub_intent | F1: detected_sub_intent | G1: sub_intent_match | H1: error
A2: How much deductible has been met on two members | B2: benefits | D2: =FALSE() -> FALSE | E2: inquire-deductible | F2: inquire-deductible | G2: =TRUE() -> TRUE
A3: Deductible amounts for the members | B3: benefits | D3: =FALSE() -> FALSE | E3: inquire-deductible | F3: inquire-deductible | G3: =TRUE() -> TRUE
A4: Explanation on a drug deductible | B4: benefits | C4: benefits | D4: =TRUE() -> TRUE | E4: inquire-deductible | F4: inquire-deductible | G4: =TRUE() -> TRUE
A5: Speak with a representative regarding deductible credits | B5: benefits | D5: =FALSE() -> FALSE | E5: inquire-deductible | F5: inquire-deductible | G5: =TRUE() -> TRUE
A6: Insurance deductible | B6: benefits | D6: =FALSE() -> FALSE | E6: inquire-deductible | F6: inquire-deductible | G6: =TRUE() -> TRUE
A7: Misinformation about deductible | B7: benefits | C7: benefits | D7: =TRUE() -> TRUE | E7: inquire-deductible | F7: inquire-deductible | G7: =TRUE() -> TRUE
A8: Plant deductible for existing group | B8: benefits | D8: =FALSE() -> FALSE | E8: inquire-deductible | F8: inquire-deductible | G8: =TRUE() -> TRUE
A9: Report of contributions | B9: benefits | C9: benefits | D9: =TRUE() -> TRUE | E9: inquire-deductible | F9: inquire-deductible | G9: =TRUE() -> TRUE
A10: About getting deductible applied | B10: benefits | C10: benefits | D10: =TRUE() -> TRUE | E10: inquire-deductible | F10: inquire-deductible | G10: =TRUE() -> TRUE
A11: Update deductible deductible amount | B11: benefits | C11: benefits | D11: =TRUE() -> TRUE | E11: inquire-deductible | F11: inquire-deductible | G11: =TRUE() -> TRUE
A12: Wish to speak to someone about deductible on our plan | B12: benefits | D12: =FALSE() -> FALSE | E12: inquire-deductible | F12: inquire-deductible | G12: =TRUE() -> TRUE
A13: I need help with how much deductible has been met on two members. | B13: benefits | D13: =FALSE() -> FALSE | E13: inquire-deductible | F13: inquire-deductible | G13: =TRUE() -> TRUE
A14: I need help with deductible amounts for the members. | B14: benefits | D14: =FALSE() -> FALSE | E14: inquire-deductible | F14: inquire-deductible | G14: =TRUE() -> TRUE
A15: I need help with explanation on a drug deductible. | B15: benefits | C15: benefits | D15: =TRUE() -> TRUE | E15: inquire-deductible | F15: inquire-deductible | G15: =TRUE() -> TRUE
A16: I need help with speak with a representative regarding deductible credits. | B16: benefits | C16: benefits | D16: =TRUE() -> TRUE | E16: inquire-deductible | F16: inquire-deductible | G16: =TRUE() -> TRUE
A17: I need help with insurance deductible. | B17: benefits | D17: =FALSE() -> FALSE | E17: inquire-deductible | F17: inquire-deductible | G17: =TRUE() -> TRUE
A18: I need help with misinformation about deductible. | B18: benefits | C18: benefits | D18: =TRUE() -> TRUE | E18: inquire-deductible | F18: inquire-deductible | G18: =TRUE() -> TRUE
A19: I need help with plant deductible for existing group. | B19: benefits | C19: benefits | D19: =TRUE() -> TRUE | E19: inquire-deductible | F19: inquire-deductible | G19: =TRUE() -> TRUE
A20: I need help with deductible. | B20: benefits | C20: benefits | D20: =TRUE() -> TRUE | E20: inquire-deductible | F20: inquire-deductible | G20: =TRUE() -> TRUE
A21: I need help with report of contributions. | B21: benefits | C21: benefits | D21: =TRUE() -> TRUE | E21: inquire-deductible | F21: inquire-deductible | G21: =TRUE() -> TRUE
A22: I need help with update deductible deductible amount. | B22: benefits | C22: benefits | D22: =TRUE() -> TRUE | E22: inquire-deductible | F22: inquire-deductible | G22: =TRUE() -> TRUE
A23: I need help with wish to speak to someone about deductible on our plan. | B23: benefits | D23: =FALSE() -> FALSE | E23: inquire-deductible | F23: inquire-deductible | G23: =TRUE() -> TRUE
A24: Calling about how much deductible has been met on two members. | B24: benefits | D24: =FALSE() -> FALSE | E24: inquire-deductible | F24: inquire-deductible | G24: =TRUE() -> TRUE
A25: Calling about deductible amounts for the members. | B25: benefits | D25: =FALSE() -> FALSE | E25: inquire-deductible | F25: inquire-deductible | G25: =TRUE() -> TRUE
A26: Calling about explanation on a drug deductible. | B26: benefits | D26: =FALSE() -> FALSE | E26: inquire-deductible | F26: inquire-deductible | G26: =TRUE() -> TRUE
A27: Calling about speak with a representative regarding deductible credits. | B27: benefits | D27: =FALSE() -> FALSE | E27: inquire-deductible | F27: inquire-deductible | G27: =TRUE() -> TRUE
A28: Calling about insurance deductible. | B28: benefits | C28: benefits | D28: =TRUE() -> TRUE | E28: inquire-deductible | F28: inquire-deductible | G28: =TRUE() -> TRUE
A29: Calling about misinformation about deductible. | B29: benefits | C29: benefits | D29: =TRUE() -> TRUE | E29: inquire-deductible | F29: inquire-deductible | G29: =TRUE() -> TRUE
A30: Calling about plant deductible for existing group. | B30: benefits | D30: =FALSE() -> FALSE | E30: inquire-deductible | F30: inquire-deductible | G30: =TRUE() -> TRUE
A31: Calling about deductible. | B31: benefits | D31: =FALSE() -> FALSE | E31: inquire-deductible | F31: inquire-deductible | G31: =TRUE() -> TRUE
A32: Calling about report of contributions. | B32: benefits | D32: =FALSE() -> FALSE | E32: inquire-deductible | F32: inquire-deductible | G32: =TRUE() -> TRUE
A33: Calling about update deductible deductible amount. | B33: benefits | D33: =FALSE() -> FALSE | E33: inquire-deductible | F33: inquire-deductible | G33: =TRUE() -> TRUE
A34: Calling about wish to speak to someone about deductible on our plan. | B34: benefits | C34: benefits | D34: =TRUE() -> TRUE | E34: inquire-deductible | F34: inquire-deductible | G34: =TRUE() -> TRUE
A35: I have a question about how much deductible has been met on two members. | B35: benefits | D35: =FALSE() -> FALSE | E35: inquire-deductible | F35: inquire-deductible | G35: =TRUE() -> TRUE
A36: I have a question about deductible amounts for the members. | B36: benefits | D36: =FALSE() -> FALSE | E36: inquire-deductible | F36: inquire-deductible | G36: =TRUE() -> TRUE
A37: I have a question about explanation on a drug deductible. | B37: benefits | D37: =FALSE() -> FALSE | E37: inquire-deductible | F37: inquire-deductible | G37: =TRUE() -> TRUE
A38: I have a question about speak with a representative regarding deductible credits. | B38: benefits | D38: =FALSE() -> FALSE | E38: inquire-deductible | F38: inquire-deductible | G38: =TRUE() -> TRUE
A39: I have a question about insurance deductible. | B39: benefits | D39: =FALSE() -> FALSE | E39: inquire-deductible | F39: inquire-deductible | G39: =TRUE() -> TRUE
A40: I have a question about misinformation about deductible. | B40: benefits | D40: =FALSE() -> FALSE | E40: inquire-deductible | F40: inquire-deductible | G40: =TRUE() -> TRUE
A41: I have a question about plant deductible for existing group. | B41: benefits | D41: =FALSE() -> FALSE | E41: inquire-deductible | F41: inquire-deductible | G41: =TRUE() -> TRUE
A42: I have a question about deductible. | B42: benefits | C42: benefits | D42: =TRUE() -> TRUE | E42: inquire-deductible | F42: inquire-deductible | G42: =TRUE() -> TRUE
A43: I have a question about report of contributions. | B43: benefits | D43: =FALSE() -> FALSE | E43: inquire-deductible | F43: inquire-deductible | G43: =TRUE() -> TRUE
A44: I have a question about update deductible deductible amount. | B44: benefits | C44: benefits | D44: =TRUE() -> TRUE | E44: inquire-deductible | F44: inquire-deductible | G44: =TRUE() -> TRUE
A45: I have a question about wish to speak to someone about deductible on our plan. | B45: benefits | C45: benefits | D45: =TRUE() -> TRUE | E45: inquire-deductible | F45: inquire-deductible | G45: =TRUE() -> TRUE
A46: Looking for help with how much deductible has been met on two members. | B46: benefits | D46: =FALSE() -> FALSE | E46: inquire-deductible | F46: inquire-deductible | G46: =TRUE() -> TRUE
A47: Looking for help with deductible amounts for the members. | B47: benefits | D47: =FALSE() -> FALSE | E47: inquire-deductible | F47: inquire-deductible | G47: =TRUE() -> TRUE
A48: Looking for help with explanation on a drug deductible. | B48: benefits | C48: benefits | D48: =TRUE() -> TRUE | E48: inquire-deductible | F48: inquire-deductible | G48: =TRUE() -> TRUE
A49: Looking for help with speak with a representative regarding deductible credits. | B49: benefits | D49: =FALSE() -> FALSE | E49: inquire-deductible | F49: inquire-deductible | G49: =TRUE() -> TRUE
A50: Looking for help with insurance deductible. | B50: benefits | C50: benefits | D50: =TRUE() -> TRUE | E50: inquire-deductible | F50: inquire-deductible | G50: =TRUE() -> TRUE
A51: Looking for help with misinformation about deductible. | B51: benefits | D51: =FALSE() -> FALSE | E51: inquire-deductible | F51: inquire-deductible | G51: =TRUE() -> TRUE
A52: Looking for help with plant deductible for existing group. | B52: benefits | C52: benefits | D52: =TRUE() -> TRUE | E52: inquire-deductible | F52: inquire-deductible | G52: =TRUE() -> TRUE
A53: Looking for help with deductible. | B53: benefits | C53: benefits | D53: =TRUE() -> TRUE | E53: inquire-deductible | F53: inquire-deductible | G53: =TRUE() -> TRUE
A54: Looking for help with report of contributions. | B54: benefits | D54: =FALSE() -> FALSE | E54: inquire-deductible | F54: inquire-deductible | G54: =TRUE() -> TRUE
A55: Looking for help with update deductible deductible amount. | B55: benefits | D55: =FALSE() -> FALSE | E55: inquire-deductible | F55: inquire-deductible | G55: =TRUE() -> TRUE
A56: Looking for help with wish to speak to someone about deductible on our plan. | B56: benefits | C56: benefits | D56: =TRUE() -> TRUE | E56: inquire-deductible | F56: inquire-deductible | G56: =TRUE() -> TRUE
A57: Calling regarding how much deductible has been met on two members. | B57: benefits | D57: =FALSE() -> FALSE | E57: inquire-deductible | F57: inquire-deductible | G57: =TRUE() -> TRUE
A58: Calling regarding deductible amounts for the members. | B58: benefits | C58: benefits | D58: =TRUE() -> TRUE | E58: inquire-deductible | F58: inquire-deductible | G58: =TRUE() -> TRUE
A59: Calling regarding explanation on a drug deductible. | B59: benefits | D59: =FALSE() -> FALSE | E59: inquire-deductible | F59: inquire-deductible | G59: =TRUE() -> TRUE
A60: Calling regarding speak with a representative regarding deductible credits. | B60: benefits | D60: =FALSE() -> FALSE | E60: inquire-deductible | F60: inquire-deductible | G60: =TRUE() -> TRUE
A61: Calling regarding insurance deductible. | B61: benefits | C61: benefits | D61: =TRUE() -> TRUE | E61: inquire-deductible | F61: inquire-deductible | G61: =TRUE() -> TRUE
A62: HEAD INTENT ACCURACY | D62: 41.67%
A63: SUB INTENT ACCURACY | G63: 100.0%

Sheet BN_inquire-employee_benefits
A1: utterance | B1: expected_head_intent | C1: detected_head_intent | D1: head_intent_match | E1: expected_sub_intent | F1: detected_sub_intent | G1: sub_intent_match | H1: error
A2: Employee group benefits | B2: benefits | C2: benefits | D2: =TRUE() -> TRUE | E2: inquire-employee_benefits | F2: inquire-employee_benefits | G2: =TRUE() -> TRUE
A3: An employee's benefit | B3: benefits | D3: =FALSE() -> FALSE | E3: inquire-employee_benefits | F3: inquire-employee_benefits | G3: =TRUE() -> TRUE
A4: Check employee benefits | B4: benefits | C4: benefits | D4: =TRUE() -> TRUE | E4: inquire-employee_benefits | F4: inquire-employee_benefits | G4: =TRUE() -> TRUE
A5: Checking on employee benefits | B5: benefits | C5: benefits | D5: =TRUE() -> TRUE | E5: inquire-employee_benefits | F5: inquire-employee_benefits | G5: =TRUE() -> TRUE
A6: Employee benefit check | B6: benefits | C6: benefits | D6: =TRUE() -> TRUE | E6: inquire-employee_benefits | F6: inquire-employee_benefits | G6: =TRUE() -> TRUE
A7: Employee benefits verification | B7: benefits | C7: benefits | D7: =TRUE() -> TRUE | E7: inquire-employee_benefits | F7: inquire-employee_benefits | G7: =TRUE() -> TRUE
A8: Group life insurance benefit | B8: benefits | C8: benefits | D8: =TRUE() -> TRUE | E8: inquire-employee_benefits | F8: inquire-employee_benefits | G8: =TRUE() -> TRUE
A9: Group plan benefits | B9: benefits | C9: benefits | D9: =TRUE() -> TRUE | E9: inquire-employee_benefits | F9: inquire-employee_benefits | G9: =TRUE() -> TRUE
A10: I need help with employee group benefits. | B10: benefits | C10: benefits | D10: =TRUE() -> TRUE | E10: inquire-employee_benefits | F10: inquire-employee_benefits | G10: =TRUE() -> TRUE
A11: I need help with check employee benefits. | B11: benefits | C11: benefits | D11: =TRUE() -> TRUE | E11: inquire-employee_benefits | F11: inquire-employee_benefits | G11: =TRUE() -> TRUE
A12: I need help with checking on employee benefits. | B12: benefits | C12: benefits | D12: =TRUE() -> TRUE | E12: inquire-employee_benefits | F12: inquire-employee_benefits | G12: =TRUE() -> TRUE
A13: I need help with employee benefit check. | B13: benefits | C13: benefits | D13: =TRUE() -> TRUE | E13: inquire-employee_benefits | F13: inquire-employee_benefits | G13: =TRUE() -> TRUE
A14: I need help with employee benefits verification. | B14: benefits | C14: benefits | D14: =TRUE() -> TRUE | E14: inquire-employee_benefits | F14: inquire-employee_benefits | G14: =TRUE() -> TRUE
A15: I need help with group life insurance benefit. | B15: benefits | C15: benefits | D15: =TRUE() -> TRUE | E15: inquire-employee_benefits | F15: inquire-employee_benefits | G15: =TRUE() -> TRUE
... A47: Need assistance with checking on employee benefits. | B47: benefits | C47: benefits | D47: =TRUE() -> TRUE | E47: inquire-employee_benefits | F47: inquire-employee_benefits | G47: =TRUE() -> TRUE
A48: Need assistance with employee benefit check. | B48: benefits | D48: =FALSE() -> FALSE | E48: inquire-employee_benefits | F48: inquire-employee_benefits | G48: =TRUE() -> TRUE
A49: Need assistance with employee benefits verification. | B49: benefits | C49: benefits | D49: =TRUE() -> TRUE | E49: inquire-employee_benefits | F49: inquire-employee_benefits | G49: =TRUE() -> TRUE
A50: Need assistance with group life insurance benefit. | B50: benefits | C50: benefits | D50: =TRUE() -> TRUE | E50: inquire-employee_benefits | F50: inquire-employee_benefits | G50: =TRUE() -> TRUE
A51: Need assistance with group plan benefits. | B51: benefits | C51: benefits | D51: =TRUE() -> TRUE | E51: inquire-employee_benefits | F51: inquire-employee_benefits | G51: =TRUE() -> TRUE
A52: I want information about employee group benefits. | B52: benefits | C52: benefits | D52: =TRUE() -> TRUE | E52: inquire-employee_benefits | F52: inquire-employee_benefits | G52: =TRUE() -> TRUE
A53: I want information about check employee benefits. | B53: benefits | C53: benefits | D53: =TRUE() -> TRUE | E53: inquire-employee_benefits | F53: inquire-employee_benefits | G53: =TRUE() -> TRUE
A54: I want information about checking on employee benefits. | B54: benefits | C54: benefits | D54: =TRUE() -> TRUE | E54: inquire-employee_benefits | F54: inquire-employee_benefits | G54: =TRUE() -> TRUE
A55: I want information about employee benefit check. | B55: benefits | C55: benefits | D55: =TRUE() -> TRUE | E55: inquire-employee_benefits | F55: inquire-employee_benefits | G55: =TRUE() -> TRUE
A56: I want information about employee benefits verification. | B56: benefits | C56: benefits | D56: =TRUE() -> TRUE | E56: inquire-employee_benefits | F56: inquire-employee_benefits | G56: =TRUE() -> TRUE
A57: I want information about group life insurance benefit. | B57: benefits | C57: benefits | D57: =TRUE() -> TRUE | E57: inquire-employee_benefits | F57: inquire-employee_benefits | G57: =TRUE() -> TRUE
A58: I want information about group plan benefits. | B58: benefits | C58: benefits | D58: =TRUE() -> TRUE | E58: inquire-employee_benefits | F58: inquire-employee_benefits | G58: =TRUE() -> TRUE
A59: Help with employee group benefits. | B59: benefits | C59: benefits | D59: =TRUE() -> TRUE | E59: inquire-employee_benefits | F59: inquire-employee_benefits | G59: =TRUE() -> TRUE
A60: Help with check employee benefits. | B60: benefits | C60: benefits | D60: =TRUE() -> TRUE | E60: inquire-employee_benefits | F60: inquire-employee_benefits | G60: =TRUE() -> TRUE
A61: Help with checking on employee benefits. | B61: benefits | C61: benefits | D61: =TRUE() -> TRUE | E61: inquire-employee_benefits | F61: inquire-employee_benefits | G61: =TRUE() -> TRUE
A62: HEAD INTENT ACCURACY | D62: 96.67%
A63: SUB INTENT ACCURACY | G63: 100.0%

Sheet BN_inquire-summary
A1: utterance | B1: expected_head_intent | C1: detected_head_intent | D1: head_intent_match | E1: expected_sub_intent | F1: detected_sub_intent | G1: sub_intent_match | H1: error
A2: Benefit summary | B2: benefits | C2: benefits | D2: =TRUE() -> TRUE | E2: inquire-summary | F2: inquire-summary | G2: =TRUE() -> TRUE
